Workbook

Sheet Trade_Log
A1: trade_id | B1: account_id | C1: system | D1: underlying_symbol | E1: asset_type | F1: direction | G1: open_date | H1: open_datetime | I1: qty | J1: entry_price | K1: stop_price | L1: risk_amount | M1: total_commissions | N1: status | O1: realized_pnl | P1: realized_R | Q1: schwab_transaction_id | R1: notes
A2: 2384 | B2: AJZ6348 | C2: TOS_Import | D2: TCBX | E2: stock | F2: long | G2: 2024-10-29 | I2: 40 | J2: 33.4175 | L2: 20.05 | M2: 0.05 | N2: closed | O2: -35.5 | P2: -1.77
A3: 2383 | B3: AJZ6348 | C3: TOS_Import | D3: AMSC | E3: stock | F3: long | G3: 2024-11-04 | I3: 65 | J3: 28.1133 | L3: 27.41 | M3: 0.07 | N3: closed | O3: 360.54 | P3: 13.15
A4: 2381 | B4: AJZ6348 | C4: TOS_Import | D4: ANGI | E4: stock | F4: long | G4: 2024-11-05 | I4: 775 | J4: 2.47 | L4: 28.71 | M4: 0.17 | N4: closed | O4: -333.25 | P4: -11.61
A5: 2382 | B5: AJZ6348 | C5: TOS_Import | D5: CF | E5: stock | F5: long | G5: 2024-11-05 | I5: 20 | J5: 85.89 | L5: 25.77 | M5: 0.05 | N5: closed | O5: -39.8 | P5: -1.54
A6: 2380 | B6: AJZ6348 | C6: TOS_Import | D6: EDN | E6: stock | F6: long | G6: 2024-11-06 | I6: 50 | J6: 32.39 | L6: 24.29 | M6: 0.05 | N6: closed | O6: -143.5 | P6: -5.91
A7: 2379 | B7: AJZ6348 | C7: TOS_Import | D7: TILE | E7: stock | F7: long | G7: 2024-11-07 | I7: 50 | J7: 24.4999 | L7: 18.37 | M7: 0.05 | N7: closed | O7: 62.5 | P7: 3.4
A8: 2374 | B8: AJZ6348 | C8: TOS_Import | D8: MCB | E8: stock | F8: long | G8: 2024-11-12 | I8: 30 | J8: 64.5607 | L8: 29.05 | M8: 0.05 | N8: closed | O8: -137.42 | P8: -4.73
A9: 2375 | B9: AJZ6348 | C9: TOS_Import | D9: DYNF | E9: stock | F9: long | G9: 2024-11-12 | I9: 35 | J9: 52.2001 | L9: 27.41 | M9: 0.06 | N9: closed | O9: 0 | P9: 0
A10: 2376 | B10: AJZ6348 | C10: TOS_Import | D10: INSG | E10: stock | F10: long | G10: 2024-11-12 | I10: 95 | J10: 18.63 | L10: 26.55 | M10: 0.07 | N10: closed | O10: -37.05 | P10: -1.4
A11: 2377 | B11: AJZ6348 | C11: TOS_Import | D11: CSV | E11: stock | F11: long | G11: 2024-11-12 | I11: 440 | J11: 40.0577 | L11: 264.38 | M11: 0.56 | N11: closed | O11: -171.79 | P11: -0.65
A12: 2378 | B12: AJZ6348 | C12: TOS_Import | D12: CEIX | E12: stock | F12: long | G12: 2024-11-12 | I12: 15 | J12: 128.66 | L12: 28.95 | M12: 0.05 | N12: closed | O12: -39.3 | P12: -1.36
A13: 2373 | B13: AJZ6348 | C13: TOS_Import | D13: FTNT | E13: stock | F13: long | G13: 2024-11-13 | I13: 20 | J13: 98.08 | L13: 29.42 | M13: 0.05 | N13: closed | O13: -129.6 | P13: -4.41
... A24: 2361 | B24: AJZ6348 | C24: TOS_Import | D24: RAND | E24: stock | F24: long | G24: 2024-12-12 | I24: 80 | J24: 22.62 | L24: 27.14 | M24: 0.06 | N24: closed | O24: -381.73 | P24: -14.07
A25: 2362 | B25: AJZ6348 | C25: TOS_Import | D25: SMLR | E25: stock | F25: long | G25: 2024-12-12 | I25: 20 | J25: 70.4178 | L25: 21.13 | M25: 0 | N25: closed | O25: 0 | P25: 0 | R25: Administratively closed 2026-09-02 -- pre-2026 legacy trade, no relevance to 2026 strategy tracking (Tony's directive).
A26: 2360 | B26: AJZ6348 | C26: TOS_Import | D26: SOUN | E26: stock | F26: long | G26: 2024-12-13 | I26: 100 | J26: 16.082 | L26: 24.12 | M26: 0.07 | N26: closed | O26: 275.55 | P26: 11.42
A27: 2359 | B27: AJZ6348 | C27: TOS_Import | D27: C | E27: call | F27: long | G27: 2024-12-16 | I27: 2 | J27: 4.89 | L27: 14.67 | M27: 2.67 | N27: closed | O27: -218 | P27: -14.86
A28: 2357 | B28: AJZ6348 | C28: TOS_Import | D28: SMLR | E28: stock | F28: long | G28: 2024-12-17 | I28: 20 | J28: 74.87 | L28: 22.46 | M28: 0.08 | N28: closed | O28: -143 | P28: -6.37
A29: 2358 | B29: AJZ6348 | C29: TOS_Import | D29: SUPV | E29: stock | F29: long | G29: 2024-12-17 | I29: 100 | J29: 15.9277 | L29: 23.89 | M29: 0.07 | N29: closed | O29: 201.23 | P29: 8.42
A30: 2356 | B30: AJZ6348 | C30: TOS_Import | D30: XMTR | E30: stock | F30: long | G30: 2024-12-18 | I30: 30 | J30: 40.32 | L30: 18.14 | M30: 0.03 | N30: closed | O30: 30 | P30: 1.65
A31: 2355 | B31: AJZ6348 | C31: TOS_Import | D31: FEIM | E31: stock | F31: long | G31: 2024-12-19 | I31: 85 | J31: 18.54 | L31: 23.64 | M31: 0.05 | N31: closed | O31: 6.8 | P31: 0.29
A32: 2354 | B32: AJZ6348 | C32: TOS_Import | D32: QNTM | E32: stock | F32: long | G32: 2024-12-20 | I32: 300 | J32: 3.81 | L32: 17.14 | M32: 0.08 | N32: closed | O32: -243 | P32: -14.18
A33: 2351 | B33: AJZ6348 | C33: TOS_Import | D33: SOUN | E33: call | F33: long | G33: 2024-12-23 | I33: 3 | J33: 3.4 | L33: 15.3 | M33: 4.01 | N33: closed | O33: 258 | P33: 16.86
A34: 2352 | B34: AJZ6348 | C34: TOS_Import | D34: SOUN | E34: stock | F34: long | G34: 2024-12-23 | I34: 50 | J34: 21 | L34: 15.75 | M34: 0.04 | N34: closed | O34: -49.62 | P34: -3.15
A35: 2353 | B35: AJZ6348 | C35: TOS_Import | D35: SCHW | E35: call | F35: long | G35: 2024-12-23 | I35: 2 | J35: 3.14 | L35: 9.42 | M35: 2.66 | N35: closed | O35: -126 | P35: -13.38
A36: 2350 | B36: AJZ6348 | C36: TOS_Import | D36: QUBT | E36: stock | F36: long | G36: 2024-12-27 | I36: 80 | J36: 21.4922 | L36: 25.79 | M36: 0.05 | N36: closed | O36: -269.42 | P36: -10.45
A37: 2347 | B37: AJZ6348 | C37: TOS_Import | D37: ARQQ | E37: stock | F37: long | G37: 2024-12-30 | I37: 30 | J37: 44.98 | L37: 20.24 | M37: 0.02 | N37: closed | O37: -479.4 | P37: -23.69
... A56: 2333 | B56: AJZ6348 | C56: TOS_Import | D56: GRRR | E56: stock | F56: long | G56: 2025-01-27 | I56: 60 | J56: 14.11 | L56: 12.7 | M56: 0.03 | N56: closed | O56: -78 | P56: -6.14
A57: 2326 | B57: AJZ6348 | C57: TOS_Import | D57: OKLO | E57: stock | F57: long | G57: 2025-01-28 | I57: 40 | J57: 33.9999 | L57: 20.4 | M57: 0 | N57: closed | O57: 0 | P57: 0 | R57: Administratively closed 2026-09-02 -- pre-2026 legacy trade, no relevance to 2026 strategy tracking (Tony's directive).
A58: 2327 | B58: AJZ6348 | C58: TOS_Import | D58: HOOD | E58: call | F58: long | G58: 2025-01-28 | I58: 2 | J58: 5.6 | L58: 16.8 | M58: 2.69 | N58: closed | O58: 480 | P58: 28.57
A59: 2328 | B59: AJZ6348 | C59: TOS_Import | D59: BAC | E59: call | F59: long | G59: 2025-01-28 | I59: 5 | J59: 1.02 | L59: 7.65 | M59: 6.62 | N59: closed | O59: -100 | P59: -13.07
A60: 2329 | B60: AJZ6348 | C60: TOS_Import | D60: ETON | E60: stock | F60: long | G60: 2025-01-28 | I60: 70 | J60: 17.52 | L60: 18.4 | M60: 0.04 | N60: closed | O60: -59.85 | P60: -3.25
A61: 2322 | B61: AJZ6348 | C61: TOS_Import | D61: OKLO | E61: stock | F61: long | G61: 2025-01-29 | I61: 40 | J61: 34.925 | L61: 20.95 | M61: 0.12 | N61: closed | O61: 1114.8 | P61: 53.21
A62: 2323 | B62: AJZ6348 | C62: TOS_Import | D62: DCTH | E62: stock | F62: long | G62: 2025-01-29 | I62: 80 | J62: 15.51 | L62: 18.61 | M62: 0.04 | N62: closed | O62: -39.2 | P62: -2.11
A63: 2324 | B63: AJZ6348 | C63: TOS_Import | D63: BOWFF | E63: stock | F63: long | G63: 2025-01-29 | I63: 30 | J63: 42.7646 | L63: 19.24 | M63: 13.94 | N63: closed | O63: 102.09 | P63: 5.31
A64: 2325 | B64: AJZ6348 | C64: TOS_Import | D64: YELP | E64: stock | F64: long | G64: 2025-01-29 | I64: 30 | J64: 41.265 | L64: 18.57 | M64: 0.04 | N64: closed | O64: -58.72 | P64: -3.16
A65: 2321 | B65: AJZ6348 | C65: TOS_Import | D65: CCSI | E65: stock | F65: long | G65: 2025-01-30 | I65: 40 | J65: 30.17 | L65: 18.1 | M65: 0.03 | N65: closed | O65: -118.76 | P65: -6.56
A66: 2319 | B66: AJZ6348 | C66: TOS_Import | D66: AG | E66: stock | F66: long | G66: 2025-01-31 | I66: 200 | J66: 5.7988 | L66: 17.4 | M66: 0.06 | N66: closed | O66: -39.76 | P66: -2.29
A67: 2320 | B67: AJZ6348 | C67: TOS_Import | D67: DSP | E67: stock | F67: long | G67: 2025-01-31 | I67: 55 | J67: 22.4 | L67: 18.48 | M67: 0.05 | N67: closed | O67: 32.18 | P67: 1.74
A68: 2318 | B68: AJZ6348 | C68: TOS_Import | D68: CAH | E68: call | F68: long | G68: 2025-02-03 | I68: 1 | J68: 9.7 | L68: 14.55 | M68: 1.35 | N68: closed | O68: 250 | P68: 17.18
A69: 2315 | B69: AJZ6348 | C69: TOS_Import | D69: IBM | E69: call | F69: long | G69: 2025-02-04 | I69: 1 | J69: 13.05 | L69: 19.57 | M69: 1.35 | N69: closed | O69: -250 | P69: -12.77
... A103: 2281 | B103: AJZ6348 | C103: TOS_Import | D103: DOCU | E103: call | F103: long | G103: 2025-02-24 | I103: 1 | J103: 7.69 | L103: 11.54 | M103: 2.02 | N103: closed | O103: 52 | P103: 4.51
A104: 2282 | B104: AJZ6348 | C104: TOS_Import | D104: DOCU | E104: call | F104: long | G104: 2025-02-24 | I104: 1 | J104: 9.7 | L104: 14.55 | M104: 0.66 | N104: closed | O104: 0 | P104: 0 | R104: Administratively closed 2026-09-02 -- pre-2026 legacy trade, no relevance to 2026 strategy tracking (Tony's directive).
A105: 2283 | B105: AJZ6348 | C105: TOS_Import | D105: NCTY | E105: stock | F105: long | G105: 2025-02-24 | I105: 40 | J105: 16.5 | L105: 9.9 | M105: 0.02 | N105: closed | O105: -140 | P105: -14.14
A106: 2279 | B106: AJZ6348 | C106: TOS_Import | D106: NFLX | E106: put | F106: long | G106: 2025-02-25 | I106: 1 | J106: 27.95 | L106: 41.92 | M106: 1.38 | N106: closed | O106: -535 | P106: -12.76
A107: 2280 | B107: AJZ6348 | C107: TOS_Import | D107: META | E107: put | F107: long | G107: 2025-02-25 | I107: 1 | J107: 20.25 | L107: 30.38 | M107: 1.39 | N107: closed | O107: 507 | P107: 16.69
A108: 2277 | B108: AJZ6348 | C108: TOS_Import | D108: XPEV | E108: stock | F108: long | G108: 2025-02-27 | I108: 50 | J108: 22.52 | L108: 16.89 | M108: 0.04 | N108: closed | O108: 86.75 | P108: 5.14
A109: 2278 | B109: AJZ6348 | C109: TOS_Import | D109: NEXA | E109: stock | F109: long | G109: 2025-02-27 | I109: 125 | J109: 5.57 | L109: 10.44 | M109: 0.04 | N109: closed | O109: 28.75 | P109: 2.75
A110: 2275 | B110: AJZ6348 | C110: TOS_Import | D110: ATEC | E110: stock | F110: long | G110: 2025-02-28 | I110: 80 | J110: 12.14 | L110: 14.57 | M110: 0.03 | N110: closed | O110: -191.2 | P110: -13.12
A111: 2276 | B111: AJZ6348 | C111: TOS_Import | D111: 92340V107 | E111: stock | F111: long | G111: 2025-02-28 | I111: 200 | J111: 5.37 | L111: 16.11 | M111: 0.06 | N111: closed | O111: -43.98 | P111: -2.73
A112: 2273 | B112: AJZ6348 | C112: TOS_Import | D112: AAOI | E112: put | F112: long | G112: 2025-03-03 | I112: 2 | J112: 2.55 | L112: 7.65 | M112: 2.67 | N112: closed | O112: 190 | P112: 24.84
A113: 2274 | B113: AJZ6348 | C113: TOS_Import | D113: CMA | E113: call | F113: long | G113: 2025-03-03 | I113: 1 | J113: 7.9 | L113: 11.85 | M113: 1.34 | N113: closed | O113: -220 | P113: -18.57
A114: 2272 | B114: AJZ6348 | C114: TOS_Import | D114: DGICA | E114: stock | F114: long | G114: 2025-03-04 | I114: 50 | J114: 18.05 | L114: 13.54 | M114: 0.04 | N114: closed | O114: 31 | P114: 2.29
A115: 2271 | B115: AJZ6348 | C115: TOS_Import | D115: BEKE | E115: stock | F115: long | G115: 2025-03-06 | I115: 30 | J115: 24.91 | L115: 11.21 | M115: 0.02 | N115: closed | O115: -62.33 | P115: -5.56
A116: 2269 | B116: AJZ6348 | C116: TOS_Import | D116: CAH | E116: call | F116: long | G116: 2025-03-10 | I116: 1 | J116: 7.1 | L116: 10.65 | M116: 1.35 | N116: closed | O116: 270 | P116: 25.35
... A135: 2251 | B135: AJZ6348 | C135: TOS_Import | D135: KR | E135: call | F135: long | G135: 2025-04-11 | I135: 2 | J135: 2.9 | L135: 8.7 | M135: 2.66 | N135: closed | O135: -122 | P135: -14.02
A136: 2248 | B136: AJZ6348 | C136: P_116 | D136: PLTR | E136: call | F136: long | G136: 2025-04-14 | I136: 6 | J136: 0.83 | L136: 7.47 | M136: 3.97 | N136: closed | O136: 0 | P136: 0 | R136: Administratively closed 2026-09-02 -- pre-2026 legacy trade, no relevance to 2026 strategy tracking (Tony's directive).
A137: 2249 | B137: AJZ6348 | C137: TOS_Import | D137: NVDA | E137: call | F137: long | G137: 2025-04-14 | I137: 6 | J137: 0.82 | L137: 7.38 | M137: 7.97 | N137: closed | O137: -138 | P137: -18.7
A138: 2250 | B138: AJZ6348 | C138: TOS_Import | D138: ROST | E138: put | F138: long | G138: 2025-04-14 | I138: 1 | J138: 9.2 | L138: 13.8 | M138: 1.34 | N138: closed | O138: -95 | P138: -6.88
A139: 2245 | B139: AJZ6348 | C139: P_116 | D139: PLTR | E139: call | F139: long | G139: 2025-04-15 | I139: 3 | J139: 1 | L139: 4.5 | M139: 7.98 | N139: closed | O139: -69 | P139: -15.33
A140: 2246 | B140: AJZ6348 | C140: TOS_Import | D140: MAG | E140: call | F140: long | G140: 2025-04-15 | I140: 4 | J140: 1.49 | L140: 8.94 | M140: 5.3 | N140: closed | O140: -176 | P140: -19.69
A141: 2247 | B141: AJZ6348 | C141: TOS_Import | D141: UUU | E141: stock | F141: long | G141: 2025-04-15 | I141: 200 | J141: 1.9 | L141: 5.7 | M141: 0.04 | N141: closed | O141: 30 | P141: 5.26
A142: 2243 | B142: AJZ6348 | C142: TOS_Import | D142: GRPN | E142: call | F142: long | G142: 2025-04-16 | I142: 4 | J142: 0.89 | L142: 5.34 | M142: 5.3 | N142: closed | O142: -96 | P142: -17.98
A143: 2244 | B143: AJZ6348 | C143: TOS_Import | D143: MOS | E143: call | F143: long | G143: 2025-04-16 | I143: 1 | J143: 2.56 | L143: 3.84 | M143: 1.33 | N143: closed | O143: 49 | P143: 12.76
A144: 2241 | B144: AJZ6348 | C144: TOS_Import | D144: MO | E144: call | F144: long | G144: 2025-04-17 | I144: 4 | J144: 0.91 | L144: 5.46 | M144: 5.3 | N144: closed | O144: -20 | P144: -3.66
A145: 2242 | B145: AJZ6348 | C145: TOS_Import | D145: GLD | E145: call | F145: long | G145: 2025-04-17 | I145: 1 | J145: 8.1 | L145: 12.15 | M145: 1.36 | N145: closed | O145: 463 | P145: 38.11
A146: 2239 | B146: AJZ6348 | C146: TOS_Import | D146: SBUX | E146: put | F146: long | G146: 2025-04-21 | I146: 4 | J146: 0.84 | L146: 5.04 | M146: 5.3 | N146: closed | O146: -92 | P146: -18.25
A147: 2240 | B147: AJZ6348 | C147: TOS_Import | D147: CVS | E147: call | F147: long | G147: 2025-04-21 | I147: 1 | J147: 8.9 | L147: 13.35 | M147: 1.34 | N147: closed | O147: -80 | P147: -5.99
A148: 2236 | B148: AJZ6348 | C148: TOS_Import | D148: TIGO | E148: stock | F148: long | G148: 2025-04-22 | I148: 20 | J148: 32.2999 | L148: 9.69 | M148: 0.02 | N148: closed | O148: 8.9 | P148: 0.92
... A155: 2229 | B155: AJZ6348 | C155: TOS_Import | D155: CCL | E155: call | F155: long | G155: 2025-04-28 | I155: 6 | J155: 0.94 | L155: 8.46 | M155: 7.97 | N155: closed | O155: -282 | P155: -33.33
A156: 2230 | B156: AJZ6348 | C156: TOS_Import | D156: DIS | E156: put | F156: long | G156: 2025-04-28 | I156: 1 | J156: 9.85 | L156: 14.77 | M156: 0.66 | N156: closed | O156: 0 | P156: 0 | R156: Administratively closed 2026-09-02 -- pre-2026 legacy trade, no relevance to 2026 strategy tracking (Tony's directive).
A157: 2231 | B157: AJZ6348 | C157: TOS_Import | D157: IBM | E157: call | F157: long | G157: 2025-04-28 | I157: 1 | J157: 10.65 | L157: 15.97 | M157: 1.36 | N157: closed | O157: 300 | P157: 18.79
A158: 2232 | B158: AJZ6348 | C158: TOS_Import | D158: ZM | E158: call | F158: long | G158: 2025-04-28 | I158: 1 | J158: 5.45 | L158: 8.17 | M158: 1.34 | N158: closed | O158: 50 | P158: 6.12
A159: 2227 | B159: AJZ6348 | C159: TOS_Import | D159: SOFI | E159: stock | F159: long | G159: 2025-04-29 | I159: 75 | J159: 13.8748 | L159: 15.61 | M159: 0.04 | N159: closed | O159: -103.11 | P159: -6.61
A160: 2225 | B160: AJZ6348 | C160: TOS_Import | D160: DUK | E160: call | F160: long | G160: 2025-05-01 | I160: 4 | J160: 0.84 | L160: 5.04 | M160: 5.29 | N160: closed | O160: -176 | P160: -34.92
A161: 2226 | B161: AJZ6348 | C161: TOS_Import | D161: MSFT | E161: call | F161: long | G161: 2025-05-01 | I161: 6 | J161: 0.87 | L161: 7.83 | M161: 7.97 | N161: closed | O161: -96 | P161: -12.26
A162: 2221 | B162: AJZ6348 | C162: TOS_Import | D162: SBH | E162: stock | F162: long | G162: 2025-05-02 | I162: 50 | J162: 8.23 | L162: 6.17 | M162: 0.01 | N162: closed | O162: 50 | P162: 8.1
A163: 2222 | B163: AJZ6348 | C163: TOS_Import | D163: LOW | E163: call | F163: long | G163: 2025-05-02 | I163: 4 | J163: 0.85 | L163: 5.1 | M163: 5.3 | N163: closed | O163: -100 | P163: -19.61
A164: 2223 | B164: AJZ6348 | C164: TOS_Import | D164: C | E164: call | F164: long | G164: 2025-05-02 | I164: 4 | J164: 1.1 | L164: 6.6 | M164: 5.3 | N164: closed | O164: 56 | P164: 8.48
A165: 2224 | B165: AJZ6348 | C165: TOS_Import | D165: DIS | E165: put | F165: long | G165: 2025-05-02 | I165: 1 | J165: 8.05 | L165: 12.08 | M165: 2.02 | N165: closed | O165: 10 | P165: 0.83
A166: 2216 | B166: AJZ6348 | C166: TOS_Import | D166: HOOD | E166: call | F166: long | G166: 2025-05-05 | I166: 2 | J166: 4.5 | L166: 13.5 | M166: 2.69 | N166: closed | O166: 533 | P166: 39.48
A167: 2217 | B167: AJZ6348 | C167: TOS_Import | D167: MRNA | E167: call | F167: long | G167: 2025-05-05 | I167: 10 | J167: 0.62 | L167: 9.3 | M167: 13.26 | N167: closed | O167: -247 | P167: -26.56
A168: 2218 | B168: AJZ6348 | C168: TOS_Import | D168: BBY | E168: call | F168: long | G168: 2025-05-05 | I168: 10 | J168: 0.71 | L168: 10.65 | M168: 13.27 | N168: closed | O168: 10 | P168: 0.94
A169: 2219 | B169: AJZ6348 | C169: TOS_Import | D169: BMY | E169: put | F169: long | G169: 2025-05-05 | I169: 1 | J169: 9.95 | L169: 14.92 | M169: 2.04 | N169: closed | O169: 207 | P169: 13.87
A170: 2220 | B170: AJZ6348 | C170: TOS_Import | D170: BMY | E170: put | F170: long | G170: 2025-05-05 | I170: 1 | J170: 9.78 | L170: 14.67 | M170: 0.66 | N170: closed | O170: 0 | P170: 0 | R170: Administratively closed 2026-09-02 -- pre-2026 legacy trade, no relevance to 2026 strategy tracking (Tony's directive).
A171: 2215 | B171: AJZ6348 | C171: TOS_Import | D171: HWM | E171: call | F171: long | G171: 2025-05-06 | I171: 1 | J171: 8.45 | L171: 12.67 | M171: 1.34 | N171: closed | O171: -145 | P171: -11.44
A172: 2214 | B172: AJZ6348 | C172: TOS_Import | D172: SCHW | E172: call | F172: long | G172: 2025-05-07 | I172: 8 | J172: 0.87 | L172: 10.44 | M172: 10.6 | N172: closed | O172: 56 | P172: 5.36
A173: 2208 | B173: AJZ6348 | C173: TOS_Import | D173: RGLD | E173: call | F173: long | G173: 2025-05-12 | I173: 1 | J173: 8.4 | L173: 12.6 | M173: 1.32 | N173: closed | O173: -240 | P173: -19.05
A174: 2209 | B174: AJZ6348 | C174: TOS_Import | D174: WMT | E174: call | F174: long | G174: 2025-05-12 | I174: 4 | J174: 4.59 | L174: 27.54 | M174: 5.29 | N174: closed | O174: 24 | P174: 0.87
A175: 2210 | B175: AJZ6348 | C175: TOS_Import | D175: LRCX | E175: call | F175: long | G175: 2025-05-12 | I175: 10 | J175: 0.83 | L175: 12.45 | M175: 13.23 | N175: closed | O175: 950 | P175: 76.31
A176: 2211 | B176: AJZ6348 | C176: TOS_Import | D176: MS | E176: call | F176: long | G176: 2025-05-12 | I176: 10 | J176: 0.5 | L176: 7.5 | M176: 13.23 | N176: closed | O176: 275 | P176: 36.67
A177: 2212 | B177: AJZ6348 | C177: TOS_Import | D177: NEE | E177: put | F177: long | G177: 2025-05-12 | I177: 1 | J177: 7.6 | L177: 11.4 | M177: 1.32 | N177: closed | O177: -250 | P177: -21.93
A178: 2213 | B178: AJZ6348 | C178: TOS_Import | D178: BITX | E178: stock | F178: long | G178: 2025-05-12 | I178: 20 | J178: 53.45 | L178: 16.04 | M178: 0 | N178: closed | O178: 9.4 | P178: 0.59
A179: 2207 | B179: AJZ6348 | C179: TOS_Import | D179: CAL | E179: stock | F179: long | G179: 2025-05-13 | I179: 40 | J179: 17.6809 | L179: 10.61 | M179: 0.01 | N179: closed | O179: -119.24 | P179: -11.24
A180: 2205 | B180: AJZ6348 | C180: TOS_Import | D180: KTTA | E180: stock | F180: long | G180: 2025-05-14 | I180: 200 | J180: 0.9682 | L180: 2.9 | M180: 0.03 | N180: closed | O180: -14.1 | P180: -4.86
A181: 2206 | B181: AJZ6348 | C181: TOS_Import | D181: IBM | E181: call | F181: long | G181: 2025-05-14 | I181: 4 | J181: 1.95 | L181: 11.7 | M181: 5.29 | N181: closed | O181: 720 | P181: 61.54
A182: 2204 | B182: AJZ6348 | C182: TOS_Import | D182: CME | E182: call | F182: long | G182: 2025-05-16 | I182: 2 | J182: 4 | L182: 12 | M182: 2.64 | N182: closed | O182: 500 | P182: 41.67
... A217: 2165 | B217: AJZ6348 | C217: TOS_Import | D217: RBLX | E217: call | F217: long | G217: 2025-06-23 | I217: 10 | J217: 0.37 | L217: 5.55 | M217: 19.87 | N217: closed | O217: -125 | P217: -22.52
A218: 2166 | B218: AJZ6348 | C218: TOS_Import | D218: RBLX | E218: call | F218: long | G218: 2025-06-23 | I218: 10 | J218: 0.41 | L218: 6.15 | M218: 6.61 | N218: closed | O218: 0 | P218: 0 | R218: Administratively closed 2026-09-02 -- pre-2026 legacy trade, no relevance to 2026 strategy tracking (Tony's directive).
A219: 2167 | B219: AJZ6348 | C219: TOS_Import | D219: KO | E219: call | F219: long | G219: 2025-06-23 | I219: 2 | J219: 4.94 | L219: 14.82 | M219: 2.65 | N219: closed | O219: 94 | P219: 6.34
...

Sheet Market_Data
A1: Date | B1: AA | C1: AADX | D1: AAL | E1: AAOI | F1: AAP | G1: AAPL | H1: AB | I1: ABNB | J1: ABT | K1: ACAD | L1: ACHR | M1: ADM | N1: AEO | O1: AFL | P1: AFRM | Q1: AG | R1: AGCO | S1: AIFF | T1: AKAM | U1: ALGS | V1: AMD | W1: AMG | X1: AMIX | Y1: AMKR | Z1: AMSC | AA1: AMZN | AB1: ANET | AC1: ANGI | AD1: ANRO | AE1: APH | AF1: APPS | AG1: APVO | AH1: ARQQ | AI1: ARR | AJ1: ASX | AK1: ATEC | AL1: AXGN | AM1: BAC | AN1: BANC | AO1: BBY | AP1: BEAM | AQ1: BEKE | AR1: BGC | AS1: BITQ | AT1: BITX | AU1: BMY | AV1: BOWFF | AW1: BTAI | AX1: BTDR | AY1: C | AZ1: CAH | BA1: CAL | BB1: CCI | BC1: CCJ | BD1: CCL | BE1: CCSI | BF1: CF | BG1: CLSK | BH1: CMCL | BI1: CMCSA | BJ1: CME | BK1: COHR | BL1: COIN | BM1: COMP | BN1: COP | BO1: COST | BP1: CPIX | BQ1: CRDO | BR1: CRML | BS1: CRNC | BT1: CSCO | BU1: CSV | BV1: CSX | BW1: CVNA | BX1: CVS | BY1: CW | BZ1: DAL | CA1: DASH | CB1: DCTH | CC1: DDOG | CD1: DELL | CE1: DG | CF1: DGICA | CG1: DINO | CH1: DIS | CI1: DJT | CJ1: DLR | CK1: DMRA | CL1: DOCU | CM1: DOMH | CN1: DOW | CO1: DOX | CP1: DSP | CQ1: DUK | CR1: DYNF | CS1: EBAY | CT1: EDN | CU1: ETON | CV1: ETSY | CW1: EWZ | CX1: F | CY1: FEIM | CZ1: FLR | DA1: FLWS | DB1: FSM | DC1: FTNT | DD1: FUTU | DE1: GDX | DF1: GE | DG1: GLD | DH1: GLXY | DI1: GM | DJ1: GOOG | DK1: GOOGL | DL1: GRPN | DM1: GRRR | DN1: HIG | DO1: HIMS | DP1: HOOD | DQ1: HWM | DR1: IAU | DS1: IBEX | DT1: IBM | DU1: ILMN | DV1: IMDX | DW1: INBS | DX1: INSG | DY1: INTC | DZ1: IONQ | EA1: IRDM | EB1: IRM | EC1: ISPC | ED1: IWM | EE1: JCI | EF1: JNJ | EG1: KC | EH1: KINS | EI1: KO | EJ1: KR | EK1: KTTA | EL1: LEVI | EM1: LION | EN1: LMND | EO1: LNG | EP1: LOW | EQ1: LQDA | ER1: LRCX | ES1: LSAK | ET1: LUNR | EU1: M | EV1: MA | EW1: MAIA | EX1: MARA | EY1: MCB | EZ1: MCHP | FA1: MDT | FB1: META | FC1: MO | FD1: MOMO | FE1: MOS | FF1: MRK | FG1: MRNA | FH1: MRVL | FI1: MS | FJ1: MSFT | FK1: MSTR | FL1: NCTY | FM1: NEE | FN1: NEM | FO1: NEXA | FP1: NFLX | FQ1: NG | FR1: NNDM | FS1: NTAP | FT1: NU | FU1: NVDA | FV1: NXT | FW1: OKLO | FX1: OPEN | FY1: OPFI | FZ1: ORMP | GA1: P | GB1: PANW | GC1: PENG | GD1: PLTR | GE1: PM | GF1: PNC | GG1: PPC | GH1: PPTA | GI1: QBTS | GJ1: QNTM | GK1: QQQ | GL1: QUBT | GM1: RAND | GN1: RBLX | GO1: RDDT | GP1: RDW | GQ1: REAL | GR1: RGLD | GS1: RGTI | GT1: RIG | GU1: RIOT | GV1: RKLB | GW1: ROKU | GX1: ROOT | GY1: ROST | GZ1: RTX | HA1: RXRX | HB1: SBH | HC1: SBUX | HD1: SCHW | HE1: SEGG | HF1: SGML | HG1: SHEL | HH1: SMTC | HI1: SNAP | HJ1: SOFI | HK1: SONY | HL1: SOUN | HM1: SPY | HN1: SSYS | HO1: SU | HP1: SUPN | HQ1: SUPV | HR1: SWAG | HS1: SWPPX | HT1: TCBX | HU1: TDOC | HV1: TIGO | HW1: TILE | HX1: TME | HY1: TMUS | HZ1: TPR | IA1: TSLA | IB1: TTD | IC1: TWLO | ID1: UAL | IE1: UBER | IF1: UBS | IG1: UPRO | IH1: UPXI | II1: URBN | IJ1: USAR | IK1: UUU | IL1: VATE | IM1: VLO | IN1: VOD | IO1: VYX | IP1: VZ | IQ1: WBD | IR1: WFC | IS1: WMG | IT1: WMT | IU1: WRAP | IV1: WT | IW1: WULF | IX1: XLE | IY1: XLK | IZ1: XLV | JA1: XMTR | JB1: XPEV | JC1: XYZ | JD1: YELP | JE1: YUM | JF1: ZION | JG1: ZM | JH1: ZSPC | JI1: ZTS
A2: 2025-09-22 | B2: 32.374348 | D2: 12.33 | E2: 30.540001 | F2: 58.975525 | G2: 255.13751 | H2: 35.537224 | I2: 125.44 | J2: 133.53354 | K2: 24.530001 | L2: 9.5500002 | M2: 58.160679 | N2: 17.470316 | O2: 105.20063 | P2: 90.120003 | Q2: 12.116218 | R2: 108.32666 | S2: 2.9400001 | T2: 76.68 | U2: 9.5299997 | V2: 159.78999 | W2: 243.97763 | X2: 23.309999 | Y2: 29.325592 | Z2: 64.629997 | AA2: 227.63 | AB2: 145.39999 | AC2: 17.08 | AD2: 3.98 | AE2: 61.511417 | AF2: 5.46 | AG2: 30.42 | AH2: 41.27 | AI2: 11.851522 | AJ2: 11.593375 | AK2: 15.6 | AL2: 17.6 | AM2: 50.836372 | AN2: 16.097094 | AO2: 68.672638 | AP2: 24.41 | AQ2: 18.988596 | AR2: 9.5721178 | AS2: 25.09 | AT2: 50.080688 | AU2: 42.919907 | AV2: 50.284149 | AW2: 2.78 | AX2: 17.959999 | AY2: 101.34604 | AZ2: 145.9521 | BA2: 13.949263 | BB2: 89.662743 | BC2: 86.142273 | BD2: 30.224304 | BE2: 28.959999 | BF2: 83.903549 | BG2: 13.74 | BH2: 33.795559 | BI2: 28.149002 | BJ2: 251.32535 | BK2: 114.6 | BL2: 331.95001 | BM2: 7.9200001 | BN2: 89.197906 | BO2: 937.78845 | BP2: 2.5047007 | BQ2: 164.10001 | BR2: 6.9099998 | BS2: 12.5 | BT2: 66.375603 | BU2: 44.856907 | BV2: 32.77866 | BW2: 78.169998 | BX2: 72.818733 | BY2: 517.31409 | BZ2: 58.252712 | CA2: 262.75 | CB2: 11.55 | CC2: 138.35001 | CD2: 133.98265 | CE2: 99.832603 | CF2: 18.58465 | CG2: 50.754372 | CH2: 110.95337 | CI2: 17.6 | CJ2: 169.8262 | CK2: 3 | CL2: 84.860001 | CM2: 5.8222656 | CN2: 22.080215 | CO2: 81.877861 | CP2: 9.4099998 | CQ2: 117.45779 | CR2: 58.797916 | CS2: 89.450043 | CT2: 18.209999 | CU2: 18.370001 | CV2: 61.669998 | CW2: 29.467108 | CX2: 11.140587 | CY2: 29.889999 | CZ2: 44.75 | DA2: 5.4000001 | DB2: 8.5100002 | DC2: 85.010002 | DD2: 165.07265 | DE2: 73.794052 | DF2: 299.49902 | DG2: 345.04999 | DH2: 33.689999 | DI2: 58.376362 | DJ2: 252.22159 | DK2: 251.87495 | DL2: 22.790001 | DM2: 20.860001 | DN2: 128.40837 | DO2: 57.700001 | DP2: 124.89 | DQ2: 191.75079 | DR2: 70.629997 | DS2: 41.959999 | DT2: 264.49396 | DU2: 101.49 | DV2: 3.27 | DW2: 13.45 | DX2: 13.41 | DY2: 28.76 | DZ2: 71.940002 | EA2: 17.76174 | EB2: 101.05965 | EC2: 65.599998 | ED2: 241.93198 | EE2: 108.65349 | EF2: 170.37057 | EG2: 16.77 | EH2: 13.71306 | EI2: 64.495461 | EJ2: 63.089924 | EK2: 0.73000002 | EL2: 22.315327 | EM2: 6.8600001 | EN2: 59.68 | EO2: 228.55049 | EP2: 255.14835 | EQ2: 22.9 | ER2: 131.47235 | ES2: 4.0999999 | ET2: 10.13 | EU2: 16.30995 | EV2: 580.8703 | EW2: 1.52 | EX2: 18.35 | EY2: 76.643494 | EZ2: 63.730747 | FA2: 91.640358 | FB2: 763.17511 | FC2: 59.749107 | FD2: 7.1978278 | FE2: 32.24567 | FF2: 78.106491 | FG2: 26.559999 | FH2: 75.369423 | FI2: 157.14757 | FJ2: 510.25189 | FK2: 335.92999 | FL2: 10.29 | FM2: 70.328819 | FN2: 82.942062 | FO2: 4.9487977 | FP2: 122.737 | FQ2: 7.6399999 | FR2: 1.47 | FS2: 122.46673 | FT2: 16.299999 | FU2: 183.17116 | FV2: 73.139999 | FW2: 140.3 | FX2: 8.3800001 | FY2: 11.63 | FZ2: 2.3026559 | GA2: 87.849998 | GB2: 208.17999 | GC2: 27.9 | GD2: 179.33 | GE2: 156.31873 | GF2: 196.64906 | GG2: 41.189999 | GH2: 18.860001 | GI2: 25.67 | GJ2: 18.49 | GK2: 600.00836 | GL2: 20.209999 | GM2: 12.981513 | GN2: 136.84 | GO2: 257.56 | GP2: 8.1099997 | GQ2: 10.74 | GR2: 189.88124 | GS2: 28.370001 | GT2: 3.3900001 | GU2: 17.5 | GV2: 49.810001 | GW2: 99.050003 | GX2: 102.88 | GY2: 143.47595 | GZ2: 157.09822 | HA2: 4.98 | HB2: 15.03 | HC2: 83.167648 | HD2: 93.238297 | HE2: 38.150002 | HF2: 6.27 | HG2: 68.501541 | HH2: 61.529999 | HI2: 8.5299997 | HJ2: 29.809999 | HK2: 29.73 | HL2: 17.309999 | HM2: 659.72247 | HN2: 10.37 | HO2: 40.923199 | HP2: 46.98 | HQ2: 6.2199998 | HR2: 1.79 | HS2: 17.091333 | HT2: 40.040001 | HU2: 8.1899996 | HV2: 44.470009 | HW2: 29.618856 | HX2: 23.665396 | HY2: 232.52783 | HZ2: 112.43216 | IA2: 434.20999 | IB2: 46.150002 | IC2: 105.19 | ID2: 104.18 | IE2: 99.389999 | IF2: 41.314217 | IG2: 111.35452 | IH2: 6.0700002 | II2: 72.120003 | IJ2: 16.08 | IK2: 6.1804423 | IL2: 5.1399999 | IM2: 162.98442 | IN2: 10.943772 | IO2: 13.03 | IP2: 40.400299 | IQ2: 19.610001 | IR2: 83.342575 | IS2: 32.31937 | IT2: 101.96153 | IU2: 2.5599999 | IV2: 14.562538 | IW2: 11.49 | IX2: 42.873158 | IY2: 140.77286 | IZ2: 134.8987 | JA2: 55.029999 | JB2: 21.360001 | JC2: 77.410004 | JD2: 31.74 | JE2: 146.42647 | JF2: 55.399086 | JG2: 83.529999 | JH2: 39 | JI2: 141.92424
A3: 2025-09-23 | B3: 31.282961 | D3: 12.19 | E3: 28.059999 | F3: 58.92651 | G3: 253.49361 | H3: 34.942493 | I3: 123.5 | J3: 132.82002 | K3: 23.6 | L3: 10 | M3: 58.976833 | N3: 17.489779 | O3: 106.01365 | P3: 82.730003 | Q3: 11.776882 | R3: 108.53448 | S3: 2.8499999 | T3: 75.269997 | U3: 10.25 | V3: 160.89999 | W3: 241.81793 | X3: 22.26 | Y3: 29.375248 | Z3: 61.34 | AA3: 220.71001 | AB3: 144.09 | AC3: 16.6 | AD3: 4.1100001 | AE3: 62.361805 | AF3: 5.4899998 | AG3: 29.52 | AH3: 40.59 | AI3: 12.003358 | AJ3: 11.583475 | AK3: 15.49 | AL3: 17.299999 | AM3: 50.620964 | AN3: 16.106852 | AO3: 69.31826 | AP3: 23.73 | AQ3: 18.389679 | AR3: 9.522521 | AS3: 24.76 | AT3: 49.58889 | AU3: 42.853115 | AV3: 50.157234 | AW3: 2.47 | AX3: 16.57 | AY3: 100.8662 | AZ3: 153.02852 | BA3: 13.607129 | BB3: 89.729317 | BC3: 86.721146 | BD3: 30.224304 | BE3: 29.18 | BF3: 85.373123 | BG3: 13.91 | BH3: 34.230488 | BI3: 28.265209 | BJ3: 252.17244 | BK3: 109.29 | BL3: 320.07001 | BM3: 7.9400001 | BN3: 90.613281 | BO3: 938.1264 | BP3: 2.3108382 | BQ3: 162.25999 | BR3: 6.6999998 | BS3: 11.95 | BT3: 66.169861 | BU3: 44.431301 | BV3: 33.637623 | BW3: 75.620003 | BX3: 74.146591 | BY3: 517.38409 | BZ3: 58.114227 | CA3: 265.75 | CB3: 11 | CC3: 137.49001 | CD3: 132.64964 | CE3: 101.60658 | CF3: 18.479057 | CG3: 51.141739 | CH3: 110.6478 | CI3: 17.469999 | CJ3: 169.27206 | CK3: 4.2199998 | CL3: 84.82 | CM3: 6.0987191 | CN3: 21.784798 | CO3: 80.513542 | CP3: 9.04 | CQ3: 118.92626 | CR3: 58.451004 | CS3: 89.914124 | CT3: 18.68 | CU3: 19.83 | CV3: 62.634998 | CW3: 29.974335 | CX3: 11.207469 | CY3: 29.84 | CZ3: 44.029999 | DA3: 5.04 | DB3: 8.5299997 | DC3: 85.269997 | DD3: 164.45259 | DE3: 73.694778 | DF3: 304.08575 | DG3: 346.45999 | DH3: 33.139999 | DI3: 58.078934 | DJ3: 251.68297 | DK3: 251.00723 | DL3: 22.33 | DM3: 20.27 | DN3: 129.489 | DO3: 56 | DP3: 126.2 | DQ3: 193.17781 | DR3: 70.940002 | DS3: 41.259998 | DT3: 265.34192 | DU3: 99.370003 | DV3: 3.01 | DW3: 13.2 | DX3: 13.81 | DY3: 29.34 | DZ3: 75.139999 | EA3: 17.369867 | EB3: 100.70169 | EC3: 62.400002 | ED3: 241.38751 | EE3: 107.65932 | EF3: 172.68834 | EG3: 16.059999 | EH3: 13.64395 | EI3: 64.982506 | EJ3: 63.901531 | EK3: 0.73000002 | EL3: 22.500477 | EM3: 6.6799998 | EN3: 57.52 | EO3: 232.62045 | EP3: 254.58 | EQ3: 22.450001 | ER3: 131.20386 | ES3: 4.21 | ET3: 10.36 | EU3: 16.541708 | EV3: 566.44012 | EW3: 1.53 | EX3: 17.709999 | EY3: 76.47538 | EZ3: 63.058361 | FA3: 91.969635 | FB3: 753.44043 | FC3: 60.760696 | FD3: 6.9973578 | FE3: 32.766541 | FF3: 77.679047 | FG3: 25.790001 | FH3: 74.461357 | FI3: 157.19644 | FJ3: 505.07443 | FK3: 327.78 | FL3: 10.63 | FM3: 70.29966 | FN3: 83.88324 | FO3: 4.9290023 | FP3: 121.847 | FQ3: 7.73 | FR3: 1.5599999 | FS3: 121.31686 | FT3: 16.15 | FU3: 178.00352 | FV3: 70.559998 | FW3: 142.64999 | FX3: 7.0900002 | FY3: 11.74 | FZ3: 2.3213007 | GA3: 88.290001 | GB3: 203.25 | GC3: 27.57 | GD3: 182.55 | GE3: 158.04614 | GF3: 197.42357 | GG3: 40.639999 | GH3: 18.950001 | GI3: 27.52 | GJ3: 18.360001 | GK3: 596.02289 | GL3: 21.405001 | GM3: 12.910962 | GN3: 132.22 | GO3: 237.45 | GP3: 9.2200003 | GQ3: 10.53 | GR3: 190.2778 | GS3: 31.459999 | GT3: 3.54 | GU3: 17.07 | GV3: 52.91 | GW3: 99 | GX3: 98.510002 | GY3: 144.4776 | GZ3: 158.19199 | HA3: 4.8099999 | HB3: 15.67 | HC3: 83.557693 | HD3: 92.724861 | HE3: 35.419998 | HF3: 6.0999999 | HG3: 68.973953 | HH3: 61.290001 | HI3: 8.4200001 | HJ3: 29.09 | HK3: 29.76 | HL3: 18.049999 | HM3: 656.13129 | HN3: 11.69 | HO3: 41.452122 | HP3: 46.830002 | HQ3: 6.1199999 | HR3: 1.76 | HS3: 17.002316 | HT3: 39.75 | HU3: 8.3699999 | HV3: 45.959957 | HW3: 29.419605 | HX3: 22.672035 | HY3: 234.53543 | HZ3: 114.66342 | IA3: 425.85001 | IB3: 46.860001 | IC3: 103.43 | ID3: 104.13 | IE3: 97.800003 | IF3: 41.021759 | IG3: 109.58101 | IH3: 6.1700001 | II3: 72.050003 | IJ3: 17.85 | IK3: 5.7678514 | IL3: 4.9000001 | IM3: 166.85239 | IN3: 10.914948 | IO3: 12.91 | IP3: 40.578152 | IQ3: 19.559999 | IR3: 82.569443 | IS3: 32.465569 | IT3: 101.66403 | IU3: 2.5599999 | IV3: 14.562538 | IW3: 11.24 | IX3: 43.611591 | IY3: 139.55768 | IZ3: 135.20477 | JA3: 54.209999 | JB3: 21.190001 | JC3: 76.540001 | JD3: 31.379999 | JE3: 146.59323 | JF3: 55.593163 | JG3: 82.580002 | JH3: 41 | JI3: 139.92265
A4: 2025-09-24 | B4: 30.98531 | D4: 11.94 | E4: 26.690001 | F4: 59.848003 | G4: 251.38139 | H4: 34.622257 | I4: 123.08 | J4: 130.86522 | K4: 21.26 | L4: 9.71 | M4: 59.734684 | N4: 17.421652 | O4: 107.07152 | P4: 81.529999 | Q4: 11.387647 | R4: 106.14944 | S4: 2.95 | T4: 76.230003 | U4: 10.75 | V4: 160.88 | W4: 237.20854 | X4: 22.26 | Y4: 29.156767 | Z4: 59.610001 | AA4: 220.21001 | AB4: 142.64 | AC4: 16.59 | AD4: 3.8800001 | AE4: 61.232925 | AF4: 5.3400002 | AG4: 32.040001 | AH4: 42.119999 | AI4: 11.919006 | AJ4: 11.425069 | AK4: 15.21 | AL4: 17.389999 | AM4: 50.620964 | AN4: 16.301964 | AO4: 70.419586 | AP4: 23.59 | AQ4: 18.870775 | AR4: 9.4332466 | AS4: 25.139999 | AT4: 51.14782 | AU4: 42.137459 | AV4: 49.181049 | AW4: 2.5799999 | AX4: 17.52 | AY4: 99.544167 | AZ4: 152.98892 | BA4: 13.626678 | BB4: 89.120659 | BC4: 82.928528 | BD4: 29.889683 | BE4: 29.459999 | BF4: 89.791687 | BG4: 14.45 | BH4: 33.281559 | BI4: 28.256269 | BJ4: 254.55019 | BK4: 106.52 | BL4: 321.76999 | BM4: 7.9299998 | BN4: 92.70726 | BO4: 939.7868 | BP4: 2.3728743 | BQ4: 149.38 | BR4: 6.6999998 | BS4: 11.66 | BT4: 65.954323 | BU4: 44.312519 | BV4: 33.390793 | BW4: 74.961998 | BX4: 74.030289 | BY4: 510.53482 | BZ4: 57.085484 | CA4: 260.73999 | CB4: 11.03 | CC4: 136.57001 | CD4: 130.42795 | CE4: 102.42005 | CF4: 18.354261 | CG4: 51.529095 | CH4: 111.81096 | CI4: 17 | CJ4: 167.21109 | CK4: 4.2600002 | CL4: 84.010002 | CM4: 5.6798506 | CN4: 22.042099 | CO4: 80.310349 | CP4: 8.7399998 | CQ4: 119.44794 | CR4: 58.322144 | CS4: 92.185181 | CT4: 19.129999 | CU4: 19.93 | CV4: 64.050003 | CW4: 29.715935 | CX4: 11.111923 | CY4: 29.25 | CZ4: 43.75 | DA4: 4.8499999 | DB4: 8.4200001 | DC4: 83.599998 | DD4: 173.6747 | DE4: 71.798546 | DF4: 298.78265 | DG4: 343.32001 | DH4: 34.290001 | DI4: 59.407463 | DJ4: 247.18471 | DK4: 246.49895 | DL4: 22.66 | DM4: 19.200001 | DN4: 129.52831 | DO4: 53.25 | DP4: 126.8 | DQ4: 189.8248 | DR4: 70.290001 | DS4: 41.82 | DT4: 260.75128 | DU4: 94.410004 | DV4: 3.2750001 | DW4: 13.6 | DX4: 14.19 | DY4: 31.219999 | DZ4: 73.860001 | EA4: 17.066164 | EB4: 97.934799 | EC4: 57 | ED4: 239.17006 | EE4: 105.91951 | EF4: 172.79593 | EG4: 16.469999 | EH4: 14.423886 | EI4: 64.72924 | EJ4: 64.097099 | EK4: 0.74000001 | EL4: 22.617413 | EM4: 6.8299999 | EN4: 53.43 | EO4: 234.30388 | EP4: 252.14992 | EQ4: 21.940001 | ER4: 127.86572 | ES4: 4.25 | ET4: 9.9899998 | EU4: 16.783123 | EV4: 565.28735 | EW4: 1.6 | EX4: 17.639999 | EY4: 75.990784 | EZ4: 64.169258 | FA4: 92.725067 | FB4: 758.68677 | FC4: 61.004219 | FD4: 7.2360129 | FE4: 34.657101 | FF4: 77.397316 | FG4: 25.879999 | FH4: 79.919724 | FI4: 154.38031 | FJ4: 505.98688 | FK4: 323.31 | FL4: 10.21 | FM4: 71.767487 | FN4: 82.694389 | FO4: 4.9883881 | FP4: 120.395 | FQ4: 7.6799998 | FR4: 1.59 | FS4: 121.13012 | FT4: 16.01 | FU4: 176.54703 | FV4: 72.760002 | FW4: 131.17 | FX4: 8.2299995 | FY4: 11.51 | FZ4: 2.2373984 | GA4: 84.849998 | GB4: 200.7 | GC4: 27.1 | GD4: 179.56 | GE4: 157.30307 | GF4: 197.57848 | GG4: 41.310001 | GH4: 18.860001 | GI4: 27.719999 | GJ4: 17.129999 | GK4: 593.93054 | GL4: 21.41 | GM4: 13.104979 | GN4: 133.13 | GO4: 235.69 | GP4: 9.3500004 | GQ4: 10.09 | GR4: 187.83888 | GS4: 31.639999 | GT4: 3.6400001 | GU4: 17.99 | GV4: 48.689999 | GW4: 98.209999 | GX4: 93.370003 | GY4: 148.19664 | GZ4: 159.0197 | HA4: 4.8800001 | HB4: 15.51 | HC4: 82.173027 | HD4: 91.204292 | HE4: 35 | HF4: 6.5500002 | HG4: 69.533157 | HH4: 59.830002 | HI4: 8.2200003 | HJ4: 28.440001 | HK4: 29.34 | HL4: 17.780001 | HM4: 654.0437 | HN4: 11.66 | HO4: 41.540279 | HP4: 47.099998 | HQ4: 6.3099999 | HR4: 1.795 | HS4: 16.95286 | HT4: 39.48 | HU4: 8.3999996 | HV4: 43.162872 | HW4: 28.552858 | HX4: 23.081066 | HY4: 233.46799 | HZ4: 111.97801 | IA4: 442.79001 | IB4: 46.869999 | IC4: 103.24 | ID4: 101.39 | IE4: 97.779999 | IF4: 40.485588 | IG4: 108.44533 | IH4: 6.1599998 | II4: 71.199997 | IJ4: 16.66 | IK4: 6.0036178 | IL4: 4.8099999 | IM4: 167.28328 | IN4: 10.886124 | IO4: 12.88 | IP4: 40.419022 | IQ4: 19.82 | IR4: 82.31498 | IS4: 32.587402 | IT4: 101.87228 | IU4: 2.3800001 | IV4: 14.244882 | IW4: 11.4 | IX4: 44.178867 | IY4: 138.69606 | IZ4: 134.66173 | JA4: 54.130001 | JB4: 21.27 | JC4: 76.489998 | JD4: 31.440001 | JE4: 146.60303 | JF4: 55.224419 | JG4: 83.010002 | JH4: 34.25 | JI4: 139.00038
A5: 2025-09-25 | B5: 31.203587 | D5: 11.39 | E5: 26.34 | F5: 58.652023 | G5: 255.92462 | H5: 34.832699 | I5: 121.75 | J5: 130.29831 | K5: 21.209999 | L5: 9.3299999 | M5: 59.33633 | N5: 17.324324 | O5: 107.23804 | P5: 77.940002 | Q5: 11.647138 | R5: 106.87187 | S5: 2.8900001 | T5: 75.379997 | U5: 9.3599997 | V5: 161.27 | W5: 237.62849 | X5: 21.629999 | Y5: 28.958153 | Z5: 57.959999 | AA5: 218.14999 | AB5: 143.06 | AC5: 16.65 | AD5: 3.8 | AE5: 60.835087 | AF5: 5.2600002 | AG5: 28.799999 | AH5: 38.450001 | AI5: 12.096147 | AJ5: 11.345865 | AK5: 15.39 | AL5: 16.92 | AM5: 50.767834 | AN5: 16.204407 | AO5: 70.438591 | AP5: 23.09 | AQ5: 18.998415 | AR5: 9.5126009 | AS5: 23.91 | AT5: 47.352554 | AU5: 41.42181 | AV5: 49.181049 | AW5: 2.8199999 | AX5: 16.57 | AY5: 99.994637 | AZ5: 147.42677 | BA5: 13.010839 | BB5: 89.377449 | BC5: 85.493538 | BD5: 29.997944 | BE5: 28.969999 | BF5: 87.891022 | BG5: 13.68 | BH5: 33.528675 | BI5: 28.265209 | BJ5: 258.68951 | BK5: 106.57 | BL5: 306.69 | BM5: 7.9499998 | BN5: 93.851196 | BO5: 937.8382 | BP5: 2.3496108 | BQ5: 144.94 | BR5: 7.02 | BS5: 11.1 | BT5: 66.473564 | BU5: 44.045284 | BV5: 33.351299 | BW5: 74.276001 | BX5: 72.314735 | BY5: 515.91632 | BZ5: 56.12598 | CA5: 262.07999 | CB5: 10.86 | CC5: 136.60001 | CD5: 129.31218 | CE5: 100.8029 | CF5: 18.21987 | CG5: 52.303825 | CH5: 111.37724 | CI5: 16.82 | CJ5: 166.58893 | CK5: 4.4499998 | CL5: 81.309998 | CM5: 5.6212096 | CN5: 21.15584 | CO5: 78.56868 | CP5: 8.6300001 | CQ5: 118.17271 | CR5: 58.153637 | CS5: 91.938332 | CT5: 17.530001 | CU5: 20.139999 | CV5: 63.599998 | CW5: 29.26613 | CX5: 11.102368 | CY5: 29.809999 | CZ5: 42.400002 | DA5: 4.7199998 | DB5: 8.5600004 | DC5: 83.209999 | DD5: 176.31238 | DE5: 72.602699 | DF5: 295.67844 | DG5: 344.75 | DH5: 32.115002 | DI5: 60.071732 | DJ5: 245.92799 | DK5: 245.15244 | DL5: 22.559999 | DM5: 18.780001 | DN5: 129.25322 | DO5: 54.869999 | DP5: 122.65 | DQ5: 189.45557 | DR5: 70.580002 | DS5: 41.259998 | DT5: 274.30881 | DU5: 92.190002 | DV5: 3.26 | DW5: 12.8 | DX5: 14.09 | DY5: 33.990002 | DZ5: 69.43 | EA5: 17.075962 | EB5: 97.518791 | EC5: 53.200001 | ED5: 236.88327 | EE5: 105.15398 | EF5: 173.81299 | EG5: 17.469999 | EH5: 14.66083 | EI5: 64.271423 | EJ5: 64.038422 | EK5: 0.70999998 | EL5: 22.227625 | EM5: 6.9699998 | EN5: 52.459999 | EO5: 235.30403 | EP5: 250.38615 | EQ5: 22.450001 | ER5: 127.67639 | ES5: 4.1599998 | ET5: 10.1 | EU5: 16.493425 | EV5: 563.78668 | EW5: 1.5700001 | EX5: 16.07 | EY5: 75.179855 | EZ5: 63.185043 | FA5: 91.330421 | FB5: 746.96722 | FC5: 61.060429 | FD5: 7.0641813 | FE5: 33.557491 | FF5: 75.38636 | FG5: 24.610001 | FH5: 83.631821 | FI5: 155.42657 | FJ5: 502.89236 | FK5: 300.70001 | FL5: 10.01 | FM5: 72.564575 | FN5: 82.892532 | FO5: 4.9487977 | FP5: 120.824 | FQ5: 7.9400001 | FR5: 1.58 | FS5: 118.7026 | FT5: 15.78 | FU5: 177.2653 | FV5: 73.510002 | FW5: 119.13 | FX5: 9.0900002 | FY5: 12.24 | FZ5: 2.2373984 | GA5: 83.470001 | GB5: 202.21001 | GC5: 26.540001 | GD5: 179.12 | GE5: 158.26811 | GF5: 196.28119 | GG5: 40.84 | GH5: 19 | GI5: 26.34 | GJ5: 17.07 | GK5: 591.37 | GL5: 20.58 | GM5: 12.972693 | GN5: 132.03999 | GO5: 232.75 | GP5: 8.96 | GQ5: 10.09 | GR5: 191.45764 | GS5: 32.099998 | GT5: 3.1600001 | GU5: 16.74 | GV5: 46.630001 | GW5: 98.010002 | GX5: 91.269997 | GY5: 148.22643 | GZ5: 158.16241 | HA5: 4.6300001 | HB5: 15.51 | HC5: 81.74398 | HD5: 93.583878 | HE5: 35 | HF5: 7.1999998 | HG5: 70.275543 | HH5: 61.630001 | HI5: 8.3299999 | HJ5: 28.120001 | HK5: 29.83 | HL5: 16.35 | HM5: 651.02631 | HN5: 11.59 | HO5: 41.824333 | HP5: 47.18 | HQ5: 5.8200002 | HR5: 1.71 | HS5: 16.863842 | HT5: 39.009998 | HU5: 7.9499998 | HV5: 43.693035 | HW5: 28.244017 | HX5: 22.944721 | HY5: 233.01749 | HZ5: 106.42947 | IA5: 423.39001 | IB5: 46.759998 | IC5: 101.33 | ID5: 99.150002 | IE5: 97.599998 | IF5: 39.461994 | IG5: 106.89668 | IH5: 5.2800002 | II5: 71.260002 | IJ5: 18.190001 | IK5: 5.3299999 | IL5: 4.75 | IM5: 170.79871 | IN5: 10.828474 | IO5: 12.59 | IP5: 40.578152 | IQ5: 19.780001 | IR5: 82.5205 | IS5: 32.446075 | IT5: 102.18961 | IU5: 2.28 | IV5: 14.036421 | IW5: 10.97 | IX5: 44.574986 | IY5: 138.45204 | IZ5: 132.43039 | JA5: 55.02 | JB5: 22.25 | JC5: 73.68 | JD5: 31.299999 | JE5: 147.54477 | JF5: 55.602871 | JG5: 83.989998 | JH5: 28.25 | JI5: 138.47057
A6: 2025-09-26 | B6: 32.453712 | D6: 11.31 | E6: 25.77 | F6: 59.798985 | G6: 254.51981 | H6: 34.677155 | I6: 123.7 | J6: 130.5329 | K6: 21.049999 | L6: 9.2799997 | M6: 58.879665 | N6: 17.470316 | O6: 109.07954 | P6: 76.029999 | Q6: 12.116218 | R6: 108.64334 | S6: 2.8599999 | T6: 76.050003 | U6: 9.79 | V6: 159.46001 | W6: 239.0083 | X6: 22.049999 | Y6: 28.829052 | Z6: 58.57 | AA6: 219.78 | AB6: 142.5 | AC6: 16.74 | AD6: 3.95 | AE6: 60.969353 | AF6: 5.4000001 | AG6: 27 | AH6: 36.450001 | AI6: 12.290156 | AJ6: 11.058754 | AK6: 15.02 | AL6: 17.16 | AM6: 51.120319 | AN6: 16.272697 | AO6: 72.299469 | AP6: 22.969999 | AQ6: 19.096598 | AR6: 9.3935709 | AS6: 23.48 | AT6: 47.084873 | AU6: 42.099293 | AV6: 48.214603 | AW6: 2.7 | AX6: 16.25 | AY6: 101.27749 | AZ6: 152.12788 | BA6: 13.343196 | BB6: 90.642296 | BC6: 85.413696 | BD6: 30.135729 | BE6: 29.389999 | BF6: 90.261963 | BG6: 12.96 | BH6: 36.177757 | BI6: 28.354603 | BJ6: 260.18158 | BK6: 106.99 | BL6: 312.59 | BM6: 7.9499998 | BN6: 95.470161 | BO6: 910.63684 | BP6: 2.3961377 | BQ6: 142.92999 | BR6: 6.4899998 | BS6: 11.92 | BT6: 65.856354 | BU6: 44.649052 | BV6: 33.578381 | BW6: 73.858002 | BX6: 73.439049 | BY6: 525.57562 | BZ6: 56.581005 | CA6: 262.47 | CB6: 10.745 | CC6: 139.07001 | CD6: 129.11469 | CE6: 100.08744 | CF6: 18.661448 | CG6: 51.577518 | CH6: 111.85039 | CI6: 16.93 | CJ6: 166.68613 | CK6: 4.4099998 | CL6: 81.519997 | CM6: 5.7301149 | CN6: 21.880093 | CO6: 78.984741 | CP6: 8.4899998 | CQ6: 118.84898 | CR6: 58.41135 | CS6: 89.993118 | CT6: 16.6 | CU6: 21.27 | CV6: 64.18 | CW6: 29.409683 | CX6: 11.474997 | CY6: 30.110001 | CZ6: 42.169998 | DA6: 4.77 | DB6: 8.6700001 | DC6: 84.32 | DD6: 170.12167 | DE6: 74.141533 | DF6: 293.48953 | DG6: 346.73999 | DH6: 30.9 | DI6: 60.716175 | DJ6: 246.53639 | DK6: 245.90048 | DL6: 22.74 | DM6: 19.9 | DN6: 130.7661 | DO6: 58.400002 | DP6: 121.78 | DQ6: 192.7487 | DR6: 70.989998 | DS6: 41.009998 | DT6: 277.10611 | DU6: 91.690002 | DV6: 3.3299999 | DW6: 11.2 | DX6: 14.41 | DY6: 35.5 | DZ6: 67.279999 | EA6: 17.291491 | EB6: 97.644554 | EC6: 46.799999 | ED6: 238.91264 | EE6: 106.38677 | EF6: 175.74936 | EG6: 15.64 | EH6: 14.720065 | EI6: 63.969448 | EJ6: 64.009094 | EK6: 0.727 | EL6: 22.432264 | EM6: 7 | EN6: 51.43 | EO6: 236.10612 | EP6: 251.94417 | EQ6: 21.799999 | ER6: 127.87569 | ES6: 4.1599998 | ET6: 10.08 | EU6: 17.38183 | EV6: 561.63019 | EW6: 1.62 | EX6: 16.129999 | EY6: 75.486427 | EZ6: 62.775761 | FA6: 91.945213 | FB6: 741.82062 | FC6: 61.547482 | FD6: 7.035543 | FE6: 34.068718 | FF6: 76.318977 | FG6: 24.49 | FH6: 82.993172 | FI6: 156.56087 | FJ6: 507.28619 | FK6: 309.06 | FL6: 10.1 | FM6: 73.731041 | FN6: 84.457848 | FO6: 4.9487977 | FP6: 121.061 | FQ6: 8.3000002 | FR6: 1.59 | FS6: 117.81808 | FT6: 15.78 | FU6: 177.7641 | FV6: 73.07 | FW6: 110.53 | FX6: 8.8100004 | FY6: 12.1 | FZ6: 2.246721 | GA6: 82.400002 | GB6: 202.37 | GC6: 26.200001 | GD6: 177.57001 | GE6: 159.12701 | GF6: 196.84268 | GG6: 40.529999 | GH6: 21.16 | GI6: 26.76 | GJ6: 16.32 | GK6: 593.80096 | GL6: 20.145 | GM6: 13.422461 | GN6: 135.06 | GO6: 240.11 | GP6: 8.8299999 | GQ6: 10.37 | GR6: 195.02684 | GS6: 31.18 | GT6: 3.1900001 | GU6: 17.690001 | GV6: 46.259998 | GW6: 99.599998 | GX6: 92.57 | GY6: 150.26942 | GZ6: 160.96089 | HA6: 4.7199998 | HB6: 15.98 | HC6: 81.314919 | HD6: 94.255302 | HE6: 33.669998 | HF6: 7.0300002 | HG6: 70.76725 | HH6: 62.970001 | HI6: 8.2700005 | HJ6: 27.98 | HK6: 29.780001 | HL6: 15.94 | HM6: 654.7561 | HN6: 11.62 | HO6: 41.745972 | HP6: 47.029999 | HQ6: 5.4000001 | HR6: 1.6799999 | HS6: 16.972643 | HT6: 39.41 | HU6: 8.1599998 | HV6: 44.08609 | HW6: 28.283867 | HX6: 23.012894 | HY6: 232.55721 | HZ6: 107.66358 | IA6: 440.39999 | IB6: 47.139999 | IC6: 102.34 | ID6: 97.910004 | IE6: 98.449997 | IF6: 39.744701 | IG6: 108.62402 | IH6: 5.2150002 | II6: 73 | IJ6: 17.325001 | IK6: 4.23 | IL6: 4.79 | IM6: 171.98361 | IN6: 10.991814 | IO6: 12.6 | IP6: 40.821526 | IQ6: 19.51 | IR6: 83.195786 | IS6: 32.455822 | IT6: 102.2987 | IU6: 2.3499999 | IV6: 13.798178 | IW6: 10.83 | IX6: 44.985764 | IY6: 138.87039 | IZ6: 133.78302 | JA6: 55.860001 | JB6: 22.790001 | JC6: 73.669998 | JD6: 31.48 | JE6: 149.79112 | JF6: 55.835762 | JG6: 84.510002 | JH6: 25 | JI6: 140.79588
A7: 2025-09-29 | B7: 33.584782 | D7: 11.38 | E7: 25.940001 | F7: 61.710598 | G7: 253.49361 | H7: 34.658859 | I7: 122.92 | J7: 130.10281 | K7: 21.32 | L7: 9.6499996 | M7: 58.5979 | N7: 16.779287 | O7: 109.06975 | P7: 76.559998 | Q7: 12.385688 | R7: 106.78281 | S7: 2.9000001 | T7: 76.230003 | U7: 9.6199999 | V7: 161.36 | W7: 238.69833 | X7: 22.26 | Y7: 28.322582 | Z7: 60.84 | AA7: 222.17 | AB7: 143.37 | AC7: 16.52 | AD7: 4.0100002 | AE7: 60.178642 | AF7: 5.9400001 | AG7: 25.92 | AH7: 35.299999 | AI7: 12.374511 | AJ7: 11.019152 | AK7: 14.75 | AL7: 17.26 | AM7: 51.325935 | AN7: 16.262943 | AO7: 71.834251 | AP7: 23.91 | AQ7: 19.842787 | AR7: 9.5126009 | AS7: 25.120001 | AT7: 51.74358 | AU7: 42.127926 | AV7: 48.309483 | AW7: 2.6199999 | AX7: 17.309999 | AY7: 101.02288 | AZ7: 152.97903 | BA7: 12.756683 | BB7: 91.47921 | BC7: 84.295868 | BD7: 28.935022 | BE7: 29.459999 | BF7: 88.674805 | BG7: 14.87 | BH7: 36.11845 | BI7: 28.149002 | BJ7: 262.06839 | BK7: 107.97 | BL7: 333.98999 | BM7: 8.2200003 | BN7: 92.920532 | BO7: 911.55151 | BP7: 2.4504192 | BQ7: 146.00999 | BR7: 6.5 | BS7: 12.04 | BT7: 66.346214 | BU7: 44.658947 | BV7: 35.375282 | BW7: 78.531998 | BX7: 73.245201 | BY7: 530.09058 | BZ7: 57.036018 | CA7: 272.5 | CB7: 10.9 | CC7: 145.25999 | CD7: 132.21518 | CE7: 100.89111 | CF7: 18.450256 | CG7: 50.822163 | CH7: 113.14169 | CI7: 16.91 | CJ7: 165.37372 | CK7: 3.8 | CL7: 82.139999 | CM7: 6.0735869 | CN7: 21.813387 | CO7: 78.820244 | CP7: 8.6300001 | CQ7: 118.63644 | CR7: 58.510468 | CS7: 90.022736 | CT7: 16.16 | CU7: 22.48 | CV7: 74.339996 | CW7: 29.658512 | CX7: 11.551432 | CY7: 32.09 | CZ7: 42.639999 | DA7: 4.8600001 | DB7: 8.6800003 | DC7: 84.650002 | DD7: 170.90904 | DE7: 75.174034 | DF7: 292.50333 | DG7: 352.45999 | DH7: 34.290001 | DI7: 60.597202 | DJ7: 243.72375 | DK7: 243.41695 | DL7: 23.25 | DM7: 19.469999 | DN7: 129.92125 | DO7: 59.119999 | DP7: 136.72 | DQ7: 191.52126 | DR7: 72.160004 | DS7: 40.900002 | DT7: 272.71036 | DU7: 91.870003 | DV7: 3.23 | DW7: 11.4 | DX7: 14.81 | DY7: 34.48 | DZ7: 64.260002 | EA7: 16.92901 | EB7: 97.083427 | EC7: 47.599998 | ED7: 239.18982 | EE7: 107.53008 | EF7: 177.61726 | EG7: 15.24 | EH7: 14.344906 | EI7: 64.329865 | EJ7: 64.957596 | EK7: 0.72000003 | EL7: 22.69537 | EM7: 6.96 | EN7: 54.369999 | EO7: 233.16508 | EP7: 248.22066 | EQ7: 22.799999 | ER7: 130.6259 | ES7: 4.0999999 | ET7: 10.26 | EU7: 17.545992 | EV7: 564.62158 | EW7: 1.6 | EX7: 18.66 | EY7: 74.60627 | EZ7: 62.434696 | FA7: 91.701248 | FB7: 741.47156 | FC7: 61.510017 | FD7: 7.1214585 | FE7: 33.470676 | FF7: 76.338409 | FG7: 25.33 | FH7: 82.214836 | FI7: 157.58759 | FJ7: 510.40054 | FK7: 326.42001 | FL7: 10.28 | FM7: 74.080986 | FN7: 83.754448 | FO7: 4.9487977 | FP7: 120.641 | FQ7: 8.4799995 | FR7: 1.59 | FS7: 116.53062 | FT7: 15.95 | FU7: 181.41537 | FV7: 76.129997 | FW7: 116.51 | FX7: 8.1999998 | FY7: 11.91 | FZ7: 2.5170732 | GA7: 82.910004 | GB7: 203.96001 | GC7: 26.139999 | GD7: 178.86 | GE7: 157.29343 | GF7: 195.41953 | GG7: 40.220001 | GH7: 20.6 | GI7: 25.309999 | GJ7: 16.190001 | GK7: 596.55096 | GL7: 18.85 | GM7: 12.840409 | GN7: 141.56 | GO7: 241.98 | GP7: 8.9300003 | GQ7: 10.74 | GR7: 196.80151 | GS7: 29.65 | GT7: 3.1099999 | GU7: 19.780001 | GV7: 47.009998 | GW7: 100.08 | GX7: 91.5 | GY7: 150.6066 | GZ7: 161.23679 | HA7: 4.9099998 | HB7: 16.35 | HC7: 83.508934 | HD7: 95.667244 | HE7: 31.219999 | HF7: 6.8000002 | HG7: 69.851311 | HH7: 61.98 | HI7: 8.3999996 | HJ7: 27.549999 | HK7: 29.1 | HL7: 15.68 | HM7: 656.59625 | HN7: 11.31 | HO7: 41.109303 | HP7: 47.599998 | HQ7: 5.3499999 | HR7: 1.58 | HS7: 17.012207 | HT7: 38.349998 | HU7: 8.1999998 | HV7: 43.976398 | HW7: 28.622597 | HX7: 23.110283 | HY7: 233.03708 | HZ7: 110.04294 | IA7: 443.20999 | IB7: 49.639999 | IC7: 104.29 | ID7: 98.639999 | IE7: 99.57 | IF7: 40.290623 | IG7: 109.51748 | IH7: 5.6199999 | II7: 72.25 | IJ7: 17.540001 | IK7: 4.2800002 | IL7: 4.5900002 | IM7: 168.56607 | IN7: 11.039854 | IO7: 12.87 | IP7: 40.484547 | IQ7: 18.860001 | IR7: 82.84346 | IS7: 32.933399 | IT7: 102.21936 | IU7: 2.28 | IV7: 13.778326 | IW7: 11.6 | IX7: 44.159309 | IY7: 139.61246 | IZ7: 134.17793 | JA7: 55.91 | JB7: 23.190001 | JC7: 75.389999 | JD7: 31.370001 | JE7: 151.00751 | JF7: 55.311756 | JG7: 83.599998 | JH7: 27.5 | JI7: 140.3642
A8: 2025-09-30 | B8: 32.632305 | D8: 11.24 | E8: 25.93 | F8: 60.191113 | G8: 253.69289 | H8: 34.969948 | I8: 121.42 | J8: 130.91409 | K8: 21.34 | L8: 9.5799999 | M8: 58.044083 | N8: 16.652761 | O8: 109.41257 | P8: 73.080002 | Q8: 12.265923 | R8: 105.9614 | S8: 2.9100001 | T8: 75.760002 | U8: 9.8000002 | V8: 161.78999 | W8: 238.39838 | X8: 22.68 | Y8: 28.203413 | Z8: 59.389999 | AA8: 219.57001 | AB8: 145.71001 | AC8: 16.26 | AD8: 4.02 | AE8: 61.541256 | AF8: 6.4000001 | AG8: 26.1 | AH8: 38.75 | AI8: 12.60226 | AJ8: 10.97955 | AK8: 14.54 | AL8: 17.84 | AM8: 50.51326 | AN8: 16.145872 | AO8: 71.796272 | AP8: 24.27 | AQ8: 18.654774 | AR8: 9.3836498 | AS8: 25.07 | AT8: 51.734192 | AU8: 43.034409 | AV8: 48.583351 | AW8: 2.5599999 | AX8: 17.09 | AY8: 99.397263 | AZ8: 155.34442 | BA8: 12.746907 | BB8: 91.764519 | BC8: 83.697037 | BD8: 28.452774 | BE8: 29.370001 | BF8: 87.881233 | BG8: 14.5 | BH8: 35.792259 | BI8: 28.08643 | BJ8: 260.095 | BK8: 107.72 | BL8: 337.48999 | BM8: 8.0299997 | BN8: 91.699043 | BO8: 920.26068 | BP8: 2.4194012 | BQ8: 145.61 | BR8: 6.2199998 | BS8: 12.46 | BT8: 67.032005 | BU8: 44.084877 | BV8: 35.059345 | BW8: 75.447998 | BX8: 73.070747 | BY8: 542.33698 | BZ8: 56.135868 | CA8: 271.98999 | CB8: 10.75 | CC8: 142.39999 | CD8: 139.98616 | CE8: 101.29295 | CF8: 18.613449 | CG8: 50.686584 | CH8: 112.86568 | CI8: 16.42 | CJ8: 168.06659 | CK8: 3.72 | CL8: 72.089996 | CM8: 5.9395494 | CN8: 21.851507 | CO8: 79.908096 | CP8: 8.6300001 | CQ8: 119.55422 | CR8: 58.678974 | CS8: 89.805511 | CT8: 15.56 | CU8: 21.73 | CV8: 66.389999 | CW8: 29.668083 | CX8: 11.427223 | CY8: 33.91 | CZ8: 42.07 | DA8: 4.5999999 | DB8: 8.96 | DC8: 84.080002 | DD8: 171.16495 | DE8: 75.849129 | DF8: 299.66577 | DG8: 355.47 | DH8: 33.810001 | DI8: 60.448483 | DJ8: 242.91586 | DK8: 242.46942 | DL8: 23.35 | DM8: 18.459999 | DN8: 131.04117 | DO8: 56.720001 | DP8: 143.17999 | DQ8: 195.82231 | DR8: 72.769997 | DS8: 40.52 | DT8: 275.01059 | DU8: 94.970001 | DV8: 3.3199999 | DW8: 10.2 | DX8: 14.97 | DY8: 33.549999 | DZ8: 61.5 | EA8: 17.10535 | EB8: 98.621681 | EC8: 51.599998 | ED8: 239.52643 | EE8: 109.30964 | EF8: 181.33351 | EG8: 14.92 | EH8: 14.512741 | EI8: 64.602615 | EJ8: 65.915871 | EK8: 0.73199999 | EL8: 22.705114 | EM8: 6.9000001 | EN8: 53.529999 | EO8: 232.68976 | EP8: 246.25111 | EQ8: 22.74 | ER8: 133.42595 | ES8: 4.1500001 | ET8: 10.52 | EU8: 17.314236 | EV8: 565.28735 | EW8: 1.54 | EX8: 18.26 | EY8: 73.993118 | EZ8: 62.580872 | FA8: 92.940575 | FB8: 732.47498 | FC8: 61.875305 | FD8: 7.0832739 | FE8: 33.451385 | FF8: 81.535789 | FG8: 25.83 | FH8: 83.891258 | FI8: 155.43636 | FJ8: 513.72327 | FK8: 322.20999 | FL8: 10.63 | FM8: 73.381104 | FN8: 83.526588 | FO8: 4.9388995 | FP8: 119.892 | FQ8: 8.8000002 | FR8: 1.5700001 | FS8: 116.42251 | FT8: 16.01 | FU8: 186.13406 | FV8: 73.989998 | FW8: 111.63 | FX8: 7.9699998 | FY8: 11.33 | FZ8: 2.4611382 | GA8: 83.809998 | GB8: 203.62 | GC8: 26.280001 | GD8: 182.42 | GE8: 156.53102 | GF8: 194.52882 | GG8: 40.720001 | GH8: 20.23 | GI8: 24.709999 | GJ8: 16.4 | GK8: 598.18506 | GL8: 18.41 | GM8: 12.787495 | GN8: 138.52 | GO8: 229.99001 | GP8: 8.9899998 | GQ8: 10.63 | GR8: 198.86372 | GS8: 29.790001 | GT8: 3.1199999 | GU8: 19.030001 | GV8: 47.91 | GW8: 100.13 | GX8: 89.510002 | GY8: 151.13223 | GZ8: 164.88268 | HA8: 4.8800001 | HB8: 16.280001 | HC8: 82.494812 | HD8: 94.265167 | HE8: 30.870001 | HF8: 6.4099998 | HG8: 68.964317 | HH8: 71.449997 | HI8: 7.71 | HJ8: 26.42 | HK8: 28.790001 | HL8: 16.08 | HM8: 659.06952 | HN8: 11.2 | HO8: 40.952587 | HP8: 47.790001 | HQ8: 4.9499998 | HR8: 1.66 | HS8: 17.081442 | HT8: 37.970001 | HU8: 7.73 | HV8: 44.369453 | HW8: 28.831812 | HX8: 22.730467 | HY8: 234.4277 | HZ8: 111.78056 | IA8: 444.72 | IB8: 49.009998 | IC8: 100.09 | ID8: 96.5 | IE8: 97.970001 | IF8: 39.968918 | IG8: 110.67896 | IH8: 5.77 | II8: 71.43 | IJ8: 17.190001 | IK8: 3.99 | IL8: 4.8899999 | IM8: 166.72508 | IN8: 11.145545 | IO8: 12.55 | IP8: 41.139786 | IQ8: 19.530001 | IR8: 82.031174 | IS8: 33.196552 | IT8: 102.19952 | IU8: 2.1700001 | IV8: 13.798178 | IW8: 11.42 | IX8: 43.689838 | IY8: 140.37444 | IZ8: 137.40651 | JA8: 54.470001 | JB8: 23.42 | JC8: 72.269997 | JD8: 31.200001 | JE8: 149.10448 | JF8: 54.904198 | JG8: 82.5 | JH8: 24.5 | JI8: 143.56276
A9: 2025-10-01 | B9: 33.584782 | D9: 11.27 | E9: 28.42 | F9: 60.681267 | G9: 254.50984 | H9: 34.091579 | I9: 122.32 | J9: 130.45471 | K9: 21.24 | L9: 9.8100004 | M9: 57.567993 | N9: 16.526237 | O9: 108.48204 | P9: 74.419998 | Q9: 12.235982 | R9: 103.78419 | S9: 2.9400001 | T9: 75.839996 | U9: 10.29 | V9: 164.00999 | W9: 230.97935 | X9: 24.57 | Y9: 29.266006 | Z9: 59.169998 | AA9: 220.63 | AB9: 149.27 | AC9: 15.84 | AD9: 4.0700002 | AE9: 61.993805 | AF9: 6.5300002 | AG9: 25.02 | AH9: 41.200001 | AI9: 13.007154 | AJ9: 11.019152 | AK9: 13.97 | AL9: 17.870001 | AM9: 49.622253 | AN9: 16.204407 | AO9: 73.438797 | AP9: 24.129999 | AQ9: 18.949322 | AR9: 9.1852646 | AS9: 25.459999 | AT9: 54.523773 | AU9: 45.257698 | AV9: 48.583351 | AW9: 2.5699999 | AX9: 18 | AY9: 96.66507 | AZ9: 156.81496 | BA9: 12.952188 | BB9: 91.022713 | BC9: 83.327751 | BD9: 27.911472 | BE9: 28.83 | BF9: 84.677536 | BG9: 14.59 | BH9: 36.88945 | BI9: 27.95092 | BJ9: 255.90752 | BK9: 114.65 | BL9: 346.17001 | BM9: 7.6300001 | BN9: 92.542458 | BO9: 912.0188 | BP9: 2.4194012 | BQ9: 144.91 | BR9: 7.0900002 | BS9: 12.7 | BT9: 67.355309 | BU9: 43.916611 | BV9: 34.555817 | BW9: 79.082001 | BX9: 74.505211 | BY9: 541.72766 | BZ9: 55.5028 | CA9: 267.64001 | CB9: 10.75 | CC9: 152.7 | CD9: 147.79662 | CE9: 97.695999 | CF9: 18.479057 | CG9: 50.347641 | CH9: 111.33781 | CI9: 16.620001 | CJ9: 166.67639 | CK9: 3.52 | CL9: 68.970001 | CM9: 5.7636247 | CN9: 21.96586 | CO9: 79.148453 | CP9: 8.3500004 | CQ9: 118.24033 | CR9: 58.688885 | CS9: 86.477928 | CT9: 15.01 | CU9: 20.26 | CV9: 70.489998 | CW9: 29.26613 | CX9: 11.723413 | CY9: 34.25 | CZ9: 42.860001 | DA9: 4.5500002 | DB9: 8.8900003 | DC9: 85.18 | DD9: 173.64516 | DE9: 76.57386 | DF9: 299.72552 | DG9: 356.03 | DH9: 35.830002 | DI9: 60.815319 | DJ9: 244.90068 | DK9: 244.26474 | DL9: 22.290001 | DM9: 18.549999 | DN9: 130.55978 | DO9: 56.310001 | DP9: 139.14 | DQ9: 194.44518 | DR9: 72.879997 | DS9: 40.73 | DT9: 279.23087 | DU9: 102.26 | DV9: 3.29 | DW9: 10.4 | DX9: 15.76 | DY9: 35.939999 | DZ9: 63.09 | EA9: 17.281694 | EB9: 98.931267 | EC9: 49.200001 | ED9: 240.0511 | EE9: 108.25582 | EF9: 181.94963 | EG9: 15.09 | EH9: 14.295543 | EI9: 65.050697 | EJ9: 65.03582 | EK9: 0.76999998 | EL9: 23.777029 | EM9: 6.7800002 | EN9: 52.41 | EO9: 229.84773 | EP9: 242.99796 | EQ9: 22.049999 | ER9: 142.28448 | ES9: 4.1799998 | ET9: 10.61 | EU9: 17.343204 | EV9: 570.21674 | EW9: 1.66 | EX9: 18.610001 | EY9: 73.528313 | EZ9: 62.473679 | FA9: 92.520966 | FB9: 715.47913 | FC9: 62.09074 | FD9: 7.1310043 | FE9: 32.621853 | FF9: 87.558929 | FG9: 27.6 | FH9: 83.711647 | FI9: 153.41225 | FJ9: 515.46887 | FK9: 338.41 | FL9: 10.62 | FM9: 76.472267 | FN9: 85.151344 | FO9: 4.9487977 | FP9: 117.09 | FQ9: 10.12 | FR9: 1.53 | FS9: 116.46181 | FT9: 15.19 | FU9: 186.79248 | FV9: 75.620003 | FW9: 115.93 | FX9: 8.0600004 | FY9: 11.2 | FZ9: 2.3772357 | GA9: 85.690002 | GB9: 206.8 | GC9: 27.07 | GD9: 184.95 | GE9: 155.23785 | GF9: 192.11816 | GG9: 41.240002 | GH9: 20.67 | GI9: 25.629999 | GJ9: 16.530001 | GK9: 601.0545 | GL9: 18.969999 | GM9: 13.157892 | GN9: 134.07001 | GO9: 202.60001 | GP9: 9.1599998 | GQ9: 10.64 | GR9: 198.37791 | GS9: 29.85 | GT9: 3.23 | GU9: 18.93 | GV9: 47.970001 | GW9: 103.57 | GX9: 88.040001 | GY9: 151.93555 | GZ9: 164.75458 | HA9: 5.0999999 | HB9: 16.299999 | HC9: 82.299789 | HD9: 91.085815 | HE9: 31.024 | HF9: 6.8299999 | HG9: 69.832031 | HH9: 71.68 | HI9: 7.71 | HJ9: 25.76 | HK9: 28.74 | HL9: 16.15 | HM9: 661.31537 | HN9: 11.08 | HO9: 40.41386 | HP9: 48.040001 | HQ9: 4.6900001 | HR9: 1.7 | HS9: 17.140787 | HT9: 37.380001 | HU9: 7.8000002 | HV9: 43.555927 | HW9: 28.463194 | HX9: 22.516214 | HY9: 228.43431 | HZ9: 112.3828 | IA9: 459.45999 | IB9: 49.32 | IC9: 102.7 | ID9: 93.150002 | IE9: 96.610001 | IF9: 39.403503 | IG9: 111.88016 | IH9: 6.5300002 | II9: 73 | IJ9: 18.41 | IK9: 4.7800002 | IL9: 4.5700002 | IM9: 164.18887 | IN9: 11.078287 | IO9: 12.55 | IP9: 41.027458 | IQ9: 19.35 | IR9: 79.144127 | IS9: 33.37199 | IT9: 101.1087 | IU9: 2.3399999 | IV9: 13.470594 | IW9: 11.47 | IX9: 43.689838 | IY9: 141.74899 | IZ9: 141.65204 | JA9: 52.439999 | JB9: 23.700001 | JC9: 73.400002 | JD9: 31.459999 | JE9: 150.27179 | JF9: 54.807156 | JG9: 81.279999 | JH9: 22.424999 | JI9: 144.18089
A10: 2025-10-02 | B10: 34.557106 | D10: 11.43 | E10: 27.98 | F10: 60.916542 | G10: 256.18365 | H10: 34.375217 | I10: 121.49 | J10: 129.98557 | K10: 21.379999 | L10: 10.18 | M10: 57.431965 | N10: 16.497036 | O10: 108.33511 | P10: 77.43 | Q10: 12.036374 | R10: 106.30779 | S10: 3.03 | T10: 78.010002 | U10: 10.24 | V10: 169.73 | W10: 236.51863 | X10: 24.57 | Y10: 29.434832 | Z10: 59.25 | AA10: 222.41 | AB10: 144.46001 | AC10: 15.85 | AD10: 4.4099998 | AE10: 61.456715 | AF10: 6.4299998 | AG10: 26.1 | AH10: 48.59 | AI10: 13.091506 | AJ10: 11.038952 | AK10: 13.76 | AL10: 17.879999 | AM10: 49.42643 | AN10: 16.506838 | AO10: 72.745712 | AP10: 25.59 | AQ10: 18.605682 | AR10: 9.1654263 | AS10: 26.5 | AT10: 57.78299 | AU10: 43.635555 | AV10: 48.583351 | AW10: 2.6400001 | AX10: 17.610001 | AY10: 95.323448 | AZ10: 157.34123 | BA10: 13.225894 | BB10: 90.784958 | BC10: 84.036369 | BD10: 28.393723 | BE10: 28.43 | BF10: 88.018387 | BG10: 15.14 | BH10: 35.881218 | BI10: 27.463091 | BJ10: 255.5128 | BK10: 112.79 | BL10: 372.07001 | BM10: 7.5500002 | BN10: 90.526024 | BO10: 911.45209 | BP10: 2.512455 | BQ10: 149.63 | BR10: 8.1000004 | BS10: 13.3 | BT10: 66.924232 | BU10: 46.430656 | BV10: 35.118584 | BW10: 78.942001 | BX10: 75.06736 | BY10: 536.17383 | BZ10: 56.462303 | CA10: 270.09 | CB10: 10.65 | CC10: 151.57001 | CD10: 145.51569 | CE10: 99.38176 | CF10: 18.431061 | CG10: 50.202377 | CH10: 110.53938 | CI10: 17.200001 | CJ10: 168.91235 | CK10: 3.95 | CL10: 68.099998 | CM10: 5.6212096 | CN10: 22.575758 | CO10: 79.96653 | CP10: 8.3800001 | CQ10: 117.44814 | CR10: 58.74836 | CS10: 87.287598 | CT10: 15.62 | CU10: 19.799999 | CV10: 72.540001 | CW10: 28.940737 | CX10: 11.67564 | CY10: 35.689999 | CZ10: 43.470001 | DA10: 4.5799999 | DB10: 8.8900003 | DC10: 86.290001 | DD10: 163.62584 | DE10: 76.544075 | DF10: 298.30103 | DG10: 354.79001 | DH10: 36.52 | DI10: 58.852253 | DJ10: 245.78836 | DK10: 245.0527 | DL10: 22.5 | DM10: 18.709999 | DN10: 130.59911 | DO10: 57.869999 | DP10: 145.7 | DQ10: 190.68303 | DR10: 72.650002 | DS10: 39.509998 | DT10: 279.45505 | DU10: 99.300003 | DV10: 3.3399999 | DW10: 10.8 | DX10: 16.5 | DY10: 37.299999 | DZ10: 69.599998 | EA10: 18.261383 | EB10: 99.937416 | EC10: 51.200001 | ED10: 241.5657 | EE10: 108.02716 | EF10: 181.88118 | EG10: 15.61 | EH10: 14.611467 | EI10: 64.388306 | EJ10: 64.889137 | EK10: 0.78899997 | EL10: 23.757542 | EM10: 6.5100002 | EN10: 53.299999 | EO10: 229.53085 | EP10: 242.35123 | EQ10: 21.9 | ER10: 146.46962 | ES10: 4.25 | ET10: 11.22 | EU10: 17.565304 | EV10: 573.75464 | EW10: 1.8 | EX10: 18.790001 | EY10: 73.033836 | EZ10: 64.442116 | FA10: 93.174797 | FB10: 725.16394 | FC10: 61.584949 | FD10: 7.2169204 | FE10: 33.528553 | FF10: 86.956619 | FG10: 28.370001 | FH10: 86.016739 | FI10: 151.85748 | FJ10: 511.53125 | FK10: 352.32999 | FL10: 10.33 | FM10: 75.995964 | FN10: 85.626877 | FO10: 4.9586954 | FP10: 116.253 | FQ10: 9.6499996 | FR10: 1.5700001 | FS10: 118.00481 | FT10: 15.22 | FU10: 188.43854 | FV10: 79.360001 | FW10: 128.8 | FX10: 8.0100002 | FY10: 10.73 | FZ10: 2.3399458 | GA10: 88.25 | GB10: 209.3 | GC10: 27.459999 | GD10: 187.05 | GE10: 152.39096 | GF10: 191.84708 | GG10: 40.919998 | GH10: 21.01 | GI10: 29.209999 | GJ10: 18.1 | GK10: 603.52545 | GL10: 19.98 | GM10: 13.157892 | GN10: 133.5 | GO10: 200.92 | GP10: 10.36 | GQ10: 11.17 | GR10: 197.327 | GS10: 35.400002 | GT10: 3.3 | GU10: 19.25 | GV10: 52.470001 | GW10: 103.84 | GX10: 90.970001 | GY10: 154.88101 | GZ10: 164.19292 | HA10: 5.52 | HB10: 16.209999 | HC10: 84.562057 | HD10: 91.530128 | HE10: 31.219999 | HF10: 6.79 | HG10: 69.195702 | HH10: 72.93 | HI10: 8.2200003 | HJ10: 25.969999 | HK10: 28.08 | HL10: 17.84 | HM10: 662.07703 | HN10: 11.58 | HO10: 40.266937 | HP10: 47.959999 | HQ10: 4.9899998 | HR10: 1.72 | HS10: 17.150677 | HT10: 36.799999 | HU10: 8.4799995 | HV10: 43.610767 | HW10: 27.945139 | HX10: 22.350653 | HY10: 225.37886 | HZ10: 114.0908 | IA10: 436 | IB10: 50.880001 | IC10: 105.42 | ID10: 94.830002 | IE10: 96.610001 | IF10: 39.325516 | IG10: 112.18791 | IH10: 7.29 | II10: 73.129997 | IJ10: 22.709999 | IK10: 4.5999999 | IL10: 4.5900002 | IM10: 161.28053 | IN10: 10.972597 | IO10: 12.6 | IP10: 40.624954 | IQ10: 19.24 | IR10: 78.782028 | IS10: 33.323254 | IT10: 100.85087 | IU10: 2.6900001 | IV10: 13.24228 | IW10: 11.58 | IX10: 43.249718 | IY10: 142.51596 | IZ10: 141.37556 | JA10: 50.259998 | JB10: 23.809999 | JC10: 76.809998 | JD10: 31.719999 | JE10: 148.46684 | JF10: 54.719822 | JG10: 82.239998 | JH10: 24.6 | JI10: 143.72955
A11: 2025-10-03 | B11: 34.229691 | D11: 11.58 | E11: 27.93 | F11: 60.13229 | G11: 257.07037 | H11: 35.152935 | I11: 120.22 | J11: 131.54941 | K11: 21.799999 | L11: 11.57 | M11: 59.307178 | N11: 16.487305 | O11: 110.01988 | P11: 74.830002 | Q11: 12.086275 | R11: 107.51514 | S11: 2.95 | T11: 77.559998 | U11: 10.07 | V11: 164.67 | W11: 243.00777 | X11: 23.940001 | Y11: 29.17663 | Z11: 59.299999 | AA11: 219.50999 | AB11: 145.5 | AC11: 16.32 | AD11: 6.8899999 | AE11: 60.78038 | AF11: 6.3299999 | AG11: 25.74 | AH11: 49.919998 | AI11: 13.066197 | AJ11: 10.969649 | AK11: 13.96 | AL11: 17.879999 | AM11: 49.583088 | AN11: 16.682442 | AO11: 72.973572 | AP11: 25.75 | AQ11: 18.360226 | AR11: 9.1356688 | AS11: 26.91 | AT11: 59.501831 | AU11: 43.964443 | AV11: 48.260571 | AW11: 2.53 | AX11: 19.42 | AY11: 95.715157 | AZ11: 153.36946 | BA11: 13.978587 | BB11: 90.775444 | BC11: 84.006432 | BD11: 28.118149 | BE11: 27.809999 | BF11: 88.263321 | BG11: 15.94 | BH11: 36.474297 | BI11: 27.914785 | BJ11: 254.78123 | BK11: 113.58 | BL11: 380.01999 | BM11: 7.8299999 | BN11: 91.282196 | BO11: 910.07013 | BP11: 2.4271557 | BQ11: 143.87 | BR11: 7.98 | BS11: 12.55 | BT11: 66.943947 | BU11: 47.351151 | BV11: 35.553001 | BW11: 75.143997 | BX11: 75.106133 | BY11: 537.41241 | BZ11: 56.64035 | CA11: 271.22 | CB11: 11.1 | CC11: 151.82001 | CD11: 138.96912 | CE11: 98.215446 | CF11: 18.536654 | CG11: 50.057114 | CH11: 110.86466 | CI11: 17.34 | CJ11: 171.43999 | CK11: 3.79 | CL11: 69.730003 | CM11: 6.1070962 | CN11: 22.699644 | CO11: 80.171043 | CP11: 8.6899996 | CQ11: 119.35134 | CR11: 58.678974 | CS11: 91.010162 | CT11: 15.52 | CU11: 19.93 | CV11: 72.379997 | CW11: 29.026871 | CX11: 12.105596 | CY11: 34.91 | CZ11: 43.130001 | DA11: 4.5799999 | DB11: 8.9300003 | DC11: 85.790001 | DD11: 167.29697 | DE11: 76.524223 | DF11: 295.86041 | DG11: 357.64001 | DH11: 36.16 | DI11: 59.615673 | DJ11: 245.8083 | DK11: 244.71359 | DL11: 22.959999 | DM11: 18.41 | DN11: 131.10994 | DO11: 52.540001 | DP11: 148.67 | DQ11: 188.8568 | DR11: 73.220001 | DS11: 37.919998 | DT11: 281.0632 | DU11: 102.12 | DV11: 3.3499999 | DW11: 11.7 | DX11: 17.280001 | DY11: 36.830002 | DZ11: 73.279999 | EA11: 18.378944 | EB11: 101.38858 | EC11: 45.599998 | ED11: 243.3575 | EE11: 108.1564 | EF11: 184.48254 | EG11: 15.26 | EH11: 14.858282 | EI11: 64.924072 | EJ11: 64.830475 | EK11: 0.79100001 | EL11: 23.825754 | EM11: 6.5 | EN11: 54.52 | EO11: 230.01608 | EP11: 241.39098 | EQ11: 22.43 | ER11: 145.29379 | ES11: 4.2600002 | ET11: 11.44 | EU11: 17.584616 | EV11: 576.85535 | EW11: 1.73 | EX11: 18.82 | EY11: 73.666763 | EZ11: 64.841652 | FA11: 95.341187 | FB11: 708.71674 | FC11: 61.566219 | FD11: 7.1310043 | FE11: 33.306702 | FF11: 86.645744 | FG11: 28.49 | FH11: 86.036697 | FI11: 154.09671 | FJ11: 513.12811 | FK11: 351.63 | FL11: 10.29 | FM11: 77.823433 | FN11: 86.052887 | FO11: 4.9784904 | FP11: 115.332 | FQ11: 9.9899998 | FR11: 1.6 | FS11: 117.18555 | FT11: 15.31 | FU11: 187.17157 | FV11: 77.129997 | FW11: 127.36 | FX11: 8.1099997 | FY11: 10.84 | FZ11: 2.2746885 | GA11: 86.879997 | GB11: 207.19 | GC11: 27.75 | GD11: 173.07001 | GE11: 149.30301 | GF11: 192.13751 | GG11: 40.720001 | GH11: 21.84 | GI11: 32.700001 | GJ11: 18.450001 | GK11: 600.9848 | GL11: 24.620001 | GM11: 13.272538 | GN11: 122.69 | GO11: 207.2 | GP11: 10.73 | GQ11: 10.99 | GR11: 199.07588 | GS11: 40.060001 | GT11: 3.3699999 | GU11: 19.440001 | GV11: 56.16 | GW11: 103.85 | GX11: 86.760002 | GY11: 151.38016 | GZ11: 164.14365 | HA11: 5.4899998 | HB11: 16.6 | HC11: 84.269524 | HD11: 92.892715 | HE11: 29.889999 | HF11: 7.4899998 | HG11: 70.584053 | HH11: 72 | HI11: 8.54 | HJ11: 25.24 | HK11: 28.959999 | HL11: 17.85 | HM11: 662.0672 | HN11: 11.64 | HO11: 40.502014 | HP11: 48.349998 | HQ11: 4.9499998 | HR11: 1.75 | HS11: 17.160568 | HT11: 37.419998 | HU11: 9.0100002 | HV11: 44.012966 | HW11: 27.526707 | HX11: 22.301958 | HY11: 225.50616 | HZ11: 113.45894 | IA11: 429.82999 | IB11: 51.549999 | IC11: 102.94 | ID11: 95.330002 | IE11: 96.599998 | IF11: 40.066402 | IG11: 112.05885 | IH11: 7.4400001 | II11: 72.849998 | IJ11: 25.959999 | IK11: 4.7399998 | IL11: 4.6500001 | IM11: 157.06981 | IN11: 10.914948 | IO11: 12.77 | IP11: 40.877686 | IQ11: 18.99 | IR11: 78.948395 | IS11: 32.99675 | IT11: 101.2178 | IU11: 2.77 | IV11: 13.500376 | IW11: 11.92 | IX11: 43.479557 | IY11: 141.79881 | IZ11: 142.98492 | JA11: 51.52 | JB11: 23.07 | JC11: 76.949997 | JD11: 31.809999 | JE11: 147.81941 | JF11: 55.243828 | JG11: 80.959999 | JH11: 25.5 | JI11: 143.66089
A12: 2025-10-06 | B12: 33.525257 | D12: 11.83 | E12: 33.790001 | F12: 57.161953 | G12: 255.74527 | H12: 35.180386 | I12: 120.35 | J12: 130.71861 | K12: 21.59 | L12: 13.64 | M12: 60.677151 | N12: 15.338839 | O12: 110.75452 | P12: 75.860001 | Q12: 12.814845 | R12: 108.62355 | S12: 3.04 | T12: 78.440002 | U12: 10.22 | V12: 203.71001 | W12: 244.86752 | X12: 24.99 | Y12: 30.358393 | Z12: 60.98 | AA12: 220.89999 | AB12: 149.5 | AC12: 15.87 | AD12: 6.54 | AE12: 61.367199 | AF12: 6.54 | AG12: 25.379999 | AH12: 53.860001 | AI12: 13.040894 | AJ12: 11.276563 | AK12: 13.6 | AL12: 17.16 | AM12: 49.33831 | AN12: 17.375107 | AO12: 71.77729 | AP12: 25.889999 | AQ12: 18.625319 | AR12: 8.9174452 | AS12: 28.34 | AT12: 62.065994 | AU12: 43.664577 | AV12: 48.338818 | AW12: 2.55 | AX12: 20.889999 | AY12: 96.018745 | AZ12: 154.0943 | BA12: 13.616903 | BB12: 89.386948 | BC12: 85.144218 | BD12: 28.629927 | BE12: 27.85 | BF12: 90.193375 | BG12: 17.43 | BH12: 37.057491 | BI12: 28.086432 | BJ12: 252.25911 | BK12: 114.77 | BL12: 386.07001 | BM12: 7.6399999 | BN12: 92.009277 | BO12: 905.65588 | BP12: 2.3961377 | BQ12: 147.42 | BR12: 11.59 | BS12: 12.61 | BT12: 67.919731 | BU12: 46.786983 | BV12: 35.789951 | BW12: 73.919998 | BX12: 74.476135 | BY12: 553.44464 | BZ12: 57.629528 | CA12: 281.73999 | CB12: 10.8 | CC12: 157.36 | CD12: 143.92593 | CE12: 96.176842 | CF12: 18.680645 | CG12: 50.50259 | CH12: 111.14066 | CI12: 17.620001 | CJ12: 172.03299 | CK12: 3.71 | CL12: 72.169998 | CM12: 6.216002 | CN12: 22.318457 | CO12: 80.278168 | CP12: 8.6199999 | CQ12: 120.16286 | CR12: 58.956509 | CS12: 90.615189 | CT12: 15.52 | CU12: 20.73 | CV12: 70 | CW12: 29.007729 | CX12: 12.134258 | CY12: 38.27 | CZ12: 43.93 | DA12: 4.4099998 | DB12: 8.9700003 | DC12: 86.379997 | DD12: 170.35788 | DE12: 78.04319 | DF12: 297.07574 | DG12: 364.38 | DH12: 38.84 | DI12: 57.692265 | DJ12: 250.85513 | DK12: 249.78038 | DL12: 22.57 | DM12: 20.67 | DN12: 130.20613 | DO12: 54.759998 | DP12: 144.25999 | DQ12: 190.08426 | DR12: 74.620003 | DS12: 37.610001 | DT12: 282.08664 | DU12: 101.02 | DV12: 3.28 | DW12: 11.4 | DX12: 16.540001 | DY12: 36.59 | DZ12: 78.989998 | EA12: 19.613354 | EB12: 102.90749 | EC12: 44.400002 | ED12: 244.32764 | EE12: 108.9418 | EF12: 184.01312 | EG12: 15.32 | EH12: 14.117836 | EI12: 64.388306 | EJ12: 63.363724 | EK12: 0.82300001 | EL12: 23.679583 | EM12: 6.4299998 | EN12: 56.099998 | EO12: 230.98651 | EP12: 236.80518 | EQ12: 22.860001 | ER12: 148.62196 | ES12: 4.29 | ET12: 11.98 | EU12: 17.671528 | EV12: 575.22546 | EW12: 1.73 | EX12: 20.57 | EY12: 75.832565 | EZ12: 64.890373 | FA12: 96.053558 | FB12: 713.80353 | FC12: 61.229027 | FD12: 7.0641813 | FE12: 34.088005 | FF12: 86.266869 | FG12: 27.540001 | FH12: 88.730957 | FI12: 154.58563 | FJ12: 524.25659 | FK12: 359.69 | FL12: 10.43 | FM12: 79.81617 | FN12: 87.687553 | FO12: 5.0180807 | FP12: 116.331 | FQ12: 9.6599998 | FR12: 1.6799999 | FS12: 118.86357 | FT12: 15.38 | FU12: 185.09654 | FV12: 78.339996 | FW12: 138.56 | FX12: 9.2799997 | FY12: 10.51 | FZ12: 2.2840109 | GA12: 90.330002 | GB12: 212.58 | GC12: 29.299999 | GD12: 179.53 | GE12: 149.56601 | GF12: 189.388 | GG12: 38.52 | GH12: 23.58 | GI12: 35.02 | GJ12: 17.875 | GK12: 605.49829 | GL12: 22.16 | GM12: 13.016788 | GN12: 126.27 | GO12: 203.63 | GP12: 11.22 | GQ12: 10.185 | GR12: 202.28549 | GS12: 41.709999 | GT12: 3.4300001 | GU12: 21.559999 | GV12: 58.5 | GW12: 104.84 | GX12: 83.239998 | GY12: 151.0033 | GZ12: 166.33118 | HA12: 5.5300002 | HB12: 16.49 | HC12: 80.06678 | HD12: 92.813728 | HE12: 28.07 | HF12: 7.5700002 | HG12: 71.606033 | HH12: 68.169998 | HI12: 8.5200005 | HJ12: 26.360001 | HK12: 30.1 | HL12: 18.25 | HM12: 664.44153 | HN12: 11.88 | HO12: 40.678322 | HP12: 48.310001 | HQ12: 5.0500002 | HR12: 1.83 | HS12: 17.219913 | HT12: 38.450001 | HU12: 8.5699997 | HV12: 44.305473 | HW12: 27.128202 | HX12: 22.301958 | HY12: 220.30603 | HZ12: 114.02169 | IA12: 453.25 | IB12: 53.139999 | IC12: 109.7 | ID12: 97.07 | IE12: 100.1 | IF12: 40.007912 | IG12: 113.27991 | IH12: 7.6999998 | II12: 73.059998 | IJ12: 26.32 | IK12: 4.9899998 | IL12: 4.4699998 | IM12: 160.02711 | IN12: 10.847691 | IO12: 12.52 | IP12: 38.790276 | IQ12: 19.08 | IR12: 78.967972 | IS12: 32.796951 | IT12: 101.84253 | IU12: 2.8199999 | IV12: 13.758471 | IW12: 11.97 | IX12: 43.694729 | IY12: 143.23312 | IZ12: 142.29379 | JA12: 52.75 | JB12: 23.629999 | JC12: 77.779999 | JD12: 32.82 | JE12: 145.9458 | JF12: 55.185604 | JG12: 81.029999 | JH12: 24.549999 | JI12: 142.62085
A13: 2025-10-07 | B13: 35.251617 | D13: 11.66 | E13: 31.334999 | F13: 55.720894 | G13: 255.53607 | H13: 35.171234 | I13: 119.85 | J13: 130.01488 | K13: 21.540001 | L13: 12.48 | M13: 61.104664 | N13: 15.066321 | O13: 110.61739 | P13: 76.650002 | Q13: 12.66514 | R13: 109.23713 | S13: 2.98 | T13: 76.599998 | U13: 9.8400002 | V13: 211.50999 | W13: 239.91818 | X13: 24.045 | Y13: 29.544069 | Z13: 56.549999 | AA13: 221.78 | AB13: 145.28999 | AC13: 14.48 | AD13: 5.9400001 | AE13: 61.92915 | AF13: 7 | AG13: 31.68 | AH13: 55.23 | AI13: 13.150553 | AJ13: 11.266663 | AK13: 13.45 | AL13: 16.9 | AM13: 49.240395 | AN13: 17.179991 | AO13: 71.425995 | AP13: 25.129999 | AQ13: 18.046038 | AR13: 9.0959911 | AS13: 28.16 | AT13: 58.224442 | AU13: 43.20026 | AV13: 47.615013 | AW13: 2.5 | AX13: 20.610001 | AY13: 95.773926 | AZ13: 155.54401 | BA13: 12.756683 | BB13: 90.480629 | BC13: 86.281998 | BD13: 28.255936 | BE13: 26.58 | BF13: 90.105202 | BG13: 17.959999 | BH13: 36.128334 | BI13: 27.643766 | BJ13: 253.75121 | BK13: 113.56 | BL13: 375.78 | BM13: 7.4099998 | BN13: 92.319496 | BO13: 909.49353 | BP13: 2.7605987 | BQ13: 137.2 | BR13: 10.02 | BS13: 12.22 | BT13: 67.998573 | BU13: 45.401283 | BV13: 35.53326 | BW13: 74.061996 | BX13: 74.74752 | BY13: 539.77979 | BZ13: 56.017174 | CA13: 276.78 | CB13: 10.8 | CC13: 154.52 | CD13: 148.97165 | CE13: 95.023201 | CF13: 18.882236 | CG13: 50.337955 | CH13: 110.92381 | CI13: 17.02 | CJ13: 170.26366 | CK13: 17.92 | CL13: 69.940002 | CM13: 5.470417 | CN13: 21.441729 | CO13: 80.26844 | CP13: 8.4700003 | CQ13: 121.30286 | CR13: 58.70871 | CS13: 91.869225 | CT13: 15.38 | CU13: 21.15 | CV13: 71.440002 | CW13: 28.404797 | CX13: 11.389005 | CY13: 36.299999 | CZ13: 42.919998 | DA13: 4.4000001 | DB13: 8.7799997 | DC13: 84.919998 | DD13: 168.23196 | DE13: 76.415016 | DF13: 300.58218 | DG13: 366.26001 | DH13: 39.580002 | DI13: 56.770218 | DJ13: 246.48654 | DK13: 245.12251 | DL13: 22.690001 | DM13: 19.99 | DN13: 131.45377 | DO13: 57.970001 | DP13: 145 | DQ13: 191.06223 | DR13: 75.010002 | DS13: 37.290001 | DT13: 286.42386 | DU13: 96.68 | DV13: 3.6800001 | DW13: 10.9 | DX13: 15.45 | DY13: 37.169998 | DZ13: 79.230003 | EA13: 19.025539 | EB13: 102.44309 | EC13: 38.68 | ED13: 241.70428 | EE13: 107.67919 | EF13: 184.72704 | EG13: 14.73 | EH13: 14.226435 | EI13: 65.06044 | EJ13: 65.397614 | EK13: 0.81199998 | EL13: 23.845242 | EM13: 6.1999998 | EN13: 55.060001 | EO13: 233.04625 | EP13: 235.061 | EQ13: 24.030001 | ER13: 139.85313 | ES13: 4.29 | ET13: 11.79 | EU13: 17.159729 | EV13: 576.24902 | EW13: 1.79 | EX13: 20.25 | EY13: 75.120506 | EZ13: 63.301983 | FA13: 95.955971 | FB13: 711.23022 | FC13: 62.427937 | FD13: 6.9114423 | FE13: 34.155525 | FF13: 85.110809 | FG13: 27.34 | FH13: 86.785095 | FI13: 152.51262 | FJ13: 519.70398 | FK13: 328.39999 | FL13: 10.72 | FM13: 80.885437 | FN13: 86.142044 | FO13: 5.0576711 | FP13: 119.106 | FQ13: 10.07 | FR13: 1.6900001 | FS13: 116.46498 | FT13: 15.13 | FU13: 184.59773 | FV13: 77.550003 | FW13: 134.12 | FX13: 9.29 | FY13: 10.13 | FZ13: 2.3119783 | GA13: 87.900002 | GB13: 211.03999 | GC13: 27 | GD13: 182.17 | GE13: 150.5499 | GF13: 187.63565 | GG13: 38.560001 | GH13: 23.6 | GI13: 35.720001 | GJ13: 17.18 | GK13: 602.30994 | GL13: 22.01 | GM13: 12.67285 | GN13: 124.99 | GO13: 205.92 | GP13: 10.97 | GQ13: 10.39 | GR13: 196.74072 | GS13: 43.91 | GT13: 3.46 | GU13: 21.469999 | GV13: 61.509998 | GW13: 101.83 | GX13: 81.839996 | GY13: 149.09917 | GZ13: 166.7943 | HA13: 5.23 | HB13: 15.89 | HC13: 79.267181 | HD13: 92.823593 | HE13: 28.280001 | HF13: 7.5599999 | HG13: 72.223083 | HH13: 70.910004 | HI13: 8.1300001 | HJ13: 28.139999 | HK13: 29.74 | HL13: 18.200001 | HM13: 661.97815 | HN13: 11.55 | HO13: 40.521606 | HP13: 48.07 | HQ13: 4.8000002 | HR13: 1.84 | HS13: 17.160568 | HT13: 38.700001 | HU13: 8.3699999 | HV13: 44.396877 | HW13: 26.809399 | HX13: 22.438303 | HY13: 222.96976 | HZ13: 113.79463 | IA13: 433.09 | IB13: 53.490002 | IC13: 107.55 | ID13: 96.650002 | IE13: 97.800003 | IF13: 39.88118 | IG13: 112.00922 | IH13: 7.0500002 | II13: 70.010002 | IJ13: 28.27 | IK13: 4.4000001 | IL13: 4.3200002 | IM13: 159.7823 | IN13: 10.828474 | IO13: 12.19 | IP13: 38.752838 | IQ13: 18.6 | IR13: 79.408363 | IS13: 31.890528 | IT13: 102.37802 | IU13: 2.8399999 | IV13: 13.450743 | IW13: 12.1 | IX13: 43.763195 | IY13: 142.27692 | IZ13: 142.40239 | JA13: 53.200001 | JB13: 23.67 | JC13: 79.019997 | JD13: 31.16 | JE13: 143.92503 | JF13: 55.030346 | JG13: 79.489998 | JH13: 25.25 | JI13: 140.07967
... A176: 2026-06-02 | B176: 83.627708 | D176: 13.93 | E176: 202.37 | F176: 57.387955 | G176: 314.92841 | H176: 36.209778 | I176: 134.35001 | J176: 86.354095 | K176: 20.889999 | L176: 6.7399998 | M176: 81.939941 | N176: 15.919797 | O176: 113.06059 | P176: 71.010002 | Q176: 20.973234 | R176: 118.04284 | S176: 1.78 | T176: 160.32001 | U176: 5.25 | V176: 521.53998 | W176: 310.5116 | X176: 8.6309996 | Y176: 74.51886 | Z176: 51.169998 | AA176: 256.51999 | AB176: 175.33 | AC176: 6.3400002 | AD176: 18.709999 | AE176: 74.088226 | AF176: 8.5500002 | AG176: 5.04 | AH176: 16.27 | AI176: 16.28241 | AJ176: 38.868992 | AK176: 7.48 | AL176: 39.459999 | AM176: 51.943718 | AN176: 18.862944 | AO176: 71.078384 | AP176: 28.959999 | AQ176: 17.23 | AR176: 10.32132 | AS176: 28.49 | AT176: 13.861239 | AU176: 53.8521 | AV176: 45.880749 | AW176: 1.1900001 | AX176: 18.76 | AY176: 130.59601 | AZ176: 194.45671 | BA176: 14.222441 | BB176: 87.608971 | BC176: 120.51 | BD176: 27.495991 | BE176: 34.709999 | BF176: 112.89831 | BG176: 17.58 | BH176: 21.299614 | BI176: 24.515966 | BJ176: 248.0732 | BK176: 426.89001 | BL176: 173.99001 | BM176: 8.6300001 | BN176: 116.09566 | BO176: 952.75525 | BP176: 4.4743414 | BQ176: 229 | BR176: 12.01 | BS176: 13.1 | BT176: 127.52294 | BU176: 39.130165 | BV176: 46.01403 | BW176: 65.599998 | BX176: 88.949318 | BY176: 720.87262 | BZ176: 79.822906 | CA176: 156.95 | CB176: 10.53 | CC176: 269.13 | CD176: 434.59186 | CE176: 105.73074 | CF176: 16.814152 | CG176: 72.768929 | CH176: 100.63886 | CI176: 9.04 | CJ176: 184.75288 | CK176: 22.950001 | CL176: 55.099998 | CM176: 3.3499999 | CN176: 34.321705 | CO176: 62.303265 | CP176: 14.01 | CQ176: 120.03463 | CR176: 67.773941 | CS176: 108.54996 | CT176: 27.469999 | CU176: 27.4 | CV176: 69.730003 | CW176: 35.442589 | CX176: 15.976964 | CY176: 72.160004 | CZ176: 49.34 | DA176: 4.6999998 | DB176: 9.8199997 | DC176: 148.86 | DD176: 101.97 | DE176: 88.050003 | DF176: 317.32446 | DG176: 411.95001 | DH176: 29.059999 | DI176: 81.384918 | DJ176: 357.94208 | DK176: 361.4017 | DL176: 18.799999 | DM176: 21.780001 | DN176: 126.61459 | DO176: 27.51 | DP176: 88.160004 | DQ176: 250.59885 | DR176: 84.419998 | DS176: 31.91 | DT176: 326.8851 | DU176: 162.55 | DV176: 5.9499998 | DW176: 2.54 | DX176: 14.54 | DY176: 107.93 | DZ176: 71.400002 | EA176: 49.282173 | EB176: 126.604 | EC176: 3.0699999 | ED176: 290.21008 | EE176: 141.59821 | EF176: 221.79611 | EG176: 13.7 | EH176: 14.992951 | EI176: 77.444885 | EJ176: 61.140495 | EK176: 0.64499998 | EL176: 22.711075 | EM176: 13.81 | EN176: 58.060001 | EO176: 235.49861 | EP176: 205.37077 | EQ176: 55.110001 | ER176: 334.17459 | ES176: 4.8400002 | ET176: 39.57 | EU176: 21.323135 | EV176: 476.88058 | EW176: 1.35 | EX176: 14.28 | EY176: 89.740334 | EZ176: 96.380127 | FA176: 73.090538 | FB176: 597.0766 | FC176: 67.147354 | FD176: 5.7600002 | FE176: 23.104425 | FF176: 114.15047 | FG176: 45.639999 | FH176: 290.71829 | FI176: 213.80305 | FJ176: 440.48077 | FK176: 136.08 | FL176: 4.5599999 | FM176: 84.422157 | FN176: 109.27253 | FO176: 15.499634 | FP176: 83.330002 | FQ176: 8.3800001 | FR176: 1.76 | FS176: 175.10815 | FT176: 11.93 | FU176: 222.31184 | FV176: 152.22 | FW176: 73.470001 | FX176: 5.4099998 | FY176: 8.3599997 | FZ176: 3.5999999 | GA176: 82.980003 | GB176: 297.17999 | GC176: 70.650002 | GD176: 152.17 | GE176: 172.2321 | GF176: 219.252 | GG176: 28 | GH176: 26.18 | GI176: 29.91 | GJ176: 5.1100001 | GK176: 745.34088 | GL176: 12.25 | GM176: 10.45871 | GN176: 45 | GO176: 169.13 | GP176: 20.58 | GQ176: 9.79 | GR176: 219.05533 | GS176: 26.879999 | GT176: 6.25 | GU176: 27.32 | GV176: 123.32 | GW176: 127.12 | GX176: 55.720001 | GY176: 222.95114 | GZ176: 173.68303 | HA176: 3.6099999 | HB176: 12.54 | HC176: 94.964478 | HD176: 87.35527 | HE176: 12.18 | HF176: 16.48 | HG176: 86.065727 | HH176: 166.63 | HI176: 5.7600002 | HJ176: 17.74 | HK176: 22.790001 | HL176: 8.8199997 | HM176: 755.74158 | HN176: 10.5 | HO176: 64.465935 | HP176: 44.07 | HQ176: 10.07 | HR176: 2.26 | HS176: 19.59 | HT176: 38.16 | HU176: 7.54 | HV176: 88.162834 | HW176: 28.727276 | HX176: 9.5100002 | HY176: 187.74643 | HZ176: 137.73306 | IA176: 423.73999 | IB176: 21.1 | IC176: 229.3 | ID176: 108.82 | IE176: 71.620003 | IF176: 48.16 | IG176: 150.53679 | IH176: 1.0700001 | II176: 72.260002 | IJ176: 30.700001 | IK176: 7.3000002 | IL176: 16.059999 | IM176: 257.26578 | IN176: 14.842633 | IO176: 7.27 | IP176: 47.067631 | IQ176: 27.18 | IR176: 78.986526 | IS176: 30.57361 | IT176: 112.78998 | IU176: 1.39 | IV176: 18.92416 | IW176: 26.49 | IX176: 57.544998 | IY176: 197.97395 | IZ176: 145.75717 | JA176: 85 | JB176: 17.889999 | JC176: 74.150002 | JD176: 23.07 | JE176: 145.8447 | JF176: 61.606071 | JG176: 111.88 | JH176: 0.21600001 | JI176: 75.861176
A177: 2026-06-03 | B177: 80.703384 | C177: 19.01 | D177: 13.57 | E177: 184.07001 | F177: 56.860363 | G177: 309.99265 | H177: 36.053322 | I177: 133.59 | J177: 86.373955 | K177: 21.43 | L177: 6.5300002 | M177: 83.579536 | N177: 16.217548 | O177: 113.92623 | P177: 66.269997 | Q177: 19.75421 | R177: 119.25916 | S177: 1.65 | T177: 160.36 | U177: 5.1399999 | V177: 542.52002 | W177: 311.60156 | X177: 8.2320004 | Y177: 75.061859 | Z177: 46.669998 | AA177: 250.02 | AB177: 174.37 | AC177: 6.0300002 | AD177: 18.85 | AE177: 73.698814 | AF177: 8.6700001 | AG177: 5.02 | AH177: 14.64 | AI177: 16.10317 | AJ177: 39.51252 | AK177: 7.6799998 | AL177: 40.630001 | AM177: 51.864532 | AN177: 18.408653 | AO177: 70.052933 | AP177: 29.549999 | AQ177: 16.91 | AR177: 10.131661 | AS177: 27.860001 | AT177: 13.113868 | AU177: 54.1092 | AV177: 45.701988 | AW177: 1.16 | AX177: 19.709999 | AY177: 129.27274 | AZ177: 195.42459 | BA177: 13.965289 | BB177: 86.342392 | BC177: 114.56 | BD177: 27.02844 | BE177: 33.689999 | BF177: 116.0023 | BG177: 17.610001 | BH177: 20.732819 | BI177: 23.203846 | BJ177: 250.16251 | BK177: 417.42999 | BL177: 163.22 | BM177: 7.6100001 | BN177: 118.26122 | BO177: 960.30322 | BP177: 4.3502693 | BQ177: 214.60001 | BR177: 11.01 | BS177: 12.28 | BT177: 126.02853 | BU177: 37.215538 | BV177: 46.31321 | BW177: 63.650002 | BX177: 90.807816 | BY177: 733.6283 | BZ177: 78.58596 | CA177: 154.58 | CB177: 10.33 | CC177: 250.33 | CD177: 420.38531 | CE177: 104.55673 | CF177: 16.37845 | CG177: 72.888184 | CH177: 98.634216 | CI177: 8.6300001 | CJ177: 181.04323 | CK177: 22.33 | CL177: 52.400002 | CM177: 3.27 | CN177: 34.993904 | CO177: 60.167152 | CP177: 12.1 | CQ177: 119.98507 | CR177: 67.385468 | CS177: 108.49014 | CT177: 26.719999 | CU177: 27.610001 | CV177: 67.050003 | CW177: 34.313339 | CX177: 15.541678 | CY177: 69.160004 | CZ177: 50.16 | DA177: 4.3299999 | DB177: 9.4200001 | DC177: 146.48 | DD177: 96.220001 | DE177: 85 | DF177: 314.24829 | DG177: 407.87 | DH177: 28.49 | DI177: 81.355042 | DJ177: 355.23541 | DK177: 358.54523 | DL177: 17.35 | DM177: 18.290001 | DN177: 125.38996 | DO177: 27.51 | DP177: 82.849998 | DQ177: 248.50986 | DR177: 83.589996 | DS177: 30.040001 | DT177: 303.45319 | DU177: 170.92999 | DV177: 6.0300002 | DW177: 2.4400001 | DX177: 13.82 | DY177: 112.71 | DZ177: 68.230003 | EA177: 48.656216 | EB177: 126.10136 | EC177: 3 | ED177: 286.23996 | EE177: 146.55449 | EF177: 222.14441 | EG177: 12.74 | EH177: 15.122545 | EI177: 77.790573 | EJ177: 60.81274 | EK177: 0.63800001 | EL177: 22.472639 | EM177: 13.36 | EN177: 52.66 | EO177: 234.86 | EP177: 206.37457 | EQ177: 55.689999 | ER177: 343.46805 | ES177: 4.8499999 | ET177: 33.830002 | EU177: 21.451052 | EV177: 470.76083 | EW177: 1.4299999 | EX177: 13.96 | EY177: 86.881149 | EZ177: 95.97258 | FA177: 77.252975 | FB177: 622.40314 | FC177: 68.175323 | FD177: 5.7600002 | FE177: 23.104425 | FF177: 113.21279 | FG177: 49.060001 | FH177: 301.57559 | FI177: 208.98956 | FJ177: 426.53705 | FK177: 126.55 | FL177: 4.4099998 | FM177: 83.33831 | FN177: 107.24675 | FO177: 15.648098 | FP177: 81.519997 | FQ177: 8.0500002 | FR177: 1.65 | FS177: 180.53169 | FT177: 11.64 | FU177: 214.26025 | FV177: 146.47 | FW177: 65.209999 | FX177: 4.8699999 | FY177: 8 | FZ177: 3.6500001 | GA177: 80.839996 | GB177: 280.42999 | GC177: 71.410004 | GD177: 142.2 | GE177: 174.49335 | GF177: 216.54359 | GG177: 27.58 | GH177: 24.77 | GI177: 27.549999 | GJ177: 4.8800001 | GK177: 743.39307 | GL177: 11.2 | GM177: 10.156548 | GN177: 43.68 | GO177: 169.49001 | GP177: 18.620001 | GQ177: 9.1199999 | GR177: 216.27199 | GS177: 24.094999 | GT177: 6.1799998 | GU177: 27.65 | GV177: 114.7 | GW177: 122.2 | GX177: 52.369999 | GY177: 231.71696 | GZ177: 171.9787 | HA177: 3.47 | HB177: 12.08 | HC177: 95.342308 | HD177: 86.338234 | HE177: 12.67 | HF177: 15.16 | HG177: 86.016159 | HH177: 163.5 | HI177: 5.73 | HJ177: 16.68 | HK177: 22.200001 | HL177: 8.0799999 | HM177: 750.43842 | HN177: 9.8500004 | HO177: 64.69297 | HP177: 44.040001 | HQ177: 9.5200005 | HR177: 2.25 | HS177: 19.440001 | HT177: 37.639999 | HU177: 7.0900002 | HV177: 85.375511 | HW177: 29.036707 | HX177: 9.1400003 | HY177: 180.40877 | HZ177: 138.68671 | IA177: 423.70001 | IB177: 20.559999 | IC177: 227.25999 | ID177: 105.14 | IE177: 71.690002 | IF177: 47.32 | IG177: 147.39375 | IH177: 1.01 | II177: 72.57 | IJ177: 27.98 | IK177: 7.1599998 | IL177: 16.540001 | IM177: 260.44348 | IN177: 14.773918 | IO177: 7.1500001 | IP177: 45.868084 | IQ177: 27 | IR177: 78.230865 | IS177: 29.203754 | IT177: 116.61083 | IU177: 1.3200001 | IV177: 18.59461 | IW177: 26.16 | IX177: 58.289627 | IY177: 195.99629 | IZ177: 146.90213 | JA177: 82.25 | JB177: 17.459999 | JC177: 69.800003 | JD177: 22.02 | JE177: 147.69537 | JF177: 60.354481 | JG177: 106.2 | JH177: 0.18000001 | JI177: 77.052864
A178: 2026-06-04 | B178: 77.868881 | C178: 18.6 | D178: 13.3 | E178: 202.89 | F178: 55.635956 | G178: 310.96182 | H178: 36.366234 | I178: 133.72 | J178: 90.137115 | K178: 21.719999 | L178: 6.3800001 | M178: 82.8442 | N178: 16.535149 | O178: 114.71227 | P178: 68.699997 | Q178: 19.75421 | R178: 119.50841 | S178: 1.71 | T178: 158.98 | U178: 5.3400002 | V178: 523.20001 | W178: 334.81094 | X178: 8.526 | Y178: 73.684402 | Z178: 46.400002 | AA178: 253.78999 | AB178: 166.00999 | AC178: 6.46 | AD178: 20.030001 | AE178: 73.274452 | AF178: 9.3199997 | AG178: 5.0799999 | AH178: 14.22 | AI178: 16.244673 | AJ178: 38.017559 | AK178: 7.9200001 | AL178: 42.389999 | AM178: 53.616444 | AN178: 19.099964 | AO178: 69.330231 | AP178: 32.84 | AQ178: 16.620001 | AR178: 10.540922 | AS178: 27.49 | AT178: 12.386428 | AU178: 55.968212 | AV178: 45.701988 | AW178: 1.23 | AX178: 19.629999 | AY178: 134.46634 | AZ178: 201.3018 | BA178: 14.054303 | BB178: 91.379517 | BC178: 114.02 | BD178: 27.704897 | BE178: 34.360001 | BF178: 116.91759 | BG178: 16.780001 | BH178: 21.180288 | BI178: 23.016399 | BJ178: 253.54897 | BK178: 421.89999 | BL178: 164.13 | BM178: 7.8800001 | BN178: 118.44003 | BO178: 970.80646 | BP178: 4.5286226 | BQ178: 217.5 | BR178: 10.97 | BS178: 12.33 | BT178: 129.51549 | BU178: 37.444893 | BV178: 46.103786 | BW178: 66.190002 | BX178: 94.236588 | BY178: 743.17499 | BZ178: 79.314163 | CA178: 160.07001 | CB178: 10.79 | CC178: 243.60001 | CD178: 421.35373 | CE178: 102.9947 | CF178: 16.55669 | CG178: 72.381332 | CH178: 98.584595 | CI178: 8.8000002 | CJ178: 186.1736 | CK178: 22.309999 | CL178: 50.939999 | CM178: 3.26 | CN178: 34.390903 | CO178: 60.167152 | CP178: 12.72 | CQ178: 120.75827 | CR178: 67.614563 | CS178: 108.81915 | CT178: 26.67 | CU178: 28.9 | CV178: 67.050003 | CW178: 34.452019 | CX178: 15.175643 | CY178: 72.419998 | CZ178: 50.41 | DA178: 4.52 | DB178: 9.4499998 | DC178: 149.67 | DD178: 95.779999 | DE178: 86.400002 | DF178: 327.2421 | DG178: 411.26999 | DH178: 28.41 | DI178: 82.868629 | DJ178: 368.80844 | DK178: 371.72888 | DL178: 18.530001 | DM178: 19.030001 | DN178: 126.7739 | DO178: 28.01 | DP178: 88.330002 | DQ178: 249.20952 | DR178: 84.279999 | DS178: 29.82 | DT178: 299.62067 | DU178: 168.06 | DV178: 6.5500002 | DW178: 2.46 | DX178: 14.01 | DY178: 111.78 | DZ178: 65.660004 | EA178: 51.736347 | EB178: 128.36812 | EC178: 3.1800001 | ED178: 290.55835 | EE178: 146.99326 | EF178: 227.0502 | EG178: 12.53 | EH178: 15.08267 | EI178: 75.874458 | EJ178: 61.815861 | EK178: 0.62 | EL178: 22.383224 | EM178: 13.5 | EN178: 51.57 | EO178: 240.54765 | EP178: 206.25531 | EQ178: 62.540001 | ER178: 336.17319 | ES178: 5.0599999 | ET178: 33.630001 | EU178: 22.661366 | EV178: 480.95377 | EW178: 1.5 | EX178: 13.88 | EY178: 90.029236 | EZ178: 95.724075 | FA178: 81.197388 | FB178: 626.98889 | FC178: 68.466255 | FD178: 5.71 | FE178: 22.707783 | FF178: 118.7007 | FG178: 51.59 | FH178: 316.35196 | FI178: 217.07506 | FJ178: 427.2457 | FK178: 129.37 | FL178: 4.6599998 | FM178: 84.422157 | FN178: 108.10497 | FO178: 14.895881 | FP178: 81.559998 | FQ178: 8.1899996 | FR178: 1.63 | FS178: 178.32837 | FT178: 12.12 | FU178: 218.4156 | FV178: 150.32001 | FW178: 65.389999 | FX178: 4.9499998 | FY178: 8.4499998 | FZ178: 3.8099999 | GA178: 78.510002 | GB178: 279.25 | GC178: 71.160004 | GD178: 141.7 | GE178: 173.55116 | GF178: 225.28391 | GG178: 28.969999 | GH178: 25.040001 | GI178: 27.639999 | GJ178: 4.48 | GK178: 739.797 | GL178: 11.19 | GM178: 10.166295 | GN178: 43.349998 | GO178: 183.91 | GP178: 21.43 | GQ178: 9.0799999 | GR178: 219.64392 | GS178: 24.16 | GT178: 6.25 | GU178: 27.469999 | GV178: 119.95 | GW178: 125.59 | GX178: 52.639999 | GY178: 232.15527 | GZ178: 178.81598 | HA178: 3.8 | HB178: 11.98 | HC178: 93.602303 | HD178: 87.744141 | HE178: 12.32 | HF178: 14.73 | HG178: 85.976517 | HH178: 169.35001 | HI178: 6.0700002 | HJ178: 17.15 | HK178: 22.23 | HL178: 8.0100002 | HM178: 753.27405 | HN178: 9.5600004 | HO178: 65.052658 | HP178: 44.700001 | HQ178: 9.5900002 | HR178: 2.1099999 | HS178: 19.530001 | HT178: 39.32 | HU178: 7.3099999 | HV178: 86.58567 | HW178: 29.695499 | HX178: 9.3000002 | HY178: 176.0042 | HZ178: 139.54102 | IA178: 418.45001 | IB178: 21.030001 | IC178: 236.64 | ID178: 104.94 | IE178: 72.209999 | IF178: 47.669998 | IG178: 149.0002 | IH178: 1.02 | II178: 72.910004 | IJ178: 27.1 | IK178: 7.1100001 | IL178: 17.15 | IM178: 257.85349 | IN178: 14.823001 | IO178: 7.0999999 | IP178: 44.117916 | IQ178: 27 | IR178: 81.154083 | IS178: 29.779491 | IT178: 117.4588 | IU178: 1.36 | IV178: 18.944132 | IW178: 26.190001 | IX178: 58.329342 | IY178: 192.93994 | IZ178: 151.41223 | JA178: 82.699997 | JB178: 16.809999 | JC178: 70.889999 | JD178: 23.629999 | JE178: 147.33717 | JF178: 62.629196 | JG178: 105.21 | JH178: 0.206 | JI178: 78.969505
A179: 2026-06-05 | B179: 71.750755 | C179: 17.540001 | D179: 13.5 | E179: 177 | F179: 56.551773 | G179: 307.07516 | H179: 36.434685 | I179: 133.53999 | J179: 90.425056 | K179: 21.559999 | L179: 5.54 | M179: 80.409653 | N179: 16.316799 | O179: 117.64748 | P179: 63.610001 | Q179: 16.976429 | R179: 116.05885 | S179: 1.58 | T179: 149.32001 | U179: 4.9099998 | V179: 466.38 | W179: 336.80087 | X179: 8.6099997 | Y179: 64.830688 | Z179: 42.34 | AA179: 246.03 | AB179: 154.27 | AC179: 5.9200001 | AD179: 18.26 | AE179: 69.300446 | AF179: 9.0100002 | AG179: 4.7199998 | AH179: 12.14 | AI179: 16.140903 | AJ179: 33.691082 | AK179: 8 | AL179: 42.799999 | AM179: 53.556751 | AN179: 19.030834 | AO179: 69.867371 | AP179: 29.4 | AQ179: 16.08 | AR179: 10.840379 | AS179: 25.049999 | AT179: 11.100949 | AU179: 56.630737 | AV179: 45.61261 | AW179: 1.105 | AX179: 17.469999 | AY179: 131.7999 | AZ179: 205.26318 | BA179: 12.234464 | BB179: 92.061516 | BC179: 103.44 | BD179: 27.267189 | BE179: 33.5 | BF179: 112.90825 | BG179: 15.59 | BH179: 19.837877 | BI179: 23.499811 | BJ179: 254.87582 | BK179: 376.98999 | BL179: 152.39999 | BM179: 7.71 | BN179: 116.36387 | BO179: 970.32727 | BP179: 4.4976048 | BQ179: 206.89 | BR179: 9.7399998 | BS179: 10.61 | BT179: 121.18665 | BU179: 37.42495 | BV179: 46.861713 | BW179: 66.510002 | BX179: 95.339752 | BY179: 732.88855 | BZ179: 79.22438 | CA179: 156.8 | CB179: 10.67 | CC179: 234.11 | CD179: 393.73938 | CE179: 103.17378 | CF179: 17.071613 | CG179: 70.950203 | CH179: 98.95179 | CI179: 8.2700005 | CJ179: 184.28917 | CK179: 21.01 | CL179: 47.259998 | CM179: 3.0999999 | CN179: 33.580311 | CO179: 59.425449 | CP179: 12.11 | CQ179: 123.13735 | CR179: 65.622375 | CS179: 109.01854 | CT179: 25.76 | CU179: 29.129999 | CV179: 66.860001 | CW179: 33.689278 | CX179: 14.740356 | CY179: 68.32 | CZ179: 47.560001 | DA179: 4.3400002 | DB179: 8.6899996 | DC179: 144.67999 | DD179: 92.330002 | DE179: 78.839996 | DF179: 327.59164 | DG179: 396.23999 | DH179: 25.139999 | DI179: 81.940544 | DJ179: 365.30286 | DK179: 368.07343 | DL179: 16.459999 | DM179: 17.139999 | DN179: 131.56288 | DO179: 26.190001 | DP179: 82.470001 | DQ179: 251.77827 | DR179: 81.220001 | DS179: 29.940001 | DT179: 282.81125 | DU179: 162.32001 | DV179: 5.2399998 | DW179: 2.45 | DX179: 11.42 | DY179: 99.169998 | DZ179: 56.779999 | EA179: 47.05653 | EB179: 122.8589 | EC179: 3.02 | ED179: 280.24985 | EE179: 143.2536 | EF179: 231.62764 | EG179: 11.69 | EH179: 15.381732 | EI179: 78.501724 | EJ179: 63.136795 | EK179: 0.58499998 | EL179: 22.383224 | EM179: 13.4 | EN179: 51.459999 | EO179: 238.30254 | EP179: 209.4456 | EQ179: 61.849998 | ER179: 303.0665 | ES179: 4.7600002 | ET179: 29.360001 | EU179: 21.80529 | EV179: 490.25815 | EW179: 1.36 | EX179: 12.32 | EY179: 90.507423 | EZ179: 87.811676 | FA179: 80.939713 | FB179: 592.45093 | FC179: 70.008202 | FD179: 5.6100001 | FE179: 22.053322 | FF179: 119.22382 | FG179: 47.439999 | FH179: 263.40503 | FI179: 210.76976 | FJ179: 415.88708 | FK179: 120.44 | FL179: 4.6900001 | FM179: 85.19931 | FN179: 99.502869 | FO179: 12.916362 | FP179: 82.18 | FQ179: 7.3299999 | FR179: 1.5599999 | FS179: 166.53419 | FT179: 11.97 | FU179: 204.87076 | FV179: 131.57001 | FW179: 58.09 | FX179: 4.4200001 | FY179: 8.3100004 | FZ179: 3.71 | GA179: 72.169998 | GB179: 272.04999 | GC179: 59.860001 | GD179: 135.53 | GE179: 176.82402 | GF179: 226.56369 | GG179: 29.879999 | GH179: 22.65 | GI179: 23.85 | GJ179: 4.2600002 | GK179: 704.28601 | GL179: 9.9549999 | GM179: 9.8933735 | GN179: 41.82 | GO179: 173.45 | GP179: 18.450001 | GQ179: 8.8699999 | GR179: 205.57762 | GS179: 20.68 | GT179: 5.9499998 | GU179: 24.66 | GV179: 110.08 | GW179: 122.26 | GX179: 53.540001 | GY179: 229.47571 | GZ179: 180.39075 | HA179: 3.3150001 | HB179: 12.08 | HC179: 94.745735 | HD179: 88.581696 | HE179: 11.55 | HF179: 13.28 | HG179: 84.658066 | HH179: 151.02 | HI179: 5.7600002 | HJ179: 16.030001 | HK179: 21.889999 | HL179: 7.3899999 | HM179: 733.83252 | HN179: 8.8500004 | HO179: 61.823376 | HP179: 44.75 | HQ179: 9.4499998 | HR179: 2.03 | HS179: 19.01 | HT179: 39.209999 | HU179: 7.0500002 | HV179: 81.993034 | HW179: 30.115152 | HX179: 9.0799999 | HY179: 177.078 | HZ179: 139.57092 | IA179: 391 | IB179: 19.950001 | IC179: 225.99001 | ID179: 105.73 | IE179: 70.709999 | IF179: 47.009998 | IG179: 137.22626 | IH179: 0.94700003 | II179: 71.300003 | IJ179: 22.469999 | IK179: 6.6599998 | IL179: 18.98 | IM179: 254.83516 | IN179: 14.7 | IO179: 6.9099998 | IP179: 44.609535 | IQ179: 26.24 | IR179: 81.47226 | IS179: 29.710007 | IT179: 118.59608 | IU179: 1.29 | IV179: 18.155209 | IW179: 24 | IX179: 57.257072 | IY179: 180.08527 | IZ179: 152.33815 | JA179: 80.660004 | JB179: 15.95 | JC179: 68.150002 | JD179: 23.25 | JE179: 150.11317 | JF179: 62.807995 | JG179: 101.62 | JH179: 0.192 | JI179: 78.890068
A180: 2026-06-08 | B180: 73.29776 | C180: 19.219999 | D180: 13.6 | E180: 196.64 | F180: 58.114639 | G180: 301.28018 | H180: 35.8382 | I180: 134.42999 | J180: 89.859093 | K180: 21.700001 | L180: 5.73 | M180: 79.714066 | N180: 17.160429 | O180: 114.66252 | P180: 65.459999 | Q180: 17.156286 | R180: 115.29116 | S180: 1.6 | T180: 141.87 | U180: 4.96 | V180: 490.32999 | W180: 336.6109 | X180: 8.4420004 | Y180: 68.164558 | Z180: 43.34 | AA180: 245.22 | AB180: 156.39999 | AC180: 6.0100002 | AD180: 18.24 | AE180: 71.691841 | AF180: 9.3500004 | AG180: 4.8899999 | AH180: 12.82 | AI180: 15.754127 | AJ180: 35.166241 | AK180: 7.9099998 | AL180: 41.459999 | AM180: 53.357765 | AN180: 19.001205 | AO180: 72.435883 | AP180: 29.780001 | AQ180: 16.16 | AR180: 10.770506 | AS180: 26.65 | AT180: 12.197093 | AU180: 54.949711 | AV180: 44.986961 | AW180: 1.105 | AX180: 18.49 | AY180: 132.6058 | AZ180: 204.03584 | BA180: 13.480659 | BB180: 89.430916 | BC180: 105.44 | BD180: 26.869274 | BE180: 33.580002 | BF180: 108.88895 | BG180: 16.52 | BH180: 19.579338 | BI180: 23.440619 | BJ180: 249.55849 | BK180: 401.92999 | BL180: 162.11 | BM180: 7.5799999 | BN180: 118.10227 | BO180: 973.2027 | BP180: 4.5441318 | BQ180: 222.27 | BR180: 10.11 | BS180: 11.04 | BT180: 123.68729 | BU180: 37.714138 | BV180: 46.981384 | BW180: 69.449997 | BX180: 96.482681 | BY180: 721.08258 | BZ180: 78.017365 | CA180: 152.49001 | CB180: 10.94 | CC180: 231.67999 | CD180: 400.10883 | CE180: 106.27795 | CF180: 16.913176 | CG180: 71.944038 | CH180: 98.118179 | CI180: 8.1499996 | CJ180: 179.7113 | CK180: 20.91 | CL180: 46.16 | CM180: 3.1700001 | CN180: 33.807671 | CO180: 57.694801 | CP180: 12.09 | CQ180: 120.98627 | CR180: 65.990929 | CS180: 108.1113 | CT180: 25.879999 | CU180: 29.950001 | CV180: 68.830002 | CW180: 33.372295 | CX180: 14.839286 | CY180: 69.959999 | CZ180: 49.52 | DA180: 4.4200001 | DB180: 8.7700005 | DC180: 143.03999 | DD180: 91.080002 | DE180: 78.669998 | DF180: 321.63907 | DG180: 397.26999 | DH180: 30.51 | DI180: 83.597115 | DJ180: 360.9357 | DK180: 363.07663 | DL180: 16.18 | DM180: 17.02 | DN180: 127.03275 | DO180: 27.17 | DP180: 85.040001 | DQ180: 246.43086 | DR180: 81.379997 | DS180: 30.459999 | DT180: 278.81989 | DU180: 158.03999 | DV180: 5.7199998 | DW180: 2.4000001 | DX180: 11.28 | DY180: 110.27 | DZ180: 62.799999 | EA180: 47.175762 | EB180: 121.71565 | EC180: 2.95 | ED180: 282.69763 | EE180: 143.65251 | EF180: 231.02063 | EG180: 11.37 | EH180: 15.491387 | EI180: 78.560974 | EJ180: 62.530952 | EK180: 0.57599998 | EL180: 22.879969 | EM180: 13.52 | EN180: 52.970001 | EO180: 236.09731 | EP180: 206.69261 | EQ180: 63.900002 | ER180: 324.22162 | ES180: 4.8099999 | ET180: 29.735001 | EU180: 21.903692 | EV180: 484.85724 | EW180: 1.27 | EX180: 13.78 | EY180: 91.384109 | EZ180: 90.823563 | FA180: 79.968483 | FB180: 584.84796 | FC180: 69.135406 | FD180: 5.5700002 | FE180: 21.200541 | FF180: 117.97029 | FG180: 47.599998 | FH180: 288.77878 | FI180: 211.07806 | FJ180: 410.96634 | FK180: 127.2 | FL180: 4.73 | FM180: 83.382973 | FN180: 98.784363 | FO180: 12.362096 | FP180: 82.639999 | FQ180: 7.2199998 | FR180: 1.51 | FS180: 169.7943 | FT180: 11.6 | FU180: 208.4068 | FV180: 125.65 | FW180: 58.939999 | FX180: 4.3099999 | FY180: 7.8400002 | FZ180: 3.6400001 | GA180: 73.769997 | GB180: 266.32999 | GC180: 64.629997 | GD180: 136.47 | GE180: 174.61237 | GF180: 225.34343 | GG180: 29.18 | GH180: 22.91 | GI180: 25.83 | GJ180: 4.0500002 | GK180: 715.28394 | GL180: 10.45 | GM180: 9.8933735 | GN180: 42.299999 | GO180: 171.13 | GP180: 18.57 | GQ180: 9.1999998 | GR180: 205.2085 | GS180: 21.764999 | GT180: 6.1700001 | GU180: 25.690001 | GV180: 113.65 | GW180: 123.57 | GX180: 54.919998 | GY180: 226.53716 | GZ180: 178.06847 | HA180: 3.3199999 | HB180: 12.69 | HC180: 94.278419 | HD180: 87.823906 | HE180: 11.69 | HF180: 13.25 | HG180: 85.897209 | HH180: 158.78999 | HI180: 5.6500001 | HJ180: 16.5 | HK180: 22.15 | HL180: 7.4899998 | HM180: 735.49408 | HN180: 8.96 | HO180: 62.846809 | HP180: 44.48 | HQ180: 9.3100004 | HR180: 2.0799999 | HS180: 19.07 | HT180: 39.650002 | HU180: 7.0799999 | HV180: 82.994873 | HW180: 30.474855 | HX180: 9.0699997 | HY180: 177.4061 | HZ180: 140.36789 | IA180: 408.95001 | IB180: 19.43 | IC180: 212.53999 | ID180: 105.32 | IE180: 70.059998 | IF180: 47.290001 | IG180: 138.26396 | IH180: 0.94999999 | II180: 71.879997 | IJ180: 22.209999 | IK180: 6.4400001 | IL180: 19.1 | IM180: 257.39529 | IN180: 14.81 | IO180: 6.9299998 | IP180: 44.678364 | IQ180: 26.469999 | IR180: 80.497849 | IS180: 29.789419 | IT180: 119.54382 | IU180: 1.3099999 | IV180: 17.566013 | IW180: 25.860001 | IX180: 57.91235 | IY180: 183.96065 | IZ180: 151.97972 | JA180: 82.199997 | JB180: 15.83 | JC180: 69.919998 | JD180: 22.959999 | JE180: 146.63074 | JF180: 62.827862 | JG180: 101.15 | JH180: 0.147 | JI180: 78.274353
A181: 2026-06-09 | B181: 72.269753 | C181: 19.120001 | D181: 14.09 | E181: 162.88 | F181: 59.767094 | G181: 290.29962 | H181: 36.160885 | I181: 131.35001 | J181: 90.603783 | K181: 21.84 | L181: 5.3200002 | M181: 79.6147 | N181: 17.43833 | O181: 115.03067 | P181: 65.110001 | Q181: 16.526791 | R181: 112.79871 | S181: 1.61 | T181: 137.81 | U181: 5.1399999 | V181: 475.51001 | W181: 342.11075 | X181: 8.5050001 | Y181: 70.779747 | Z181: 40.529999 | AA181: 244.19 | AB181: 152.16 | AC181: 5.77 | AD181: 21.15 | AE181: 76.918961 | AF181: 9.8500004 | AG181: 4.7600002 | AH181: 12.49 | AI181: 16.188072 | AJ181: 34.730625 | AK181: 8.2600002 | AL181: 42.869999 | AM181: 54.143753 | AN181: 19.297485 | AO181: 73.363678 | AP181: 30.469999 | AQ181: 15.97 | AR181: 10.950181 | AS181: 25.799999 | AT181: 11.698846 | AU181: 55.849552 | AV181: 45.701988 | AW181: 1.0700001 | AX181: 17.41 | AY181: 134.04846 | AZ181: 212.20805 | BA181: 13.619124 | BB181: 90.190872 | BC181: 102.27 | BD181: 27.585522 | BE181: 34.220001 | BF181: 108.02342 | BG181: 15.97 | BH181: 18.893215 | BI181: 23.529409 | BJ181: 254.74414 | BK181: 355.94 | BL181: 155.5 | BM181: 8.1700001 | BN181: 116.01619 | BO181: 967.05249 | BP181: 4.4355688 | BQ181: 234.32001 | BR181: 9.4099998 | BS181: 9.9099998 | BT181: 119.91142 | BU181: 38.382263 | BV181: 47.150917 | BW181: 69.610001 | BX181: 96.462799 | BY181: 733.31836 | BZ181: 80.97007 | CA181: 155.67 | CB181: 11.69 | CC181: 227.34 | CD181: 381.15018 | CE181: 108.82496 | CF181: 16.942883 | CG181: 69.191109 | CH181: 98.574677 | CI181: 8.1599998 | CJ181: 182.45407 | CK181: 20.959999 | CL181: 45.07 | CM181: 3.25 | CN181: 32.838913 | CO181: 57.338783 | CP181: 11.88 | CQ181: 122.74084 | CR181: 65.662224 | CS181: 108.33064 | CT181: 26.219999 | CU181: 30.530001 | CV181: 68.760002 | CW181: 33.600128 | CX181: 14.789821 | CY181: 66.940002 | CZ181: 49.48 | DA181: 4.3200002 | DB181: 8.5900002 | DC181: 138.39 | DD181: 91.309998 | DE181: 77.589996 | DF181: 330.02863 | DG181: 390.78 | DH181: 32.68 | DI181: 83.587143 | DJ181: 362.05496 | DK181: 364.02603 | DL181: 16.610001 | DM181: 16.08 | DN181: 128.40672 | DO181: 28.98 | DP181: 83.769997 | DQ181: 257.03574 | DR181: 80.07 | DS181: 30.370001 | DT181: 275.51361 | DU181: 160.03 | DV181: 5.8499999 | DW181: 2.4200001 | DX181: 10.45 | DY181: 107.92 | DZ181: 56.689999 | EA181: 44.811008 | EB181: 124.3175 | EC181: 2.9200001 | ED181: 283.60309 | EE181: 147.3423 | EF181: 235.83687 | EG181: 11.43 | EH181: 15.710699 | EI181: 80.338814 | EJ181: 62.560749 | EK181: 0.57999998 | EL181: 23.416449 | EM181: 13.52 | EN181: 53.580002 | EO181: 238.88126 | EP181: 216.03487 | EQ181: 64.010002 | ER181: 326.92972 | ES181: 4.9000001 | ET181: 27.469999 | EU181: 21.82497 | EV181: 494.41119 | EW181: 1.3 | EX181: 13.31 | EY181: 93.575813 | EZ181: 90.922958 | FA181: 81.246948 | FB181: 584.04871 | FC181: 69.39724 | FD181: 5.4899998 | FE181: 21.101381 | FF181: 118.04926 | FG181: 47.73 | FH181: 266.81418 | FI181: 209.09895 | FJ181: 402.65201 | FK181: 117.02 | FL181: 4.3499999 | FM181: 84.196854 | FN181: 98.335297 | FO181: 12.619433 | FP181: 81.410004 | FQ181: 7.1799998 | FR181: 1.49 | FS181: 164.50038 | FT181: 11.88 | FU181: 207.95731 | FV181: 119.27 | FW181: 56.48 | FX181: 4.3400002 | FY181: 8.4399996 | FZ181: 3.6500001 | GA181: 70 | GB181: 260.51999 | GC181: 61.689999 | GD181: 132.07001 | GE181: 177.02238 | GF181: 230.34355 | GG181: 29.74 | GH181: 22.66 | GI181: 23.52 | GJ181: 3.8900001 | GK181: 707.05298 | GL181: 9.5050001 | GM181: 9.7569141 | GN181: 43 | GO181: 178.11 | GP181: 15.75 | GQ181: 9.54 | GR181: 204.30066 | GS181: 19.690001 | GT181: 5.8699999 | GU181: 25.295 | GV181: 108.23 | GW181: 120.91 | GX181: 53.849998 | GY181: 229.00739 | GZ181: 180.95886 | HA181: 3.22 | HB181: 13.04 | HC181: 96.85363 | HD181: 88.511894 | HE181: 12.25 | HF181: 14.15 | HG181: 84.687805 | HH181: 157.52 | HI181: 5.5900002 | HJ181: 16.469999 | HK181: 21.309999 | HL181: 7.02 | HM181: 733.33502 | HN181: 8.6599998 | HO181: 60.809879 | HP181: 45.66 | HQ181: 9.8199997 | HR181: 2.03 | HS181: 19.02 | HT181: 40 | HU181: 6.9299998 | HV181: 86.655106 | HW181: 31.324156 | HX181: 9.0699997 | HY181: 178.43019 | HZ181: 145.07007 | IA181: 396.67999 | IB181: 19.889999 | IC181: 204.69 | ID181: 109.63 | IE181: 70.379997 | IF181: 47.860001 | IG181: 136.92691 | IH181: 0.89099997 | II181: 73.779999 | IJ181: 20.9 | IK181: 6.4299998 | IL181: 16.629999 | IM181: 252.80301 | IN181: 14.67 | IO181: 6.9899998 | IP181: 45.012665 | IQ181: 26.559999 | IR181: 81.531914 | IS181: 29.144197 | IT181: 118.59608 | IU181: 1.2 | IV181: 17.076683 | IW181: 25.299999 | IX181: 56.97908 | IY181: 180.55472 | IZ181: 153.89131 | JA181: 81.029999 | JB181: 15.48 | JC181: 68.290001 | JD181: 23.74 | JE181: 150.86937 | JF181: 64.397316 | JG181: 96.830002 | JH181: 0.14300001 | JI181: 81.630951
A182: 2026-06-10 | B182: 65.423042 | C182: 18.41 | D182: 13.42 | E182: 175.13 | F182: 59.090183 | G182: 291.32874 | H182: 36.200001 | I182: 129.10001 | J182: 88.538513 | K182: 21.25 | L182: 5.0500002 | M182: 80.76738 | N182: 17.39863 | O182: 116.52316 | P182: 62.810001 | Q182: 15.697453 | R182: 108.38206 | S182: 1.6 | T182: 129.97 | U182: 5.1599998 | V182: 452.39999 | W182: 335.33093 | X182: 7.9590001 | Y182: 69.482132 | Z182: 36.779999 | AA182: 238 | AB182: 151.75999 | AC182: 5.6900001 | AD182: 19.68 | AE182: 74.497612 | AF182: 10.22 | AG182: 4.7199998 | AH182: 13.09 | AI182: 15.876762 | AJ182: 33.958393 | AK182: 8.1300001 | AL182: 41.34 | AM182: 54.263145 | AN182: 19.406118 | AO182: 73.871513 | AP182: 29.49 | AQ182: 16 | AR182: 11.069964 | AS182: 24.65 | AT182: 11.639057 | AU182: 54.979374 | AV182: 45.701988 | AW182: 1.09 | AX182: 16.1 | AY182: 132.70529 | AZ182: 215.83017 | BA182: 13.589453 | BB182: 90.980049 | BC182: 95.029999 | BD182: 25.854588 | BE182: 34.23 | BF182: 108.69994 | BG182: 14.9 | BH182: 18.644621 | BI182: 23.647795 | BJ182: 262.56741 | BK182: 354.76999 | BL182: 153.97 | BM182: 7.9099998 | BN182: 119.12545 | BO182: 981.80902 | BP182: 4.2494612 | BQ182: 237.67999 | BR182: 9.1700001 | BS182: 9.9499998 | BT182: 118.35723 | BU182: 39.888035 | BV182: 46.283295 | BW182: 67.25 | BX182: 97.416893 | BY182: 718.77338 | BZ182: 76.281654 | CA182: 151 | CB182: 11.19 | CC182: 227.63 | CD182: 369.21988 | CE182: 109.40202 | CF182: 17.309269 | CG182: 70.324089 | CH182: 97.860153 | CI182: 7.79 | CJ182: 178.35963 | CK182: 20.15 | CL182: 45.130001 | CM182: 3.1199999 | CN182: 33.847214 | CO182: 56.339954 | CP182: 11.58 | CQ182: 123.9502 | CR182: 64.66613 | CS182: 106.08746 | CT182: 25.93 | CU182: 30.950001 | CV182: 68.730003 | CW182: 33.461449 | CX182: 14.146786 | CY182: 66.629997 | CZ182: 46.84 | DA182: 4.2199998 | DB182: 8.0900002 | DC182: 138.88 | DD182: 92.93 | DE182: 73.809998 | DF182: 318.3132 | DG182: 374.57999 | DH182: 30.15 | DI182: 79.236137 | DJ182: 353.09076 | DK182: 356.15109 | DL182: 16.09 | DM182: 16.110001 | DN182: 128.69545 | DO182: 27.780001 | DP182: 86.360001 | DQ182: 249.36945 | DR182: 76.790001 | DS182: 30.790001 | DT182: 270.42014 | DU182: 162.47 | DV182: 5.7600002 | DW182: 2.3499999 | DX182: 10.37 | DY182: 107.04 | DZ182: 56.630001 | EA182: 45.317745 | EB182: 121.57768 | EC182: 2.6800001 | ED182: 280.64783 | EE182: 138.97545 | EF182: 237.31956 | EG182: 11.07 | EH182: 15.790449 | EI182: 82.561119 | EJ182: 64.020729 | EK182: 0.57999998 | EL182: 22.800489 | EM182: 13.69 | EN182: 55.860001 | EO182: 241.28604 | EP182: 214.86212 | EQ182: 65.25 | ER182: 321.57346 | ES182: 4.75 | ET182: 26.535 | EU182: 22.789284 | EV182: 488.26151 | EW182: 1.27 | EX182: 12.62 | EY182: 93.535965 | EZ182: 87.384254 | FA182: 79.53241 | FB182: 570.45129 | FC182: 70.919785 | FD182: 5.48 | FE182: 19.653635 | FF182: 117.54586 | FG182: 45.990002 | FH182: 252.52769 | FI182: 205.52861 | FJ182: 396.61334 | FK182: 115.35 | FL182: 4.3600001 | FM182: 84.484688 | FN182: 92.577278 | FO182: 11.985988 | FP182: 82 | FQ182: 6.8000002 | FR182: 1.52 | FS182: 160.17352 | FT182: 11.62 | FU182: 200.19598 | FV182: 111.95 | FW182: 54.02 | FX182: 4.48 | FY182: 8.2700005 | FZ182: 3.7 | GA182: 66.529999 | GB182: 263.22 | GC182: 58.52 | GD182: 130.21001 | GE182: 181.44571 | GF182: 230.79993 | GG182: 29.5 | GH182: 21.360001 | GI182: 23.25 | GJ182: 3.9300001 | GK182: 692.92853 | GL182: 9.5299997 | GM182: 9.7861557 | GN182: 41.5 | GO182: 172.21001 | GP182: 14.87 | GQ182: 9.1199999 | GR182: 196.59912 | GS182: 19.445 | GT182: 6.0100002 | GU182: 24.08 | GV182: 105.05 | GW182: 116.94 | GX182: 53.959999 | GY182: 231.47263 | GZ182: 176.8226 | HA182: 3.04 | HB182: 13.08 | HC182: 98.195915 | HD182: 89.010445 | HE182: 9.7299995 | HF182: 12.99 | HG182: 85.302422 | HH182: 154.28 | HI182: 5.3800001 | HJ182: 15.87 | HK182: 20.76 | HL182: 6.75 | HM182: 721.77362 | HN182: 8.46 | HO182: 61.694206 | HP182: 45.09 | HQ182: 9.6599998 | HR182: 1.96 | HS182: 18.709999 | HT182: 40.09 | HU182: 7.0300002 | HV182: 88.529854 | HW182: 30.374939 | HX182: 9.21 | HY182: 184.48524 | HZ182: 140.38782 | IA182: 381.59 | IB182: 19.290001 | IC182: 207.09 | ID182: 102.78 | IE182: 68.610001 | IF182: 46.77 | IG182: 130.40137 | IH182: 0.86000001 | II182: 72.690002 | IJ182: 20.33 | IK182: 6.1999998 | IL182: 16.049999 | IM182: 256.9968 | IN182: 15.05 | IO182: 6.98 | IP182: 46.163055 | IQ182: 26.23 | IR182: 81.502083 | IS182: 28.479122 | IT182: 120.30199 | IU182: 1.23 | IV182: 16.747131 | IW182: 23.190001 | IX182: 57.832924 | IY182: 176.41965 | IZ182: 152.17886 | JA182: 82.370003 | JB182: 14.86 | JC182: 66.629997 | JD182: 24.280001 | JE182: 150.32213 | JF182: 65.380707 | JG182: 93.959999 | JH182: 0.23999999 | JI182: 80.727257
A183: 2026-06-11 | B183: 68.846397 | C183: 22.09 | D183: 14.65 | E183: 172.78 | F183: 60.344452 | G183: 295.37524 | H183: 35.593735 | I183: 130.87 | J183: 89.015114 | K183: 21.389999 | L183: 5.3000002 | M183: 78.40239 | N183: 18.152935 | O183: 115.86646 | P183: 66.489998 | Q183: 16.906487 | R183: 110.69507 | S183: 1.61 | T183: 132.46001 | U183: 5.2800002 | V183: 488.45001 | W183: 344.32068 | X183: 8.1689997 | Y183: 76.010124 | Z183: 39.509998 | AA183: 241.50999 | AB183: 156.39999 | AC183: 5.4899998 | AD183: 21.43 | AE183: 76.115173 | AF183: 10.14 | AG183: 4.8600001 | AH183: 13.69 | AI183: 16.159769 | AJ183: 36.433495 | AK183: 8.1300001 | AL183: 42.360001 | AM183: 54.879997 | AN183: 19.623388 | AO183: 75.297379 | AP183: 29.41 | AQ183: 16.4 | AR183: 11.189747 | AS183: 26.290001 | AT183: 12.256883 | AU183: 56.264866 | AV183: 46.248188 | AW183: 1.11 | AX183: 17.65 | AY183: 137.37158 | AZ183: 220.67963 | BA183: 14.643207 | BB183: 89.674484 | BC183: 98.970001 | BD183: 27.973492 | BE183: 34.900002 | BF183: 106.01377 | BG183: 16.17 | BH183: 19.360573 | BI183: 23.647795 | BJ183: 260.95499 | BK183: 363.57999 | BL183: 160.42999 | BM183: 8.4499998 | BN183: 114.59566 | BO183: 974.14117 | BP183: 4.3967962 | BQ183: 264.76001 | BR183: 9.7399998 | BS183: 10.8 | BT183: 121.37594 | BU183: 39.539017 | BV183: 47.240673 | BW183: 67.82 | BX183: 99.861763 | BY183: 756.97021 | BZ183: 81.628448 | CA183: 154.59 | CB183: 11.765 | CC183: 234.24001 | CD183: 390.80423 | CE183: 113.75979 | CF183: 17.299366 | CG183: 69.469383 | CH183: 99.576996 | CI183: 8.25 | CJ183: 180.39206 | CK183: 21.360001 | CL183: 44.549999 | CM183: 3.21 | CN183: 33.244209 | CO183: 55.420238 | CP183: 11.16 | CQ183: 123.10761 | CR183: 66.0009 | CS183: 109.27775 | CT183: 28.370001 | CU183: 32.110001 | CV183: 69.440002 | CW183: 34.481739 | CX183: 14.552393 | CY183: 77.150002 | CZ183: 50.150002 | DA183: 4.23 | DB183: 8.6099997 | DC183: 145.06 | DD183: 95.529999 | DE183: 77.720001 | DF183: 332.34573 | DG183: 386.32001 | DH183: 33.27 | DI183: 80.683144 | DJ183: 356.32867 | DK183: 357.54016 | DL183: 16.870001 | DM183: 17.780001 | DN183: 127.83921 | DO183: 28.870001 | DP183: 92.230003 | DQ183: 264.47214 | DR183: 79.129997 | DS183: 30.719999 | DT183: 272.89243 | DU183: 166.21001 | DV183: 5.4299998 | DW183: 2.395 | DX183: 10.66 | DY183: 116.96 | DZ183: 57.990002 | EA183: 49.590187 | EB183: 123.36153 | EC183: 2.75 | ED183: 288.96631 | EE183: 143.61261 | EF183: 237.16034 | EG183: 10.88 | EH183: 15.830324 | EI183: 81.514168 | EJ183: 63.683052 | EK183: 0.60799998 | EL183: 24.082085 | EM183: 13.92 | EN183: 57.18 | EO183: 239.61966 | EP183: 219.69228 | EQ183: 71.629997 | ER183: 362.2648 | ES183: 4.6900001 | ET183: 30.639999 | EU183: 24.639193 | EV183: 485.69583 | EW183: 1.3 | EX183: 13.61 | EY183: 95.817329 | EZ183: 92.384171 | FA183: 79.611702 | FB183: 567.90363 | FC183: 69.251778 | FD183: 5.5100002 | FE183: 20.912975 | FF183: 119.19421 | FG183: 49.639999 | FH183: 280.64075 | FI183: 211.49577 | FJ183: 389.60657 | FK183: 120.15 | FL183: 4.5799999 | FM183: 84.206772 | FN183: 97.387268 | FO183: 12.777795 | FP183: 81.269997 | FQ183: 7.0700002 | FR183: 1.52 | FS183: 159.98409 | FT183: 12.09 | FU183: 204.64101 | FV183: 119.68 | FW183: 57.860001 | FX183: 4.4699998 | FY183: 8.3000002 | FZ183: 3.8 | GA183: 69.339996 | GB183: 279.53 | GC183: 64.330002 | GD183: 131.08 | GE183: 179.28365 | GF183: 232.08965 | GG183: 29.66 | GH183: 23.440001 | GI183: 23.82 | GJ183: 4 | GK183: 716.33276 | GL183: 9.9099998 | GM183: 9.8933735 | GN183: 43.490002 | GO183: 173.25999 | GP183: 17.09 | GQ183: 9.8400002 | GR183: 204.08121 | GS183: 20.629999 | GT183: 6.0300002 | GU183: 26.139999 | GV183: 114.78 | GW183: 119.64 | GX183: 54.740002 | GY183: 238.64876 | GZ183: 183.6001 | HA183: 3.1500001 | HB183: 13.56 | HC183: 101.69581 | HD183: 88.442101 | HE183: 10.71 | HF183: 14.73 | HG183: 85.104156 | HH183: 163.57001 | HI183: 5.3299999 | HJ183: 16.67 | HK183: 21.15 | HL183: 7 | HM183: 734.0415 | HN183: 9 | HO183: 61.406052 | HP183: 45.549999 | HQ183: 10.89 | HR183: 2.0599999 | HS183: 19.040001 | HT183: 39.450001 | HU183: 7.3099999 | HV183: 91.366776 | HW183: 31.29418 | HX183: 9.2600002 | HY183: 184.75371 | HZ183: 144.84094 | IA183: 399.14999 | IB183: 18.9 | IC183: 206.62 | ID183: 112.61 | IE183: 69.550003 | IF183: 48.189999 | IG183: 136.98677 | IH183: 0.89899999 | II183: 77.379997 | IJ183: 22.559999 | IK183: 6.0999999 | IL183: 17.299999 | IM183: 254.61601 | IN183: 15.26 | IO183: 7.1199999 | IP183: 46.153221 | IQ183: 26.860001 | IR183: 81.929626 | IS183: 28.340149 | IT183: 120.21221 | IU183: 1.27 | IV183: 17.256437 | IW183: 25.35 | IX183: 56.711014 | IY183: 182.99181 | IZ183: 153.41341 | JA183: 86.150002 | JB183: 14.46 | JC183: 69.089996 | JD183: 23.02 | JE183: 152.50114 | JF183: 65.996574 | JG183: 92.32 | JH183: 0.36000001 | JI183: 80.836494
A184: 2026-06-12 | B184: 68.636803 | C184: 20.43 | D184: 14.98 | E184: 169.05 | F184: 60.523636 | G184: 290.87915 | H184: 35.632847 | I184: 132.28 | J184: 87.555527 | K184: 21.09 | L184: 5.0799999 | M184: 79.73394 | N184: 18.649187 | O184: 117.20969 | P184: 66.169998 | Q184: 17.635902 | R184: 112.15067 | S184: 1.52 | T184: 133.5 | U184: 5.2800002 | V184: 511.57001 | W184: 354.61041 | X184: 8.1059999 | Y184: 82.627937 | Z184: 40.02 | AA184: 238.55 | AB184: 163.24001 | AC184: 5.5900002 | AD184: 21.469999 | AE184: 76.784157 | AF184: 9.7600002 | AG184: 4.7800002 | AH184: 13.6 | AI184: 16.131472 | AJ184: 37.740345 | AK184: 8.2799997 | AL184: 43 | AM184: 55.735634 | AN184: 19.919662 | AO184: 76.693947 | AP184: 29.030001 | AQ184: 16.889999 | AR184: 11.828591 | AS184: 26.780001 | AT184: 12.266849 | AU184: 56.492298 | AV184: 46.248188 | AW184: 1.14 | AX184: 17.83 | AY184: 139.12267 | AZ184: 223.36378 | BA184: 14.553738 | BB184: 89.791405 | BC184: 100.96 | BD184: 29.027967 | BE184: 34.810001 | BF184: 108.91881 | BG184: 16.48 | BH184: 20.066584 | BI184: 24.170671 | BJ184: 268.27063 | BK184: 385.03 | BL184: 159.78 | BM184: 8.5900002 | BN184: 116.20493 | BO184: 980.79059 | BP184: 4.342515 | BQ184: 250.81 | BR184: 9.8999996 | BS184: 10.62 | BT184: 120.64866 | BU184: 40.227085 | BV184: 47.440128 | BW184: 64.099998 | BX184: 101.33265 | BY184: 757.73999 | BZ184: 82.855415 | CA184: 150.58 | CB184: 11.72 | CC184: 229.89999 | CD184: 394.91742 | CE184: 114.21746 | CF184: 17.438 | CG184: 70.821007 | CH184: 99.279282 | CI184: 7.8000002 | CJ184: 181.73386 | CK184: 20.780001 | CL184: 45.029999 | CM184: 3.1600001 | CN184: 33.461685 | CO184: 55.776257 | CP184: 11.1 | CQ184: 123.88081 | CR184: 66.37941 | CS184: 108.28078 | CT184: 27.559999 | CU184: 31.59 | CV184: 69.480003 | CW184: 34.769001 | CX184: 14.681 | CY184: 75.279999 | CZ184: 50.759998 | DA184: 4.3200002 | DB184: 8.9300003 | DC184: 146.3 | DD184: 97.540001 | DE184: 80.029999 | DF184: 334.88254 | DG184: 386.54001 | DH184: 33.360001 | DI184: 81.331802 | DJ184: 357.92764 | DK184: 359.44894 | DL184: 17.01 | DM184: 17.4 | DN184: 129.05388 | DO184: 26.82 | DP184: 93.190002 | DQ184: 264.54211 | DR184: 79.190002 | DS184: 30.92 | DT184: 270.30099 | DU184: 160.97 | DV184: 5.6100001 | DW184: 2.4000001 | DX184: 11.09 | DY184: 124.57 | DZ184: 57.849998 | EA184: 47.016785 | EB184: 125.40161 | EC184: 2.75 | ED184: 291.49368 | EE184: 144.56 | EF184: 239.68787 | EG184: 10.73 | EH184: 16.179228 | EI184: 81.603065 | EJ184: 64.269028 | EK184: 0.59100002 | EL184: 23.853582 | EM184: 14.32 | EN184: 57.490002 | EO184: 240.75719 | EP184: 219.42392 | EQ184: 71.230003 | ER184: 366.55179 | ES184: 4.6999998 | ET184: 26.620001 | EU184: 24.963911 | EV184: 489.16003 | EW184: 1.3 | EX184: 14.08 | EY184: 96.265625 | EZ184: 94.67041 | FA184: 79.482857 | FB184: 566.45496 | FC184: 69.765762 | FD184: 5.6799998 | FE184: 22.499546 | FF184: 117.50639 | FG184: 49.91 | FH184: 279.63101 | FI184: 212.86821 | FJ184: 390.0058 | FK184: 123.97 | FL184: 4.7199998 | FM184: 85.34819 | FN184: 100.02179 | FO184: 13.589397 | FP184: 80.339996 | FQ184: 7.4400001 | FR184: 1.49 | FS184: 161.12064 | FT184: 12.19 | FU184: 204.96066 | FV184: 121.88 | FW184: 57.490002 | FX184: 4.4400001 | FY184: 8.3599997 | FZ184: 3.8699999 | GA184: 72.309998 | GB184: 279.62 | GC184: 64.129997 | GD184: 127.99 | GE184: 182.78461 | GF184: 235.78023 | GG184: 30.07 | GH184: 24.09 | GI184: 23.370001 | GJ184: 3.8299999 | GK184: 720.54816 | GL184: 9.9300003 | GM184: 9.8933735 | GN184: 43.310001 | GO184: 162.10001 | GP184: 15.12 | GQ184: 10.28 | GR184: 207.07404 | GS184: 20.98 | GT184: 6.04 | GU184: 26.610001 | GV184: 102.39 | GW184: 143.66 | GX184: 54.900002 | GY184: 239.66679 | GZ184: 182.92233 | HA184: 3.1500001 | HB184: 13.85 | HC184: 102.45147 | HD184: 90.835121 | HE184: 8.4700003 | HF184: 15.98 | HG184: 84.91581 | HH184: 166.71001 | HI184: 5.2600002 | HJ184: 16.58 | HK184: 20.530001 | HL184: 6.9000001 | HM184: 738.01135 | HN184: 8.9200001 | HO184: 61.207329 | HP184: 44.41 | HQ184: 11 | HR184: 2.0899999 | HS184: 19.139999 | HT184: 40.080002 | HU184: 7.3400002 | HV184: 93.013382 | HW184: 31.843727 | HX184: 9.2200003 | HY184: 188.01488 | HZ184: 146.86327 | IA184: 406.42999 | IB184: 19.280001 | IC184: 204.08 | ID184: 115.52 | IE184: 68.849998 | IF184: 48.970001 | IG184: 139.1021 | IH184: 0.91000003 | II184: 77 | IJ184: 21.99 | IK184: 6.0999999 | IL184: 16.719999 | IM184: 257.67419 | IN184: 15.53 | IO184: 7.8499999 | IP184: 47.303612 | IQ184: 26.98 | IR184: 83.252037 | IS184: 28.250811 | IT184: 120.75092 | IU184: 1.3099999 | IV184: 17.945496 | IW184: 26.059999 | IX184: 57.137936 | IY184: 184.57991 | IZ184: 153.13463 | JA184: 86.989998 | JB184: 14.49 | JC184: 69.519997 | JD184: 23.1 | JE184: 153.53592 | JF184: 66.801163 | JG184: 93.68 | JH184: 0.28 | JI184: 79.019165
A185: 2026-06-15 | B185: 64.035736 | C185: 19.780001 | D185: 15.46 | E185: 191.55 | F185: 60.762547 | G185: 296.16458 | H185: 35.23193 | I185: 138.96001 | J185: 88.042053 | K185: 21.27 | L185: 5.5500002 | M185: 78.770058 | N185: 18.321659 | O185: 116.3739 | P185: 71.900002 | Q185: 18.884905 | R185: 112.20052 | S185: 1.52 | T185: 134.2 | U185: 5.1100001 | V185: 547.26001 | W185: 352.92044 | X185: 8.3579998 | Y185: 85.283058 | Z185: 41.07 | AA185: 246.02 | AB185: 169.09 | AC185: 5.4400001 | AD185: 21.17 | AE185: 79.175552 | AF185: 9.8299999 | AG185: 4.6999998 | AH185: 17.92 | AI185: 16.303696 | AJ185: 38.116562 | AK185: 8.29 | AL185: 43.740002 | AM185: 55.586391 | AN185: 19.611679 | AO185: 75.600136 | AP185: 31.120001 | AQ185: 16.57 | AR185: 11.778682 | AS185: 27.799999 | AT185: 13.392886 | AU185: 55.612236 | AV185: 46.248188 | AW185: 1.16 | AX185: 18.32 | AY185: 140.4957 | AZ185: 225.90823 | BA185: 13.977155 | BB185: 87.468185 | BC185: 107.02 | BD185: 29.96307 | BE185: 34.66 | BF185: 106.35204 | BG185: 17.139999 | BH185: 20.862087 | BI185: 23.647795 | BJ185: 264.83676 | BK185: 413.84 | BL185: 169.62 | BM185: 9.1400003 | BN185: 111.5162 | BO185: 977.89526 | BP185: 4.342515 | BQ185: 259.41 | BR185: 10.48 | BS185: 10.875 | BT185: 119.72212 | BU185: 38.481983 | BV185: 47.26062 | BW185: 68.900002 | BX185: 100.06053 | BY185: 762.59003 | BZ185: 83.86293 | CA185: 168.09 | CB185: 11.79 | CC185: 233.09 | CD185: 408.39514 | CE185: 115.79939 | CF185: 17.170637 | CG185: 66.835709 | CH185: 100.91673 | CI185: 8.4399996 | CJ185: 183.64076 | CK185: 20.07 | CL185: 44.195 | CM185: 3.26 | CN185: 32.848797 | CO185: 55.281788 | CP185: 11.11 | CQ185: 124.18811 | CR185: 67.810463 | CS185: 108.84905 | CT185: 28.74 | CU185: 32.150002 | CV185: 72.190002 | CW185: 34.639999 | CX185: 14.611751 | CY185: 74.309998 | CZ185: 50.470001 | DA185: 4.27 | DB185: 9.4499998 | DC185: 149.49001 | DD185: 100.12 | DE185: 85.269997 | DF185: 341.83392 | DG185: 396.54999 | DH185: 33.630001 | DI185: 83.8965 | DJ185: 366.8718 | DK185: 369.11276 | DL185: 17.450001 | DM185: 17.49 | DN185: 129.25302 | DO185: 30.17 | DP185: 98.120003 | DQ185: 270.30933 | DR185: 81.260002 | DS185: 30.860001 | DT185: 266.79614 | DU185: 166.89 | DV185: 5.6999998 | DW185: 2.3299999 | DX185: 11.38 | DY185: 127.86 | DZ185: 61.18 | EA185: 45.242565 | EB185: 125.30636 | EC185: 2.8299999 | ED185: 293.8725 | EE185: 146.06 | EF185: 234.50345 | EG185: 11.34 | EH185: 16.139355 | EI185: 80.430069 | EJ185: 63.623455 | EK185: 0.56 | EL185: 23.893322 | EM185: 14.37 | EN185: 60.75 | EO185: 234.74026 | EP185: 218.83755 | EQ185: 71.800003 | ER185: 388.64624 | ES185: 4.6999998 | ET185: 25.76 | EU185: 24.470144 | EV185: 489.81891 | EW185: 1.36 | EX185: 14.64 | EY185: 94.402687 | EZ185: 99.720032 | FA185: 79.661247 | FB185: 593.47998 | FC185: 68.496033 | FD185: 5.79 | FE185: 22.330973 | FF185: 114.22575 | FG185: 52.130001 | FH185: 308.80383 | FI185: 216.78664 | FJ185: 399.00888 | FK185: 131.14 | FL185: 5.4400001 | FM185: 85.477226 | FN185: 105.58022 | FO185: 14.262434 | FP185: 81.669998 | FQ185: 8.1199999 | FR185: 1.25 | FS185: 161.33002 | FT185: 12.43 | FU185: 212.21254 | FV185: 125.83 | FW185: 60.740002 | FX185: 4.6100001 | FY185: 8.2600002 | FZ185: 3.8399999 | GA185: 74.699997 | GB185: 284.54001 | GC185: 63.869999 | GD185: 134.71001 | GE185: 180.31508 | GF185: 228.73637 | GG185: 29.040001 | GH185: 26.01 | GI185: 26.26 | GJ185: 3.7 | GK185: 743.18329 | GL185: 11.1 | GM185: 10.088318 | GN185: 45.66 | GO185: 181.88 | GP185: 14.83 | GQ185: 11.07 | GR185: 215.00504 | GS185: 22.700001 | GT185: 5.8299999 | GU185: 27.379999 | GV185: 109.25 | GW185: 140.89999 | GX185: 54.860001 | GY185: 236.31328 | GZ185: 183.03197 | HA185: 3.29 | HB185: 13.62 | HC185: 101.00975 | HD185: 90.685562 | HE185: 8.6099997 | HF185: 15.4 | HG185: 81.892303 | HH185: 174.3 | HI185: 5.71 | HJ185: 17.129999 | HK185: 20.4 | HL185: 7.3299999 | HM185: 751.02545 | HN185: 8.8999996 | HO185: 59.26976 | HP185: 43.860001 | HQ185: 11.29 | HR185: 2.27 | HS185: 19.459999 | HT185: 39.360001 | HU185: 7.46 | HV185: 88.728241 | HW185: 31.324156 | HX185: 9.2299995 | HY185: 187.77625 | HZ185: 150.4198 | IA185: 411.14999 | IB185: 19.27 | IC185: 202 | ID185: 119.97 | IE185: 72.849998 | IF185: 49.549999 | IG185: 146.41592 | IH185: 1.08 | II185: 77.010002 | IJ185: 23.02 | IK185: 5.1900001 | IL185: 16.59 | IM185: 246.2085 | IN185: 15 | IO185: 7.4400001 | IP185: 46.281044 | IQ185: 26.83 | IR185: 82.665405 | IS185: 28.28059 | IT185: 120.53145 | IU185: 1.25 | IV185: 18.295017 | IW185: 28.17 | IX185: 55.152256 | IY185: 191.56158 | IZ185: 152.21867 | JA185: 87.029999 | JB185: 14.49 | JC185: 74.349998 | JD185: 22.57 | JE185: 153.89412 | JF185: 65.827705 | JG185: 94.25 | JH185: 0.235 | JI185: 79.39653
A186: 2026-06-16 | B186: 62.74823 | C186: 22.129999 | D186: 15.71 | E186: 170.81 | F186: 60.095589 | G186: 298.98215 | H186: 35.642628 | I186: 141.2 | J186: 89.978249 | K186: 20.940001 | L186: 5.4400001 | M186: 77.527939 | N186: 17.408556 | O186: 116.82166 | P186: 74.690002 | Q186: 19.40449 | R186: 112.86849 | S186: 1.48 | T186: 132.31 | U186: 4.9899998 | V186: 507.29001 | W186: 357.49033 | X186: 8.316 | Y186: 86.391022 | Z186: 40.459999 | AA186: 246 | AB186: 168.00999 | AC186: 5.3899999 | AD186: 21 | AE186: 79.285385 | AF186: 9.3999996 | AG186: 4.54 | AH186: 19.940001 | AI186: 16.303696 | AJ186: 36.473095 | AK186: 8.4399996 | AL186: 43.400002 | AM186: 56.551472 | AN186: 19.860054 | AO186: 73.81292 | AP186: 30.99 | AQ186: 16.120001 | AR186: 11.818609 | AS186: 27.67 | AT186: 13.034149 | AU186: 55.295803 | AV186: 45.781437 | AW186: 1.2 | AX186: 18.25 | AY186: 142.26669 | AZ186: 227.22537 | BA186: 13.311103 | BB186: 86.86692 | BC186: 107.88 | BD186: 30.739006 | BE186: 34.720001 | BF186: 105.04874 | BG186: 17.26 | BH186: 21.289671 | BI186: 23.341963 | BJ186: 260.37772 | BK186: 382.81 | BL186: 169.27 | BM186: 9.4200001 | BN186: 110.60229 | BO186: 985.11377 | BP186: 4.3967962 | BQ186: 239.17999 | BR186: 9.5600004 | BS186: 10.27 | BT186: 119.12436 | BU186: 38.521873 | BV186: 46.771957 | BW186: 70.040001 | BX186: 100.10028 | BY186: 764.60999 | BZ186: 82.935219 | CA186: 170.03 | CB186: 11.54 | CC186: 231.11 | CD186: 403.41336 | CE186: 113.17279 | CF186: 17.289463 | CG186: 66.169838 | CH186: 100.50985 | CI186: 8.1599998 | CJ186: 189.15297 | CK186: 20.59 | CL186: 44.43 | CM186: 3.2 | CN186: 32.581894 | CO186: 55.390568 | CP186: 11.37 | CQ186: 124.96131 | CR186: 67.471161 | CS186: 108.98863 | CT186: 27.41 | CU186: 32.349998 | CV186: 73.339996 | CW186: 34.41 | CX186: 14.255607 | CY186: 70.150002 | CZ186: 50.650002 | DA186: 4.27 | DB186: 9.6899996 | DC186: 147.02 | DD186: 96.010002 | DE186: 87.239998 | DF186: 351.29211 | DG186: 397.63 | DH186: 33.18 | DI186: 82.339722 | DJ186: 370.85925 | DK186: 373.01025 | DL186: 17.26 | DM186: 17.700001 | DN186: 130.44778 | DO186: 31.469999 | DP186: 96.709999 | DQ186: 277.28595 | DR186: 81.5 | DS186: 31.110001 | DT186: 268.8812 | DU186: 164.28 | DV186: 5.3200002 | DW186: 2.3 | DX186: 10.65 | DY186: 117.05 | DZ186: 56.060001 | EA186: 43.308868 | EB186: 127.22149 | EC186: 2.6300001 | ED186: 291.31912 | EE186: 145.17 | EF186: 234.02579 | EG186: 10.75 | EH186: 15.989824 | EI186: 79.803802 | EJ186: 63.692978 | EK186: 0.50999999 | EL186: 23.654884 | EM186: 16.360001 | EN186: 60.740002 | EO186: 230.35977 | EP186: 222.64403 | EQ186: 68.010002 | ER186: 369.08002 | ES186: 4.6700001 | ET186: 23.360001 | EU186: 24.727934 | EV186: 500.491 | EW186: 1.3200001 | EX186: 14.42 | EY186: 95.528419 | EZ186: 95.058075 | FA186: 80.592842 | FB186: 600.21002 | FC186: 69.086609 | FD186: 5.73 | FE186: 21.50794 | FF186: 114.49416 | FG186: 55.400002 | FH186: 278.60129 | FI186: 219.62103 | FJ186: 393.09 | FK186: 122.81 | FL186: 5.1199999 | FM186: 85.586403 | FN186: 108.21474 | FO186: 14.688031 | FP186: 78.720001 | FQ186: 8.3299999 | FR186: 1.23 | FS186: 160.7717 | FT186: 12.72 | FU186: 207.17818 | FV186: 125.62 | FW186: 57.450001 | FX186: 4.75 | FY186: 8.7799997 | FZ186: 3.77 | GA186: 73.260002 | GB186: 279.89999 | GC186: 60.380001 | GD186: 133.25 | GE186: 182.54659 | GF186: 232.83371 | GG186: 29.09 | GH186: 25.77 | GI186: 23.940001 | GJ186: 3.6400001 | GK186: 729.05878 | GL186: 10.12 | GM186: 10.088318 | GN186: 49.34 | GO186: 175.39 | GP186: 13.5 | GQ186: 11.31 | GR186: 221.00067 | GS186: 20.639999 | GT186: 5.5900002 | GU186: 27.42 | GV186: 104.63 | GW186: 137.95 | GX186: 57.169998 | GY186: 234.03767 | GZ186: 186.15161 | HA186: 3.1800001 | HB186: 13.38 | HC186: 101.09924 | HD186: 93.397652 | HE186: 8.0500002 | HF186: 14.8 | HG186: 81.535431 | HH186: 161.59 | HI186: 5.1599998 | HJ186: 17.709999 | HK186: 20.379999 | HL186: 7.0300002 | HM186: 746.54816 | HN186: 8.7399998 | HO186: 57.789257 | HP186: 43.580002 | HQ186: 11.03 | HR186: 2.22 | HS186: 19.35 | HT186: 39.459999 | HU186: 7.5700002 | HV186: 86.605507 | HW186: 31.523989 | HX186: 8.9099998 | HY186: 183.30208 | HZ186: 148.82584 | IA186: 404.66 | IB186: 18.959999 | IC186: 192.67999 | ID186: 118.51 | IE186: 73.25 | IF186: 50.459999 | IG186: 143.82166 | IH186: 0.95200002 | II186: 76.099998 | IJ186: 21.74 | IK186: 5.1999998 | IL186: 17.27 | IM186: 243.19017 | IN186: 14.89 | IO186: 7.52 | IP186: 45.946739 | IQ186: 26.6 | IR186: 84.564507 | IS186: 28.598238 | IT186: 120.74094 | IU186: 1.22 | IV186: 18.444813 | IW186: 28.01 | IX186: 54.963615 | IY186: 186.21796 | IZ186: 152.26846 | JA186: 85.980003 | JB186: 13.84 | JC186: 74.68 | JD186: 23.299999 | JE186: 156.87906 | JF186: 66.284637 | JG186: 92.07 | JH186: 0.22499999 | JI186: 78.78083
A187: 2026-06-17 | B187: 61.610439 | C187: 20.23 | D187: 15.42 | E187: 167.34 | F187: 57.835907 | G187: 295.69498 | H187: 35.359051 | I187: 140.53999 | J187: 87.87326 | K187: 21.6 | L187: 5.3600001 | M187: 76.017525 | N187: 16.971853 | O187: 115.65751 | P187: 70.730003 | Q187: 18.535183 | R187: 111.63223 | S187: 1.4400001 | T187: 127.86 | U187: 5.3499999 | V187: 512.47998 | W187: 355.6604 | X187: 8.1689997 | Y187: 86.27124 | Z187: 40.130001 | AA187: 237.5 | AB187: 164.92999 | AC187: 5.0999999 | AD187: 21.790001 | AE187: 80.433655 | AF187: 8.6199999 | AG187: 4.8000002 | AH187: 22.6 | AI187: 15.959249 | AJ187: 37.06712 | AK187: 8.2399998 | AL187: 44.57 | AM187: 56.243042 | AN187: 19.701094 | AO187: 71.3909 | AP187: 32.48 | AQ187: 15.52 | AR187: 12.048193 | AS187: 27.190001 | AT187: 12.45339 | AU187: 54.662949 | AV187: 45.781437 | AW187: 1.1900001 | AX187: 17.92 | AY187: 143.05269 | AZ187: 225.7885 | BA187: 12.416406 | BB187: 84.540749 | BC187: 105.67 | BD187: 29.754164 | BE187: 34.189999 | BF187: 105.30741 | BG187: 16.780001 | BH187: 20.404673 | BI187: 22.385002 | BJ187: 251.36002 | BK187: 378.85001 | BL187: 164.92 | BM187: 9.3999996 | BN187: 110.47316 | BO187: 964.05725 | BP187: 4.3502693 | BQ187: 249.33 | BR187: 10.07 | BS187: 10 | BT187: 116.89271 | BU187: 37.803886 | BV187: 45.445587 | BW187: 62.860001 | BX187: 98.549889 | BY187: 777.28998 | BZ187: 82.047417 | CA187: 165.66 | CB187: 11.93 | CC187: 226.63 | CD187: 418.62823 | CE187: 108.13847 | CF187: 17.358782 | CG187: 65.503967 | CH187: 100.09304 | CI187: 8.1000004 | CJ187: 185.80592 | CK187: 21.42 | CL187: 42.580002 | CM187: 3.1500001 | CN187: 32.127171 | CO187: 54.342293 | CP187: 10.97 | CQ187: 122.65163 | CR187: 66.872398 | CS187: 107.56297 | CT187: 27.4 | CU187: 32.759998 | CV187: 72.830002 | CW187: 34.110001 | CX187: 13.810429 | CY187: 70.220001 | CZ187: 51.919998 | DA187: 3.8699999 | DB187: 9.4300003 | DC187: 144.14 | DD187: 96.639999 | DE187: 84.360001 | DF187: 356.58551 | DG187: 388.60001 | DH187: 33.040001 | DI187: 79.415771 | DJ187: 361.86508 | DK187: 363.55634 | DL187: 16.559999 | DM187: 17.26 | DN187: 129.07381 | DO187: 31.889999 | DP187: 105.2 | DQ187: 283.09314 | DR187: 79.639999 | DS187: 30.5 | DT187: 260.48145 | DU187: 159.09 | DV187: 5.3200002 | DW187: 2.25 | DX187: 10.12 | DY187: 121.1 | DZ187: 54.689999 | EA187: 44.903671 | EB187: 124.47284 | EC187: 2.55 | ED187: 289.12488 | EE187: 143.62 | EF187: 233.05061 | EG187: 10.41 | EH187: 15.840293 | EI187: 79.455879 | EJ187: 61.39872 | EK187: 0.50199997 | EL187: 23.237621 | EM187: 15.35 | EN187: 57.279999 | EO187: 230.90858 | EP187: 215.93549 | EQ187: 68.650002 | ER187: 374.17999 | ES187: 4.5500002 | ET187: 22.719999 | EU187: 23.686861 | EV187: 492.16495 | EW187: 1.3200001 | EX187: 13.92 | EY187: 92.808716 | EZ187: 93.547173 | FA187: 77.441277 | FB187: 567.58002 | FC187: 67.866096 | FD187: 5.5900002 | FE187: 22.321056 | FF187: 114.76259 | FG187: 61.799999 | FH187: 289.4686 | FI187: 223.72844 | FJ187: 378.19803 | FK187: 116.56 | FL187: 4.9400001 | FM187: 85.090134 | FN187: 105.45049 | FO187: 14.193151 | FP187: 76.959999 | FQ187: 8.1000004 | FR187: 1.34 | FS187: 154.34123 | FT187: 12.89 | FU187: 204.42125 | FV187: 123.31 | FW187: 58.82 | FX187: 4.4499998 | FY187: 8.3400002 | FZ187: 3.79 | GA187: 72.669998 | GB187: 282.13 | GC187: 59.68 | GD187: 130.63 | GE187: 177.96457 | GF187: 231.28606 | GG187: 28.35 | GH187: 24.9 | GI187: 22.92 | GJ187: 3.97 | GK187: 721.71686 | GL187: 9.7700005 | GM187: 10.088318 | GN187: 48.02 | GO187: 165.95 | GP187: 14.36 | GQ187: 11.39 | GR187: 217.8981 | GS187: 20.245001 | GT187: 5.5799999 | GU187: 27.43 | GV187: 107.98 | GW187: 137.28999 | GX187: 48.5 | GY187: 232.80006 | GZ187: 191.94237 | HA187: 3.1099999 | HB187: 13.05 | HC187: 99.249863 | HD187: 94.235214 | HE187: 7.3499999 | HF187: 14.8 | HG187: 79.681679 | HH187: 150.2 | HI187: 4.7399998 | HJ187: 17.42 | HK187: 20.24 | HL187: 6.96 | HM187: 737.22534 | HN187: 8.8199997 | HO187: 55.921238 | HP187: 43.580002 | HQ187: 11.21 | HR187: 2.24 | HS187: 19.110001 | HT187: 38.470001 | HU187: 7.5900002 | HV187: 88.212433 | HW187: 30.904501 | HX187: 8.6899996 | HY187: 180.26958 | HZ187: 145.31912 | IA187: 396.38 | IB187: 18.16 | IC187: 188.11 | ID187: 115.83 | IE187: 70.910004 | IF187: 49.73 | IG187: 138.43358 | IH187: 0.92900002 | II187: 72.470001 | IJ187: 23.549999 | IK187: 5.0700002 | IL187: 18.91 | IM187: 238.84695 | IN187: 14.53 | IO187: 7.52 | IP187: 45.071659 | IQ187: 26.24 | IR187: 83.331573 | IS187: 28.310371 | IT187: 117.84787 | IU187: 1.23 | IV187: 18.12525 | IW187: 27.860001 | IX187: 54.278553 | IY187: 185.57872 | IZ187: 150.04825 | JA187: 88.860001 | JB187: 13.44 | JC187: 72.839996 | JD187: 22.530001 | JE187: 153.29713 | JF187: 65.708511 | JG187: 87.389999 | JH187: 0.22 | JI187: 76.725159
A188: 2026-06-18 | B188: 59.255009 | C188: 18.82 | D188: 15.99 | E188: 161.85001 | F188: 59.826817 | G188: 297.7532 | H188: 35.153702 | I188: 142.41 | J188: 87.783897 | K188: 21.620001 | L188: 5.5700002 | M188: 74.626358 | N188: 17.676531 | O188: 114.89137 | P188: 73.919998 | Q188: 17.985622 | R188: 113.31714 | S188: 1.37 | T188: 124.91 | U188: 5.2800002 | V188: 537.37 | W188: 352.89044 | X188: 7.6440001 | Y188: 90.293831 | Z188: 43.400002 | AA188: 244.39 | AB188: 169.67 | AC188: 5.02 | AD188: 22.74 | AE188: 81.856506 | AF188: 8.6099997 | AG188: 4.6700001 | AH188: 24.379999 | AI188: 16.035791 | AJ188: 40.156048 | AK188: 8.8100004 | AL188: 44.84 | AM188: 55.914719 | AN188: 19.959404 | AO188: 73.95401 | AP188: 34.139999 | AQ188: 14.91 | AR188: 12.02823 | AS188: 27.870001 | AT188: 11.934499 | AU188: 53.397236 | AV188: 45.185585 | AW188: 1.2 | AX188: 17.93 | AY188: 142.33632 | AZ188: 221.2883 | BA188: 13.062576 | BB188: 80.874069 | BC188: 106.49 | BD188: 30.709164 | BE188: 34.139999 | BF188: 102.40238 | BG188: 17.24 | BH188: 20.742762 | BI188: 22.128496 | BJ188: 245.22882 | BK188: 389.57001 | BL188: 163.25999 | BM188: 10.01 | BN188: 107.02615 | BO188: 949.9397 | BP188: 4.4355688 | BQ188: 271.82999 | BR188: 10.15 | BS188: 10.77 | BT188: 119.09447 | BU188: 38.053188 | BV188: 45.505424 | BW188: 66.559998 | BX188: 97.71505 | BY188: 771.92999 | BZ188: 83.972664 | CA188: 173.46001 | CB188: 11.69 | CC188: 223 | CD188: 408.82443 | CE188: 112.87431 | CF188: 17.31917 | CG188: 64.102646 | CH188: 103.1 | CI188: 8.4899998 | CJ188: 186.86864 | CK188: 21.23 | CL188: 43.470001 | CM188: 3.3699999 | CN188: 31.366005 | CO188: 50.90078 | CP188: 11.24 | CQ188: 122.78049 | CR188: 67.58094 | CS188: 107.9119 | CT188: 27.860001 | CU188: 32.48 | CV188: 73.949997 | CW188: 33.73 | CX188: 13.909357 | CY188: 72.82 | CZ188: 53.66 | DA188: 3.8900001 | DB188: 9.2600002 | DC188: 144.73 | DD188: 96.639999 | DE188: 82.510002 | DF188: 357.19476 | DG188: 387.12 | DH188: 34.200001 | DI188: 79.126366 | DJ188: 367.22159 | DK188: 367.79358 | DL188: 16.190001 | DM188: 16.540001 | DN188: 127.68987 | DO188: 35.470001 | DP188: 108.15 | DQ188: 277.52585 | DR188: 79.330002 | DS188: 30.219999 | DT188: 247.32582 | DU188: 161.92999 | DV188: 5.4400001 | DW188: 2.29 | DX188: 10.31 | DY188: 133.99001 | DZ188: 56.549999 | EA188: 44.425228 | EB188: 126.84441 | EC188: 2.5899999 | ED188: 294.82001 | EE188: 144.82001 | EF188: 227.26912 | EG188: 10.06 | EH188: 16.199165 | EI188: 78.919083 | EJ188: 56.224228 | EK188: 0.5 | EL188: 23.545603 | EM188: 15.49 | EN188: 58.84 | EO188: 226.53807 | EP188: 220.83521 | EQ188: 71.07 | ER188: 389.04001 | ES188: 4.5300002 | ET188: 22.85 | EU188: 23.934734 | EV188: 488.97034 | EW188: 1.4 | EX188: 14.22 | EY188: 92.758904 | EZ188: 99.173317 | FA188: 78.630547 | FB188: 577.21997 | FC188: 68.033424 | FD188: 5.4400001 | FE188: 22.707783 | FF188: 113.2018 | FG188: 63.959999 | FH188: 310.50339 | FI188: 221.94823 | FJ188: 378.6871 | FK188: 112.53 | FL188: 4.9499998 | FM188: 86.102516 | FN188: 103.57439 | FO188: 14.094175 | FP188: 77.379997 | FQ188: 7.8000002 | FR188: 1.35 | FS188: 159.22639 | FT188: 12.71 | FU188: 210.45451 | FV188: 125.9 | FW188: 61.169998 | FX188: 4.4699998 | FY188: 8.4300003 | FZ188: 3.8800001 | GA188: 74.610001 | GB188: 287.78 | GC188: 67.150002 | GD188: 128.47 | GE188: 176.93312 | GF188: 230.20467 | GG188: 27.32 | GH188: 24.32 | GI188: 24.690001 | GJ188: 3.8 | GK188: 739.80701 | GL188: 10.76 | GM188: 10.020087 | GN188: 51.529999 | GO188: 174.96001 | GP188: 14.35 | GQ188: 12.45 | GR188: 214.30672 | GS188: 21.360001 | GT188: 5.3099999 | GU188: 28.1 | GV188: 107.24 | GW188: 138.07001 | GX188: 51.990002 | GY188: 232.35094 | GZ188: 184.98549 | HA188: 3.23 | HB188: 13.83 | HC188: 100.07512 | HD188: 91.43338 | HE188: 7.2800002 | HF188: 13.65 | HG188: 78.12532 | HH188: 158.23 | HI188: 4.6599998 | HJ188: 17.91 | HK188: 20.33 | HL188: 7.1199999 | HM188: 744.89026 | HN188: 8.9200001 | HO188: 54.977299 | HP188: 44.380001 | HQ188: 11.38 | HR188: 2.1700001 | HS188: 19.32 | HT188: 38.990002 | HU188: 8.0699997 | HV188: 83.728912 | HW188: 32.533157 | HX188: 8.7299995 | HY188: 180.6275 | HZ188: 142.95807 | IA188: 400.48999 | IB188: 18.51 | IC188: 186.17 | ID188: 118.32 | IE188: 71.639999 | IF188: 50.799999 | IG188: 142.49458 | IH188: 0.90799999 | II188: 76.419998 | IJ188: 24.639999 | IK188: 5.0100002 | IL188: 20.059999 | IM188: 235.3903 | IN188: 14.3 | IO188: 7.4899998 | IP188: 44.609535 | IQ188: 26.200001 | IR188: 81.730766 | IS188: 27.962944 | IT188: 116.90014 | IU188: 1.24 | IV188: 18.28503 | IW188: 28.98 | IX188: 53.385002 | IY188: 191.21201 | IZ188: 148.74399 | JA188: 93.279999 | JB188: 13.21 | JC188: 74.779999 | JD188: 22.879999 | JE188: 151.22757 | JF188: 65.728371 | JG188: 86.360001 | JH188: 0.17900001 | JI188: 78.165115
... A207: 2026-07-17 | B207: 43.894817 | C207: 17 | D207: 14.98 | E207: 102.41 | F207: 53.16 | G207: 333.45239 | H207: 37.060509 | I207: 145.98 | J207: 100.68 | K207: 25.6 | L207: 4.4400001 | M207: 85.358246 | N207: 17.030001 | O207: 124.09502 | P207: 76.07 | Q207: 15.797373 | R207: 114.9821 | S207: 1.15 | T207: 120.19 | U207: 5.7399998 | V207: 495.76001 | W207: 369.81998 | X207: 4.4499998 | Y207: 62.824383 | Z207: 33.029999 | AA207: 247.23 | AB207: 168.61 | AC207: 6.1199999 | AD207: 27.540001 | AE207: 75.599998 | AF207: 8.3400002 | AG207: 4.7399998 | AH207: 17.42 | AI207: 16.118364 | AJ207: 38.41 | AK207: 8.54 | AL207: 39.849998 | AM207: 60.958984 | AN207: 21.072123 | AO207: 84.523109 | AP207: 27.530001 | AQ207: 17.4 | AR207: 11.279585 | AS207: 22.120001 | AT207: 12.203922 | AU207: 60.740002 | AV207: 46.754345 | AW207: 0.88739997 | AX207: 10.74 | AY207: 128.70563 | AZ207: 228.52 | BA207: 11.780177 | BB207: 78.035339 | BC207: 85.620003 | BD207: 26.2724 | BE207: 37.439999 | BF207: 120.7976 | BG207: 13.03 | BH207: 16.884567 | BI207: 23.790001 | BJ207: 243.90503 | BK207: 277.60001 | BL207: 157.12 | BM207: 12 | BN207: 113.94997 | BO207: 939.37646 | BP207: 5.3040719 | BQ207: 202.67999 | BR207: 6.4000001 | BS207: 8.6300001 | BT207: 111.94 | BU207: 37.564556 | BV207: 50.611446 | BW207: 67.339996 | BX207: 106.80875 | BY207: 707.84003 | BZ207: 84.169998 | CA207: 184.14 | CB207: 12.81 | CC207: 258.69 | CD207: 395.68613 | CE207: 125.75 | CF207: 18.527254 | CG207: 88.044235 | CH207: 97.669998 | CI207: 9.6599998 | CJ207: 172.69583 | CK207: 31.48 | CL207: 52.740002 | CM207: 2.76 | CN207: 29.576769 | CO207: 52.630001 | CP207: 11.5 | CQ207: 123.92047 | CR207: 66.852432 | CS207: 111.72032 | CT207: 24.59 | CU207: 42.32 | CV207: 84.099998 | CW207: 35.23 | CX207: 14.077536 | CY207: 65.900002 | CZ207: 49.080002 | DA207: 4.1100001 | DB207: 8.1599998 | DC207: 161.61 | DD207: 95.099998 | DE207: 71.32 | DF207: 348.82999 | DG207: 368.41 | DH207: 21.629999 | DI207: 75.91301 | DJ207: 345.89545 | DK207: 346.54724 | DL207: 27.83 | DM207: 12.04 | DN207: 139.64742 | DO207: 32.84 | DP207: 99.959999 | DQ207: 272.29834 | DR207: 75.5 | DS207: 35.389999 | DT207: 211.15527 | DU207: 186.64999 | DV207: 4.7399998 | DW207: 2.1110001 | DX207: 7.4899998 | DY207: 95.040001 | DZ207: 34.779999 | EA207: 46.528378 | EB207: 122.86533 | EC207: 2.0999999 | ED207: 293.27405 | EE207: 140.46001 | EF207: 251.79814 | EG207: 9.54 | EH207: 20.027155 | EI207: 81.076202 | EJ207: 58.419167 | EK207: 0.44999999 | EL207: 24.201303 | EM207: 13.88 | EN207: 67.18 | EO207: 262.03101 | EP207: 207.44794 | EQ207: 79.940002 | ER207: 313.29999 | ES207: 4.77 | ET207: 13.52 | EU207: 23.478647 | EV207: 543.59998 | EW207: 1.3 | EX207: 10.69 | EY207: 98.078766 | EZ207: 80.475815 | FA207: 83.199997 | FB207: 646.01001 | FC207: 73.043411 | FD207: 6.0050001 | FE207: 21.944244 | FF207: 126.75182 | FG207: 61.82 | FH207: 188.67999 | FI207: 214.32022 | FJ207: 393.08002 | FK207: 94.849998 | FL207: 3.8900001 | FM207: 88.137222 | FN207: 89.513657 | FO207: 12.065168 | FP207: 68.949997 | FQ207: 5.1799998 | FR207: 1.55 | FS207: 163.88 | FT207: 13.59 | FU207: 202.58331 | FV207: 103.1 | FW207: 41.110001 | FX207: 4.5 | FY207: 9.3800001 | FZ207: 4.0300002 | GA207: 69.379997 | GB207: 358.67999 | GC207: 60.41 | GD207: 132.38 | GE207: 192.98 | GF207: 250.86 | GG207: 29.110001 | GH207: 16.9 | GI207: 16.73 | GJ207: 3.24 | GK207: 695.33002 | GL207: 7.8000002 | GM207: 9.8056498 | GN207: 51.68 | GO207: 181.17999 | GP207: 8.4499998 | GQ207: 11.21 | GR207: 189.17 | GS207: 14.11 | GT207: 5.1399999 | GU207: 18.26 | GV207: 67.620003 | GW207: 144.42999 | GX207: 59.630001 | GY207: 233.00966 | GZ207: 192.86929 | HA207: 2.9449999 | HB207: 14.88 | HC207: 104.88747 | HD207: 101.26471 | HE207: 5.8730001 | HF207: 10.26 | HG207: 86.561386 | HH207: 124.96 | HI207: 4.5300002 | HJ207: 17.280001 | HK207: 21.120001 | HL207: 6.27 | HM207: 741.44879 | HN207: 8.1400003 | HO207: 62.03204 | HP207: 48.040001 | HQ207: 9.71 | HR207: 2.0999999 | HS207: 19.219999 | HT207: 40.619999 | HU207: 9.4300003 | HV207: 98.339996 | HW207: 33.032745 | HX207: 9.1199999 | HY207: 191.32576 | HZ207: 140.92578 | IA207: 380.84 | IB207: 18.59 | IC207: 206.78 | ID207: 115.41 | IE207: 72.459999 | IF207: 52.73 | IG207: 139.05 | IH207: 0.80500001 | II207: 72.980003 | IJ207: 15.65 | IK207: 3.74 | IL207: 9.0299997 | IM207: 308.45792 | IN207: 15.74 | IO207: 8.21 | IP207: 43.59 | IQ207: 26.870001 | IR207: 87.01046 | IS207: 28.121767 | IT207: 113.96716 | IU207: 2.05 | IV207: 20.022659 | IW207: 18.16 | IX207: 57.68 | IY207: 175.59 | IZ207: 161.09 | JA207: 98.540001 | JB207: 13.53 | JC207: 79.940002 | JD207: 26.219999 | JE207: 147.17798 | JF207: 71.787659 | JG207: 91.129997 | JH207: 0.164 | JI207: 76.029999
A208: 2026-07-20 | B208: 43.395786 | C208: 16.85 | D208: 15.14 | E208: 103.02 | F208: 52.040001 | G208: 326.30856 | H208: 37.119179 | I208: 144.94 | J208: 101.66 | K208: 25.09 | L208: 5.3099999 | M208: 85.129692 | N208: 17.540001 | O208: 123.45823 | P208: 75.32 | Q208: 15.837341 | R208: 111.99115 | S208: 1.12 | T208: 123.13 | U208: 5.2800002 | V208: 503.57001 | W208: 366.11008 | X208: 4.23 | Y208: 62.445084 | Z208: 32.509998 | AA208: 249.99001 | AB208: 169.35001 | AC208: 6.2399998 | AD208: 25.9 | AE208: 75.254997 | AF208: 8.3400002 | AG208: 4.7550001 | AH208: 17.209999 | AI208: 15.914578 | AJ208: 36.900002 | AK208: 8.2700005 | AL208: 39.48 | AM208: 60.113297 | AN208: 20.674723 | AO208: 84.24601 | AP208: 26.33 | AQ208: 16.969999 | AR208: 11.169783 | AS208: 23.549999 | AT208: 12.543198 | AU208: 60.16 | AV208: 46.774254 | AX208: 11.37 | AY208: 128.06886 | AZ208: 225.75 | BA208: 11.790117 | BB208: 77.059532 | BC208: 84.849998 | BD208: 25.904327 | BE208: 36.700001 | BF208: 122.93658 | BG208: 14.42 | BH208: 16.695637 | BI208: 23.780001 | BJ208: 243.96475 | BK208: 285.39999 | BL208: 160.42999 | BM208: 11.74 | BN208: 114.91354 | BO208: 934.31451 | BP208: 5.6607785 | BQ208: 212.07001 | BR208: 6.21 | BS208: 8.6000004 | BT208: 110.7 | BU208: 36.996151 | BV208: 49.973194 | BW208: 64.139999 | BX208: 106.94789 | BY208: 709.02002 | BZ208: 84.540001 | CA208: 189.02 | CB208: 12.59 | CC208: 263.20001 | CD208: 381.25 | CE208: 124.75 | CF208: 18.428232 | CG208: 89.853035 | CH208: 96.410004 | CI208: 9.7399998 | CJ208: 175.04968 | CK208: 32.990002 | CL208: 52.299999 | CM208: 2.8 | CN208: 30.021608 | CO208: 53.189999 | CP208: 11.9 | CQ208: 124.75314 | CR208: 66.772606 | CS208: 113.84387 | CT208: 25.1 | CU208: 41.07 | CV208: 84.029999 | CW208: 35.48 | CX208: 13.840107 | CY208: 66.720001 | CZ208: 49.490002 | DA208: 4.23 | DB208: 8.0299997 | DC208: 160.36 | DD208: 98.279999 | DE208: 70.739998 | DF208: 341.29999 | DG208: 367.60001 | DH208: 23.66 | DI208: 75.64357 | DJ208: 351.14203 | DK208: 351.76389 | DL208: 27.950001 | DM208: 12.15 | DN208: 139.88637 | DO208: 32.700001 | DP208: 99.279999 | DQ208: 271.84857 | DR208: 75.349998 | DS208: 35.07 | DT208: 211.48293 | DU208: 184.67999 | DV208: 4.8400002 | DW208: 1.97 | DX208: 7.5 | DY208: 97.059998 | DZ208: 34.240002 | EA208: 46.259254 | EB208: 123.27217 | EC208: 2.3199999 | ED208: 291.54855 | EE208: 139.37 | EF208: 247.59886 | EG208: 10.04 | EH208: 20.116873 | EI208: 81.632889 | EJ208: 57.962299 | EK208: 0.47299999 | EL208: 23.76417 | EM208: 13.69 | EN208: 67.449997 | EO208: 264.37592 | EP208: 203.45264 | EQ208: 77.080002 | ER208: 306.76001 | ES208: 4.7600002 | ET208: 13.83 | EU208: 23.111794 | EV208: 547.44 | EW208: 1.28 | EX208: 11.67 | EY208: 98.178391 | EZ208: 80.028511 | FA208: 83.290001 | FB208: 645.84998 | FC208: 73.486336 | FD208: 6 | FE208: 22.221895 | FF208: 123.67001 | FG208: 59.490002 | FH208: 194.94 | FI208: 209.78519 | FJ208: 401.53412 | FK208: 97.82 | FL208: 4.29 | FM208: 87.343193 | FN208: 89.014702 | FO208: 11.89691 | FP208: 67.599998 | FQ208: 5.2199998 | FR208: 1.53 | FS208: 161.16 | FT208: 13.99 | FU208: 203.0528 | FV208: 100.23 | FW208: 41.509998 | FX208: 4.4450002 | FY208: 9.3000002 | FZ208: 4.0999999 | GA208: 69.93 | GB208: 348.66 | GC208: 53.23 | GD208: 134.85001 | GE208: 192.72 | GF208: 250.14 | GG208: 29.16 | GH208: 17.02 | GI208: 16.719999 | GJ208: 3.04 | GK208: 696.06 | GL208: 7.9200001 | GM208: 9.7861557 | GN208: 53.25 | GO208: 181.64 | GP208: 8.6000004 | GQ208: 11.51 | GR208: 187.36 | GS208: 14.25 | GT208: 5.02 | GU208: 19.9 | GV208: 65.739998 | GW208: 144.13 | GX208: 60.07 | GY208: 235.32518 | GZ208: 193.79622 | HA208: 2.8900001 | HB208: 14.89 | HC208: 104.21136 | HD208: 102.24187 | HE208: 5.467 | HF208: 10.19 | HG208: 85.451111 | HH208: 125.88 | HI208: 4.5599999 | HJ208: 17.01 | HK208: 21.15 | HL208: 6.3099999 | HM208: 740.25183 | HN208: 8.0799999 | HO208: 61.853184 | HP208: 47.419998 | HQ208: 9.6499996 | HR208: 2.0999999 | HS208: 19.190001 | HT208: 40.040001 | HU208: 9.6499996 | HV208: 97.379997 | HW208: 32.023579 | HX208: 9.1700001 | HY208: 194.51735 | HZ208: 140.58705 | IA208: 369.57001 | IB208: 18.639999 | IC208: 205.24001 | ID208: 117.52 | IE208: 72.169998 | IF208: 51.5 | IG208: 138.47 | IH208: 0.85500002 | II208: 74.830002 | IJ208: 15.23 | IK208: 3.8599999 | IL208: 8.8699999 | IM208: 312.10382 | IN208: 15.4 | IO208: 8.0900002 | IP208: 43.5 | IQ208: 25.860001 | IR208: 85.837196 | IS208: 27.85375 | IT208: 111.93203 | IU208: 1.87 | IV208: 20.2124 | IW208: 18.860001 | IX208: 57.939999 | IY208: 175.71001 | IZ208: 159.25 | JA208: 100.12 | JB208: 13.19 | JC208: 79.290001 | JD208: 26.33 | JE208: 146.63074 | JF208: 71.410194 | JG208: 90.910004 | JH208: 0.16500001 | JI208: 76.199997
A209: 2026-07-21 | B209: 44.264099 | C209: 18.030001 | D209: 15.28 | E209: 119.26 | F209: 55.639999 | G209: 327.45758 | H209: 36.767151 | I209: 144.10001 | J209: 99.669998 | K209: 25.43 | L209: 5.2800002 | M209: 85.656349 | N209: 17.360001 | O209: 122.97068 | P209: 74.720001 | Q209: 16.856527 | R209: 111.45277 | S209: 1.15 | T209: 124.91 | U209: 5.4400001 | V209: 544.42999 | W209: 340.57077 | X209: 4.29 | Y209: 66.60743 | Z209: 34.549999 | AA209: 247.55 | AB209: 174.58 | AC209: 6 | AD209: 27.07 | AE209: 78.904999 | AF209: 9.1800003 | AG209: 4.4200001 | AH209: 17.200001 | AI209: 15.943692 | AJ209: 40.009998 | AK209: 8.3000002 | AL209: 40.259998 | AM209: 60.909237 | AN209: 21.688093 | AO209: 84.335083 | AP209: 27.290001 | AQ209: 16.57 | AR209: 11.329494 | AS209: 24.82 | AT209: 13.062089 | AU209: 60.93 | AV209: 46.326321 | AX209: 12.48 | AY209: 132.16801 | AZ209: 227.09 | BA209: 11.730472 | BB209: 75.107903 | BC209: 88.68 | BD209: 26.023703 | BE209: 36.110001 | BF209: 122.3297 | BG209: 15.38 | BH209: 18.157375 | BI209: 23.809999 | BJ209: 236.27087 | BK209: 317.22 | BL209: 175.85001 | BM209: 11.42 | BN209: 116.72149 | BO209: 927.74493 | BP209: 6.0872755 | BQ209: 223.87 | BR209: 6.3499999 | BS209: 9.21 | BT209: 112.18 | BU209: 36.547413 | BV209: 49.753792 | BW209: 65.580002 | BX209: 109.91949 | BY209: 722.09003 | BZ209: 84.629997 | CA209: 188.03999 | CB209: 12.81 | CC209: 254.78999 | CD209: 404.14999 | CE209: 123.2 | CF209: 18.388622 | CG209: 91.125145 | CH209: 96.139999 | CI209: 9.8199997 | CJ209: 178.08884 | CK209: 32.990002 | CL209: 50.740002 | CM209: 2.8399999 | CN209: 30.120459 | CO209: 51.610001 | CP209: 11.76 | CQ209: 124.81263 | CR209: 67.660774 | CS209: 112.70733 | CT209: 26.549999 | CU209: 43.200001 | CV209: 81.690002 | CW209: 35.619999 | CX209: 14.117107 | CY209: 79.849998 | CZ209: 51.389999 | DA209: 4.1999998 | DB209: 8.4700003 | DC209: 158.10001 | DD209: 103.66 | DE209: 74.190002 | DF209: 340.70001 | DG209: 374.81 | DH209: 25.41 | DI209: 79.355888 | DJ209: 345.96539 | DK209: 346.927 | DL209: 26.049999 | DM209: 12.73 | DN209: 141.35991 | DO209: 32.73 | DP209: 106.36 | DQ209: 278.86517 | DR209: 76.82 | DS209: 34.939999 | DT209: 209.00073 | DU209: 192.53 | DV209: 5 | DW209: 1.8099999 | DX209: 7.5999999 | DY209: 105.45 | DZ209: 35.509998 | EA209: 47.086559 | EB209: 124.59191 | EC209: 2.26 | ED209: 295.76755 | EE209: 141.71001 | EF209: 249.38008 | EG209: 10.05 | EH209: 19.847717 | EI209: 81.48378 | EJ209: 57.38625 | EK209: 0.45500001 | EL209: 24.4 | EM209: 13.52 | EN209: 68.620003 | EO209: 262.02103 | EP209: 202.25999 | EQ209: 80.889999 | ER209: 322 | ES209: 4.75 | ET209: 14.64 | EU209: 23.597626 | EV209: 538.29999 | EW209: 1.33 | EX209: 12.25 | EY209: 98.696426 | EZ209: 82.88134 | FA209: 82.349998 | FB209: 643.81 | FC209: 71.842583 | FD209: 6.0300002 | FE209: 21.785589 | FF209: 125.51909 | FG209: 59.66 | FH209: 207.96001 | FI209: 215.21529 | FJ209: 397.00262 | FK209: 101.95 | FL209: 3.98 | FM209: 87.273712 | FN209: 92.297867 | FO209: 12.688717 | FP209: 68.669998 | FQ209: 5.6300001 | FR209: 1.49 | FS209: 165.75999 | FT209: 14.39 | FU209: 207.0583 | FV209: 105.67 | FW209: 44.130001 | FX209: 4.48 | FY209: 9.46 | FZ209: 4.02 | GA209: 74.32 | GB209: 342.14999 | GC209: 58.099998 | GD209: 132.66 | GE209: 188.03999 | GF209: 250.38 | GG209: 28.549999 | GH209: 18.620001 | GI209: 17.799999 | GJ209: 3.02 | GK209: 708.96997 | GL209: 8.2200003 | GM209: 9.7959023 | GN209: 52.5 | GO209: 185.84 | GP209: 9.4200001 | GQ209: 11.92 | GR209: 194.00999 | GS209: 15.28 | GT209: 5.2399998 | GU209: 21.49 | GV209: 69.120003 | GW209: 144.27 | GX209: 59.060001 | GY209: 235.35512 | GZ209: 193.02876 | HA209: 3.0799999 | HB209: 14.89 | HC209: 103.85341 | HD209: 99.669365 | HE209: 5.1729999 | HF209: 10.48 | HG209: 86.442429 | HH209: 137.84 | HI209: 4.5599999 | HJ209: 17.639999 | HK209: 21.02 | HL209: 6.5549998 | HM209: 746.42651 | HN209: 8.3699999 | HO209: 63.293941 | HP209: 47.869999 | HQ209: 9.6899996 | HR209: 2.0999999 | HS209: 19.360001 | HT209: 40.07 | HU209: 9.71 | HV209: 98.610001 | HW209: 32.423248 | HX209: 8.9399996 | HY209: 189.67529 | HZ209: 141.62314 | IA209: 378.92999 | IB209: 18.25 | IC209: 196.22 | ID209: 117.7 | IE209: 71.550003 | IF209: 52.330002 | IG209: 141.89 | IH209: 0.86199999 | II209: 73.739998 | IJ209: 15.8 | IK209: 3.9200001 | IL209: 8.54 | IM209: 313.58807 | IN209: 15.27 | IO209: 7.9400001 | IP209: 43.779999 | IQ209: 25.83 | IR209: 87.239143 | IS209: 27.739597 | IT209: 110.12636 | IU209: 1.88 | IV209: 20.661787 | IW209: 19.870001 | IX209: 58.5 | IY209: 180.78 | IZ209: 160.25 | JA209: 104.85 | JB209: 13.33 | JC209: 80.379997 | JD209: 25.790001 | JE209: 146.43173 | JF209: 68.589157 | JG209: 89.769997 | JH209: 0.16 | JI209: 75.349998
A210: 2026-07-22 | B210: 46.080574 | C210: 17.290001 | D210: 14.79 | E210: 110.52 | F210: 55.490002 | G210: 325.60919 | H210: 36.512913 | I210: 140.05 | J210: 100.57 | K210: 24.959999 | L210: 5.1799998 | M210: 86.769287 | N210: 17.82 | O210: 122.96073 | P210: 73.915001 | Q210: 17.296173 | R210: 116.92622 | S210: 1.13 | T210: 124.3 | U210: 5.1500001 | V210: 552.33002 | W210: 346.69064 | X210: 3.98 | Y210: 66.846985 | Z210: 33.400002 | AA210: 244.85001 | AB210: 174.87 | AC210: 5.7800002 | AD210: 27.23 | AE210: 78.754997 | AF210: 8.4899998 | AG210: 4.4499998 | AH210: 18.08 | AI210: 15.895171 | AJ210: 40.490002 | AK210: 8.0600004 | AL210: 39.369999 | AM210: 61.307205 | AN210: 21.191343 | AO210: 86.205452 | AP210: 26.639999 | AQ210: 16.059999 | AR210: 11.489205 | AS210: 24.709999 | AT210: 12.856309 | AU210: 60.759998 | AV210: 46.326321 | AX210: 12.26 | AY210: 131.58101 | AZ210: 220.53999 | BA210: 12.485993 | BB210: 76.389275 | BC210: 90.370003 | BD210: 25.964016 | BE210: 34.27 | BF210: 126.6972 | BG210: 15.325 | BH210: 18.515352 | BI210: 23.52 | BJ210: 248.07545 | BK210: 312.19 | BL210: 166.12 | BM210: 11.26 | BN210: 118.00294 | BO210: 925.83801 | BP210: 5.5211973 | BQ210: 228.27 | BR210: 6.52 | BS210: 9.5600004 | BT210: 112.21 | BU210: 36.896435 | BV210: 49.793686 | BW210: 62.75 | BX210: 107.415 | BY210: 732.47998 | BZ210: 83.519997 | CA210: 177.73 | CB210: 12.53 | CC210: 245.77 | CD210: 441.79999 | CE210: 120.24 | CF210: 17.992529 | CG210: 90.300255 | CH210: 95.870003 | CI210: 9.2299995 | CJ210: 177.19498 | CK210: 29.99 | CL210: 47.889999 | CM210: 2.8299999 | CN210: 30.891512 | CO210: 51.220001 | CP210: 11.03 | CQ210: 126.83484 | CR210: 67.650795 | CS210: 110.61369 | CT210: 27.27 | CU210: 43.580002 | CV210: 80.480003 | CW210: 36.619999 | CX210: 14.2655 | CY210: 72.389999 | CZ210: 51.59 | DA210: 4.21 | DB210: 8.6099997 | DC210: 155.05 | DD210: 106.09 | DE210: 76.68 | DF210: 341.19 | DG210: 379.12 | DH210: 24.790001 | DI210: 81.960503 | DJ210: 341.68817 | DK210: 341.87024 | DL210: 27.92 | DM210: 12.68 | DN210: 140.22488 | DO210: 31.68 | DP210: 104.48 | DQ210: 280.56436 | DR210: 77.690002 | DS210: 33.099998 | DT210: 204.30443 | DU210: 190.87 | DV210: 4.9899998 | DW210: 1.8 | DX210: 7.4400001 | DY210: 102.62 | DZ210: 34.68 | EA210: 46.70779 | EB210: 123.55001 | EC210: 2.25 | ED210: 293.02469 | EE210: 142.49001 | EF210: 254.37544 | EG210: 9.7600002 | EH210: 19.169844 | EI210: 81.71241 | EJ210: 57.147888 | EK210: 0.46000001 | EL210: 24.74 | EM210: 13.85 | EN210: 63.419998 | EO210: 266.82059 | EP210: 204.35001 | EQ210: 87.040001 | ER210: 319.29001 | ES210: 4.6100001 | ET210: 14.09 | EU210: 24.123119 | EV210: 531.97998 | EW210: 1.3 | EX210: 12.41 | EY210: 89.849915 | EZ210: 84.511528 | FA210: 81.889999 | FB210: 627.16998 | FC210: 71.035477 | FD210: 5.9299998 | FE210: 22.588791 | FF210: 126.72199 | FG210: 58.07 | FH210: 210.99001 | FI210: 217.30379 | FJ210: 389.60657 | FK210: 100.01 | FL210: 3.96 | FM210: 88.742668 | FN210: 95.551094 | FO210: 13.490422 | FP210: 68.529999 | FQ210: 6.21 | FR210: 1.48 | FS210: 166.53999 | FT210: 14.51 | FU210: 211.82298 | FV210: 104.96 | FW210: 44.5 | FX210: 4.3800001 | FY210: 9.2399998 | FZ210: 4.02 | GA210: 74.580002 | GB210: 335.28 | GC210: 59.200001 | GD210: 124.57 | GE210: 194.3 | GF210: 252.50999 | GG210: 28.43 | GH210: 18.5 | GI210: 17.35 | GJ210: 2.8499999 | GK210: 705.34998 | GL210: 7.9099998 | GM210: 9.7959023 | GN210: 49.639999 | GO210: 170.38 | GP210: 8.9899998 | GQ210: 11.37 | GR210: 201.25999 | GS210: 15.23 | GT210: 5.3000002 | GU210: 23.379999 | GV210: 69.75 | GW210: 143.08 | GX210: 58.68 | GY210: 237.7505 | GZ210: 194.23476 | HA210: 2.98 | HB210: 14.65 | HC210: 103.3861 | HD210: 100.50693 | HE210: 4.6339998 | HF210: 10.16 | HG210: 87.007477 | HH210: 136.92999 | HI210: 4.4699998 | HJ210: 17.07 | HK210: 20.92 | HL210: 6.46 | HM210: 745.55859 | HN210: 8.21 | HO210: 64.307442 | HP210: 46.939999 | HQ210: 10.24 | HR210: 2.1700001 | HS210: 19.33 | HT210: 40.139999 | HU210: 8.9200001 | HV210: 97.860001 | HW210: 32.703018 | HX210: 8.7799997 | HY210: 189.84431 | HZ210: 143.18719 | IA210: 374.01001 | IB210: 17.58 | IC210: 183.38 | ID210: 117.26 | IE210: 70.330002 | IF210: 52.650002 | IG210: 141.27 | IH210: 0.86199999 | II210: 73.709999 | IJ210: 15.82 | IK210: 3.8900001 | IL210: 8.0500002 | IM210: 309.72305 | IN210: 15.51 | IO210: 7.79 | IP210: 44.290001 | IQ210: 25.85 | IR210: 85.926682 | IS210: 27.178749 | IT210: 109.06889 | IU210: 1.78 | IV210: 19.902822 | IW210: 19.49 | IX210: 59.200001 | IY210: 180.27 | IZ210: 159.42999 | JA210: 98.440002 | JB210: 12.85 | JC210: 77.459999 | JD210: 24.809999 | JE210: 146.82974 | JF210: 69.602348 | JG210: 85.809998 | JH210: 0.16 | JI210: 74.190002
A211: 2026-07-23 | B211: 45.18232 | C211: 19.1 | D211: 13.56 | E211: 112.02 | F211: 53.419998 | G211: 321.38284 | H211: 36.327122 | I211: 137.57001 | J211: 100.75 | K211: 24.83 | L211: 5.1100001 | M211: 85.805405 | N211: 17.08 | O211: 123.71692 | P211: 71.209999 | Q211: 16.436863 | R211: 116.91624 | S211: 1.1 | T211: 117.37 | U211: 4.6900001 | V211: 539.69 | W211: 347.76059 | X211: 3.5 | Y211: 65.209999 | Z211: 33 | AA211: 233.66 | AB211: 176.61 | AC211: 5.4200001 | AD211: 26.85 | AE211: 78.714996 | AF211: 8.0299997 | AG211: 4.3699999 | AH211: 18.35 | AI211: 15.652571 | AJ211: 39.459999 | AK211: 8.21 | AL211: 39.73 | AM211: 60.968929 | AN211: 21.241018 | AO211: 83.553284 | AP211: 25.91 | AQ211: 16.08 | AR211: 11.56906 | AS211: 24.41 | AT211: 12.406787 | AU211: 61.509998 | AV211: 46.326321 | AX211: 12.17 | AY211: 131.21289 | AZ211: 225.98 | BA211: 11.611178 | BB211: 73.501266 | BC211: 89.330002 | BD211: 25.13834 | BE211: 34.549999 | BF211: 126.06049 | BG211: 15.61 | BH211: 18.425858 | BI211: 21.92 | BJ211: 253.13171 | BK211: 313.22 | BL211: 161.16 | BM211: 10.78 | BN211: 119.40359 | BO211: 924.58997 | BP211: 5.4203892 | BQ211: 236.5 | BR211: 6.1100001 | BS211: 8.8100004 | BT211: 112.76 | BU211: 37.66428 | BV211: 52.665825 | BW211: 60.189999 | BX211: 106.89 | BY211: 750.03003 | BZ211: 81.970001 | CA211: 169.77 | CB211: 12.43 | CC211: 244.39 | CD211: 439.34 | CE211: 115.16 | CF211: 18.259893 | CG211: 88.541161 | CH211: 92.830002 | CI211: 8.8900003 | CJ211: 178.11864 | CK211: 29.17 | CL211: 47.040001 | CM211: 2.72 | CN211: 30.545527 | CO211: 50.849998 | CP211: 10.41 | CQ211: 128.13342 | CR211: 67.071983 | CS211: 108.98863 | CT211: 26.59 | CU211: 44.139999 | CV211: 80.910004 | CW211: 36.169998 | CX211: 13.998392 | CY211: 73.239998 | CZ211: 53.259998 | DA211: 3.8900001 | DB211: 8.4200001 | DC211: 151.53999 | DD211: 98.959999 | DE211: 75.019997 | DF211: 349 | DG211: 371.51999 | DH211: 24.32 | DI211: 80.503517 | DJ211: 318.13345 | DK211: 317.48593 | DL211: 25.42 | DM211: 12.57 | DN211: 141.55902 | DO211: 32.740002 | DP211: 101.58 | DQ211: 286.95126 | DR211: 76.150002 | DS211: 32.209999 | DT211: 205.17815 | DU211: 196.86 | DV211: 4.96 | DW211: 1.8099999 | DX211: 7.0799999 | DY211: 100.23 | DZ211: 34.07 | EA211: 47.485256 | EB211: 123.58971 | EC211: 2.23 | ED211: 291.3291 | EE211: 143.28999 | EF211: 257.99756 | EG211: 9.6899996 | EH211: 18.820938 | EI211: 80.688522 | EJ211: 55.380016 | EK211: 0.47999999 | EL211: 24.1 | EM211: 13.4 | EN211: 60.709999 | EO211: 271.40063 | EP211: 201.92 | EQ211: 89.029999 | ER211: 319.78 | ES211: 4.75 | ET211: 13.71 | EU211: 23.131622 | EV211: 530.28998 | EW211: 1.28 | EX211: 12.77 | EY211: 90.447655 | EZ211: 80.86348 | FA211: 82.010002 | FB211: 606.09998 | FC211: 70.946892 | FD211: 5.8899999 | FE211: 22.092987 | FF211: 129.71432 | FG211: 57.02 | FH211: 209.32001 | FI211: 214.00197 | FJ211: 380.86301 | FK211: 93.629997 | FL211: 3.71 | FM211: 89.119827 | FN211: 94.523239 | FO211: 13.08462 | FP211: 68.889999 | FQ211: 5.9200001 | FR211: 1.47 | FS211: 164.64 | FT211: 14.19 | FU211: 208.52666 | FV211: 104.49 | FW211: 44 | FX211: 3.845 | FY211: 8.8599997 | FZ211: 4.1599998 | GA211: 75.190002 | GB211: 325.63 | GC211: 58.41 | GD211: 123.37 | GE211: 191.12 | GF211: 249.25999 | GG211: 27.92 | GH211: 17.84 | GI211: 17.1 | GJ211: 2.8399999 | GK211: 691.96002 | GL211: 7.8600001 | GM211: 9.8543854 | GN211: 47.549999 | GO211: 168.78 | GP211: 9.2799997 | GQ211: 11.37 | GR211: 199.64 | GS211: 14.85 | GT211: 5.3200002 | GU211: 23.860001 | GV211: 69.989998 | GW211: 141.67 | GX211: 57.540001 | GY211: 231.94173 | GZ211: 208.46748 | HA211: 3.01 | HB211: 14.49 | HC211: 102.6205 | HD211: 101.31457 | HE211: 4.263 | HF211: 10.02 | HG211: 87.185913 | HH211: 138.67999 | HI211: 4.4099998 | HJ211: 16.65 | HK211: 20.690001 | HL211: 6.2199998 | HM211: 736.3515 | HN211: 8 | HO211: 65.986671 | HP211: 47.189999 | HQ211: 9.6700001 | HR211: 2.05 | HS211: 19.1 | HT211: 42.389999 | HU211: 8.6599998 | HV211: 96.25 | HW211: 32.623085 | HX211: 8.7600002 | HY211: 169.44206 | HZ211: 138.60458 | IA211: 319.69 | IB211: 16.790001 | IC211: 185.06 | ID211: 115.35 | IE211: 68.910004 | IF211: 51.549999 | IG211: 136.13 | IH211: 0.80599999 | II211: 69.610001 | IJ211: 15.14 | IK211: 3.8499999 | IL211: 8.4399996 | IM211: 304.08484 | IN211: 15.25 | IO211: 7.5999999 | IP211: 43.82 | IQ211: 25.950001 | IR211: 85.697998 | IS211: 26.404484 | IT211: 108.14111 | IU211: 1.8 | IV211: 19.673138 | IW211: 20.049999 | IX211: 59.380001 | IY211: 178.45 | IZ211: 161.44 | JA211: 86.510002 | JB211: 12.76 | JC211: 76.489998 | JD211: 24.5 | JE211: 146.63074 | JF211: 68.698425 | JG211: 84.110001 | JH211: 0.185 | JI211: 74.57
A212: 2026-07-24 | B212: 44.154316 | C212: 18.01 | D212: 14.48 | E212: 100.15 | F212: 55.799999 | G212: 332.73303 | H212: 36.376015 | I212: 141.10001 | J212: 103.06 | K212: 24.84 | L212: 4.77 | M212: 85.378113 | N212: 17 | O212: 124.9706 | P212: 70.230003 | Q212: 16.296972 | R212: 120.84436 | S212: 1.11 | T212: 115.37 | U212: 4.0799999 | V212: 521.95001 | W212: 358.2803 | X212: 2.9200001 | Y212: 64.840675 | Z212: 30.52 | AA212: 232.11 | AB212: 173.99001 | AC212: 5.5300002 | AD212: 26.780001 | AE212: 76.334999 | AF212: 8.4499998 | AG212: 4.3899999 | AH212: 16.65 | AI212: 15.788427 | AJ212: 36.84 | AK212: 8.2600002 | AL212: 39.490002 | AM212: 61.735023 | AN212: 21.141668 | AO212: 84.5429 | AP212: 25.1 | AQ212: 15.89 | AR212: 11.628952 | AS212: 23.290001 | AT212: 12.167043 | AU212: 62.09 | AV212: 45.987881 | AX212: 11.56 | AY212: 131.52132 | AZ212: 228.03 | BA212: 11.710588 | BB212: 73.826538 | BC212: 87.860001 | BD212: 26.192816 | BE212: 36.369999 | BF212: 124.42889 | BG212: 14.52 | BH212: 18.555126 | BI212: 22.299999 | BJ212: 254.11708 | BK212: 282.39001 | BL212: 158.28999 | BM212: 11.07 | BN212: 119.4632 | BO212: 935.03003 | BP212: 5.1257186 | BQ212: 213.14999 | BR212: 5.8099999 | BS212: 8.4449997 | BT212: 114.17 | BU212: 38.850945 | BV212: 53.084675 | BW212: 60.459999 | BX212: 107.74 | BY212: 750.19 | BZ212: 85.059998 | CA212: 172.91 | CB212: 12.22 | CC212: 246.86 | CD212: 437.5 | CE212: 117.23 | CF212: 18.576767 | CG212: 87.756035 | CH212: 94.849998 | CI212: 8.5600004 | CJ212: 197.72421 | CK212: 28.82 | CL212: 50.439999 | CM212: 2.6400001 | CN212: 29.497686 | CO212: 52.099998 | CP212: 10.7 | CQ212: 129.38245 | CR212: 67.042046 | CS212: 109.05842 | CT212: 25.709999 | CU212: 42.59 | CV212: 80.620003 | CW212: 35.73 | CX212: 14.216036 | CY212: 72.459999 | CZ212: 52.189999 | DA212: 3.8199999 | DB212: 8.5500002 | DC212: 152.37 | DD212: 99.360001 | DE212: 75.230003 | DF212: 353.73001 | DG212: 371.89999 | DH212: 22.68 | DI212: 82.469452 | DJ212: 318.88297 | DK212: 319.53461 | DL212: 25.809999 | DM212: 12.01 | DN212: 139.91624 | DO212: 28.09 | DP212: 94.910004 | DQ212: 289.12024 | DR212: 76.230003 | DS212: 33.459999 | DT212: 212.66446 | DU212: 194.09 | DV212: 4.7399998 | DW212: 1.75 | DX212: 6.6599998 | DY212: 92.32 | DZ212: 32.84 | EA212: 45.631298 | EB212: 127.32071 | EC212: 1.97 | ED212: 290.41153 | EE212: 143.37 | EF212: 262.1073 | EG212: 9.4700003 | EH212: 19.847717 | EI212: 81.762115 | EJ212: 56.482452 | EK212: 0.45500001 | EL212: 24.540001 | EM212: 13.34 | EN212: 60.139999 | EO212: 269.13556 | EP212: 207.64 | EQ212: 86.220001 | ER212: 305.20999 | ES212: 4.52 | ET212: 12.92 | EU212: 23.181198 | EV212: 539.65997 | EW212: 1.24 | EX212: 12.12 | EY212: 90.686745 | EZ212: 78.388374 | FA212: 83.209999 | FB212: 595.19 | FC212: 71.842583 | FD212: 5.8800001 | FE212: 22.112818 | FF212: 130.30087 | FG212: 54.07 | FH212: 194.23 | FI212: 213.3058 | FJ212: 380.98282 | FK212: 91.669998 | FL212: 3.21 | FM212: 89.109901 | FN212: 92.996414 | FO212: 12.738205 | FP212: 70.089996 | FQ212: 5.9299998 | FR212: 1.47 | FS212: 167.74001 | FT212: 14.09 | FU212: 206.60881 | FV212: 100.03 | FW212: 40.25 | FX212: 3.835 | FY212: 9.0200005 | FZ212: 4.0300002 | GA212: 74.559998 | GB212: 323.79001 | GC212: 53.849998 | GD212: 122.92 | GE212: 193 | GF212: 250.99001 | GG212: 28.68 | GH212: 17.84 | GI212: 16.209999 | GJ212: 2.99 | GK212: 684.22998 | GL212: 7.4299998 | GM212: 9.8543854 | GN212: 47.549999 | GO212: 168.73 | GP212: 8.6899996 | GQ212: 11.13 | GR212: 200.96001 | GS212: 14.15 | GT212: 5.3499999 | GU212: 22.530001 | GV212: 63.91 | GW212: 141.97 | GX212: 57.950001 | GY212: 238.42918 | GZ212: 212.08545 | HA212: 2.96 | HB212: 14.64 | HC212: 102.66027 | HD212: 101.67352 | HE212: 4.4099998 | HF212: 9.6300001 | HG212: 87.612175 | HH212: 125.92 | HI212: 4.3499999 | HJ212: 16.459999 | HK212: 20.98 | HL212: 6.1599998 | HM212: 737.09961 | HN212: 8.0299997 | HO212: 65.390488 | HP212: 46.200001 | HQ212: 9.5200005 | HR212: 1.98 | HS212: 19.110001 | HT212: 42.75 | HU212: 8.7700005 | HV212: 94.540001 | HW212: 32.952812 | HX212: 8.8599997 | HY212: 179.05656 | HZ212: 142.06148 | IA212: 313.03 | IB212: 17.290001 | IC212: 191.46001 | ID212: 118.27 | IE212: 65.940002 | IF212: 51.740002 | IG212: 136.27 | IH212: 0.80000001 | II212: 69.970001 | IJ212: 14.15 | IK212: 3.6900001 | IL212: 8.3400002 | IM212: 301.33545 | IN212: 15.15 | IO212: 7.6700001 | IP212: 46.380001 | IQ212: 25.77 | IR212: 85.817307 | IS212: 26.354849 | IT212: 109.20856 | IU212: 1.7 | IV212: 19.423477 | IW212: 18.459999 | IX212: 59.619999 | IY212: 175.88 | IZ212: 162.57001 | JA212: 86.309998 | JB212: 12.33 | JC212: 77.150002 | JD212: 25.1 | JE212: 148.17296 | JF212: 68.827553 | JG212: 87.989998 | JH212: 0.15000001 | JI212: 75.349998
A213: 2026-07-27 | B213: 43.994625 | C213: 18.68 | D213: 14.95 | E213: 97.82 | F213: 57.73 | G213: 336.61969 | H213: 37.060509 | I213: 146.86 | J213: 104.49 | K213: 25.389999 | L213: 4.9499998 | M213: 82.665337 | N213: 17.77 | O213: 125.9258 | P213: 73.050003 | Q213: 16.207045 | R213: 119.87728 | S213: 1.1799999 | T213: 112.85 | U213: 4.0799999 | V213: 494.95001 | W213: 363.79013 | X213: 2.79 | Y213: 60.59848 | Z213: 30.530001 | AA213: 231.39 | AB213: 170.75999 | AC213: 5.9299998 | AD213: 27.870001 | AE213: 74.639999 | AF213: 8.5900002 | AG213: 4.21 | AH213: 18.18 | AI213: 15.730203 | AJ213: 36.549999 | AK213: 8.6700001 | AL213: 41.139999 | AM213: 61.814617 | AN213: 20.654854 | AO213: 87.531532 | AP213: 25.07 | AQ213: 16.389999 | AR213: 11.7687 | AS213: 23.559999 | AT213: 12.426765 | AU213: 62.560001 | AV213: 46.535358 | AX213: 11.35 | AY213: 132.42671 | AZ213: 229.35001 | BA213: 12.436288 | BB213: 73.067574 | BC213: 89.349998 | BD213: 26.978701 | BE213: 36.349998 | BF213: 119.16601 | BG213: 14.025 | BH213: 18.80372 | BI213: 22.799999 | BJ213: 254.16685 | BK213: 271.31 | BL213: 167.49001 | BM213: 11.8 | BN213: 114.81421 | BO213: 951.58002 | BP213: 5.4514074 | BQ213: 208.14 | BR213: 6.04 | BS213: 8.29 | BT213: 114.57 | BU213: 39.888035 | BV213: 51.658577 | BW213: 64.040001 | BX213: 107.07 | BY213: 743.83002 | BZ213: 86.669998 | CA213: 184.37 | CB213: 11.94 | CC213: 251.86 | CD213: 426.91 | CE213: 123.22 | CF213: 18.725302 | CG213: 90.220749 | CH213: 96.650002 | CI213: 9.5600004 | CJ213: 194.4268 | CK213: 29.440001 | CL213: 52.91 | CM213: 2.48 | CN213: 28.420191 | CO213: 53.099998 | CP213: 11.295 | CQ213: 127.70718 | CR213: 66.872398 | CS213: 112.86684 | CT213: 26.02 | CU213: 42.310001 | CV213: 83.839996 | CW213: 35.869999 | CX213: 14.522715 | CY213: 70.639999 | CZ213: 51.700001 | DA213: 3.8299999 | DB213: 8.5600004 | DC213: 152.38 | DD213: 104.27 | DE213: 75.730003 | DF213: 361.60999 | DG213: 374.63 | DH213: 22.700001 | DI213: 86.860374 | DJ213: 326.35812 | DK213: 326.35022 | DL213: 27.530001 | DM213: 12.13 | DN213: 139.52794 | DO213: 30.24 | DP213: 95.650002 | DQ213: 287.80087 | DR213: 76.779999 | DS213: 34.880001 | DT213: 214.73956 | DU213: 189.47 | DV213: 4.6999998 | DW213: 1.72 | DX213: 7.02 | DY213: 91.669998 | DZ213: 35.919998 | EA213: 45.810715 | EB213: 126.01089 | EC213: 2.01 | ED213: 292.14697 | EE213: 143.39 | EF213: 264.64481 | EG213: 9.9300003 | EH213: 19.608467 | EI213: 83.57132 | EJ213: 57.584888 | EK213: 0.44999999 | EL213: 25.530001 | EM213: 13.27 | EN213: 61.990002 | EO213: 255.32556 | EP213: 211.55 | EQ213: 84.419998 | ER213: 291.60999 | ES213: 4.5700002 | ET213: 13.31 | EU213: 24.747763 | EV213: 551.71002 | EW213: 1.28 | EX213: 11.77 | EY213: 90.885994 | EZ213: 77.43412 | FA213: 84.220001 | FB213: 593.87 | FC213: 71.744156 | FD213: 5.8800001 | FE213: 22.152483 | FF213: 129.99268 | FG213: 55.630001 | FH213: 189.17 | FI213: 213.38536 | FJ213: 388.3689 | FK213: 98.650002 | FL213: 4.54 | FM213: 88.167 | FN213: 93.275833 | FO213: 12.758 | FP213: 70.400002 | FQ213: 5.96 | FR213: 1.48 | FS213: 169.8 | FT213: 14.53 | FU213: 196.29036 | FV213: 103.73 | FW213: 41.810001 | FX213: 3.8499999 | FY213: 9.4200001 | FZ213: 4.1599998 | GA213: 74.209999 | GB213: 317.32001 | GC213: 52.490002 | GD213: 131.53 | GE213: 195.66 | GF213: 249.64 | GG213: 29.190001 | GH213: 18.24 | GI213: 19.51 | GJ213: 2.97 | GK213: 682.12 | GL213: 7.96 | GM213: 9.8153963 | GN213: 48.419998 | GO213: 179.23 | GP213: 8.8299999 | GQ213: 11.66 | GR213: 201.02 | GS213: 15.64 | GT213: 5.2800002 | GU213: 21.969999 | GV213: 66.940002 | GW213: 142.92 | GX213: 59.650002 | GY213: 242.88058 | GZ213: 217.69681 | HA213: 3.01 | HB213: 15 | HC213: 103.05798 | HD213: 103.8771 | HE213: 4.4029999 | HF213: 9.9499998 | HG213: 85.619644 | HH213: 121.52 | HI213: 4.52 | HJ213: 16.879999 | HK213: 22.290001 | HL213: 6.4099998 | HM213: 737.25928 | HN213: 8.0600004 | HO213: 63.59203 | HP213: 46.98 | HQ213: 9.79 | HR213: 2.01 | HS213: 19.110001 | HT213: 42.189999 | HU213: 8.9099998 | HV213: 95.379997 | HW213: 33.702194 | HX213: 9.3299999 | HY213: 176.19312 | HZ213: 146.87323 | IA213: 309.22 | IB213: 17.879999 | IC213: 194.47 | ID213: 120.57 | IE213: 68.18 | IF213: 52.540001 | IG213: 136.36 | IH213: 0.84799999 | II213: 72.610001 | IJ213: 14.93 | IK213: 3.1500001 | IL213: 8.5299997 | IM213: 303.7561 | IN213: 15.8 | IO213: 8.21 | IP213: 47.32 | IQ213: 25.280001 | IR213: 86.771828 | IS213: 27.407061 | IT213: 111.47313 | IU213: 1.79 | IV213: 19.683123 | IW213: 17.98 | IX213: 58.360001 | IY213: 174.3 | IZ213: 163.39999 | JA213: 85.919998 | JB213: 12.78 | JC213: 81.239998 | JD213: 26.41 | JE213: 147.05858 | JF213: 68.062683 | JG213: 91.220001 | JH213: 0.16 | JI213: 76.919998
A214: 2026-07-28 | B214: 44.274082 | C214: 18.860001 | D214: 15.36 | E214: 88.139999 | F214: 58.700001 | G214: 339.78693 | H214: 36.52269 | I214: 153.11 | J214: 107.27 | K214: 26.01 | L214: 4.8200002 | M214: 82.655396 | N214: 18.139999 | O214: 128.90082 | P214: 72.400002 | Q214: 15.677468 | R214: 123.33681 | S214: 1.11 | T214: 111.79 | U214: 4.25 | V214: 454.62 | W214: 370.10999 | X214: 2.75 | Y214: 45.606071 | Z214: 28.75 | AA214: 230.86 | AB214: 169.71001 | AC214: 6.2399998 | AD214: 27.42 | AE214: 71.925003 | AF214: 8.46 | AG214: 4.21 | AH214: 17.549999 | AI214: 15.924283 | AJ214: 33.93 | AK214: 9.3199997 | AL214: 41.150002 | AM214: 62.302128 | AN214: 21.042318 | AO214: 88.540947 | AP214: 26.290001 | AQ214: 16.65 | AR214: 11.948375 | AS214: 23.040001 | AT214: 12.017202 | AU214: 63.599998 | AV214: 46.535358 | AX214: 10.28 | AY214: 131.7999 | AZ214: 232.50999 | BA214: 13.221633 | BB214: 74.664352 | BC214: 86.959999 | BD214: 28.082916 | BE214: 37.130001 | BF214: 122.28991 | BG214: 13.48 | BH214: 18.565071 | BI214: 24.190001 | BJ214: 258.78519 | BK214: 243.33 | BL214: 167.89999 | BM214: 11.88 | BN214: 113.34401 | BO214: 966.58002 | BP214: 5.2808084 | BQ214: 192.28 | BR214: 5.6599998 | BS214: 8.1400003 | BT214: 115.58 | BU214: 40.725685 | BV214: 50.701199 | BW214: 66.07 | BX214: 109.34 | BY214: 728.79999 | BZ214: 89.370003 | CA214: 195.52 | CB214: 11.55 | CC214: 250.88 | CD214: 392.10001 | CE214: 125.97 | CF214: 19.01247 | CG214: 88.74987 | CH214: 98.889999 | CI214: 9.8800001 | CJ214: 191.86438 | CK214: 29.42 | CL214: 55.970001 | CM214: 2.4100001 | CN214: 28.519043 | CO214: 54.869999 | CP214: 11.36 | CQ214: 128.1136 | CR214: 66.712723 | CS214: 117.08402 | CT214: 25.35 | CU214: 46.66 | CV214: 86.470001 | CW214: 36.049999 | CX214: 14.799714 | CY214: 66.459999 | CZ214: 49.34 | DA214: 3.96 | DB214: 8.4200001 | DC214: 149.98 | DD214: 101.84 | DE214: 74.209999 | DF214: 363.59 | DG214: 369.37 | DH214: 20.940001 | DI214: 90.113647 | DJ214: 332.38422 | DK214: 333.49564 | DL214: 28.1 | DM214: 11.65 | DN214: 142.79361 | DO214: 29.32 | DP214: 92.760002 | DQ214: 285.90179 | DR214: 75.699997 | DS214: 35.869999 | DT214: 225.92931 | DU214: 192.98 | DV214: 4.6100001 | DW214: 1.594 | DX214: 6.8200002 | DY214: 86.300003 | DZ214: 33.880001 | EA214: 45.292404 | EB214: 124.73083 | EC214: 1.89 | ED214: 292.60577 | EE214: 140.28 | EF214: 265.42096 | EG214: 10.11 | EH214: 20.126842 | EI214: 87.746399 | EJ214: 58.786644 | EK214: 0.44999999 | EL214: 25.459999 | EM214: 13.25 | EN214: 62.110001 | EO214: 251.63356 | EP214: 218.24001 | EQ214: 86.82 | ER214: 269.60999 | ES214: 4.5700002 | ET214: 12.37 | EU214: 24.936148 | EV214: 562.75 | EW214: 1.24 | EX214: 11.38 | EY214: 91.71286 | EZ214: 75.25721 | FA214: 86.879997 | FB214: 593.40997 | FC214: 73.643822 | FD214: 5.8800001 | FE214: 22.886272 | FF214: 131.04646 | FG214: 55.805 | FH214: 174.47 | FI214: 210.42168 | FJ214: 392.6109 | FK214: 96.160004 | FL214: 4.6199999 | FM214: 88.613632 | FN214: 91.32988 | FO214: 12.36 | FP214: 72.389999 | FQ214: 5.8200002 | FR214: 1.49 | FS214: 174.53 | FT214: 14.68 | FU214: 196.78979 | FV214: 95.349998 | FW214: 39.580002 | FX214: 3.9400001 | FY214: 9.6499996 | FZ214: 4.1700001 | GA214: 72.989998 | GB214: 319 | GC214: 48.130001 | GD214: 123.53 | GE214: 200.17 | GF214: 251.60001 | GG214: 29.809999 | GH214: 17.389999 | GI214: 17.635 | GJ214: 3 | GK214: 675.48999 | GL214: 7.7199998 | GM214: 9.8153963 | GN214: 49.5 | GO214: 178.44 | GP214: 8.5699997 | GQ214: 11.93 | GR214: 196.16 | GS214: 14.52 | GT214: 4.9899998 | GU214: 21.24 | GV214: 63.889999 | GW214: 143.91 | GX214: 61.400002 | GY214: 250.54576 | GZ214: 217.85629 | HA214: 3.05 | HB214: 15.47 | HC214: 102.51112 | HD214: 105.66189 | HE214: 4.0739999 | HF214: 9.4899998 | HG214: 85.451111 | HH214: 111.3 | HI214: 4.77 | HJ214: 16.74 | HK214: 22.709999 | HL214: 6.2399998 | HM214: 739.02484 | HN214: 7.9499998 | HO214: 63.492668 | HP214: 47.73 | HQ214: 9.6199999 | HR214: 2.03 | HS214: 19.15 | HT214: 43.650002 | HU214: 9.3599997 | HV214: 95.639999 | HW214: 34.4216 | HX214: 9.5200005 | HY214: 181.34338 | HZ214: 150.33012 | IA214: 307.44 | IB214: 18.91 | IC214: 194.33 | ID214: 123.77 | IE214: 70.739998 | IF214: 52.029999 | IG214: 137.3 | IH214: 0.88099998 | II214: 75.199997 | IJ214: 14.06 | IK214: 3.1600001 | IL214: 7.7800002 | IM214: 297.7294 | IN214: 16.389999 | IO214: 8.6000004 | IP214: 48.189999 | IQ214: 25.610001 | IR214: 86.374115 | IS214: 28.548607 | IT214: 112.82988 | IU214: 1.73 | IV214: 19.383532 | IW214: 17.09 | IX214: 57.57 | IY214: 171.09 | IZ214: 167.25999 | JA214: 82.989998 | JB214: 12.71 | JC214: 83.099998 | JD214: 27.4 | JE214: 149.52614 | JF214: 69.056015 | JG214: 91.480003 | JH214: 0.18000001 | JI214: 77.510002
A215: 2026-07-29 | B215: 42.796947 | C215: 17.309999 | D215: 14.84 | E215: 76.519997 | F215: 58.43 | G215: 337.89859 | H215: 36.28801 | I215: 153.00999 | J215: 108 | K215: 26.34 | L215: 4.48 | M215: 79.873055 | N215: 17.540001 | O215: 128.02522 | P215: 70.110001 | Q215: 15.207844 | R215: 115.81956 | S215: 1.0700001 | T215: 107.41 | U215: 4.25 | V215: 429.56 | W215: 360.06027 | X215: 4.5700002 | Y215: 42.651508 | Z215: 26.639999 | AA215: 226.64999 | AB215: 157.97 | AC215: 6.0999999 | AD215: 26.719999 | AE215: 75.154999 | AF215: 8.1199999 | AG215: 3.98 | AH215: 15.49 | AI215: 15.875764 | AJ215: 31.120001 | AK215: 9.6499996 | AL215: 41.369999 | AM215: 60.759998 | AN215: 18.469154 | AO215: 89.233673 | AP215: 26.02 | AQ215: 16.67 | AR215: 11.748735 | AS215: 21.35 | AT215: 11.897329 | AU215: 63.099998 | AV215: 46.535358 | AX215: 8.8999996 | AY215: 126.48691 | AZ215: 229.12 | BA215: 12.784225 | BB215: 77.956482 | BC215: 84.57 | BD215: 27.665106 | BE215: 36.709999 | BF215: 126.6972 | BG215: 12.01 | BH215: 18.097712 | BI215: 24.610001 | BJ215: 264.19977 | BK215: 222.05 | BL215: 160.09 | BM215: 11.61 | BN215: 117.27777 | BO215: 974.03003 | BP215: 5.1644907 | BQ215: 177.45 | BR215: 5.1300001 | BS215: 7.9499998 | BT215: 112.48 | BU215: 40.65588 | BV215: 50.601475 | BW215: 66.32 | BX215: 105.92 | BY215: 679.40997 | BZ215: 86.25 | CA215: 193.53 | CB215: 11.58 | CC215: 264.20001 | CD215: 369.64001 | CE215: 128.67999 | CF215: 19.121395 | CG215: 89.445557 | CH215: 98.480003 | CI215: 9.8500004 | CJ215: 186.89842 | CK215: 28.33 | CL215: 58.169998 | CM215: 2.23 | CN215: 30.100689 | CO215: 56.82 | CP215: 11.46 | CQ215: 127.95499 | CR215: 65.505211 | CS215: 114.95051 | CT215: 25.48 | CU215: 48.130001 | CV215: 85.580002 | CW215: 35.470001 | CX215: 15.116285 | CY215: 57.689999 | CZ215: 46.830002 | DA215: 3.9300001 | DB215: 8.3699999 | DC215: 153.22 | DD215: 101.88 | DE215: 73.57 | DF215: 350.63 | DG215: 371.07999 | DH215: 18.26 | DI215: 89.2155 | DJ215: 335.54218 | DK215: 336.49371 | DL215: 27.219999 | DM215: 10.65 | DN215: 145.04375 | DO215: 25 | DP215: 89.839996 | DQ215: 272.6582 | DR215: 76.040001 | DS215: 36.52 | DT215: 224.82721 | DU215: 194.82001 | DV215: 4.3699999 | DW215: 1.55 | DX215: 6.3600001 | DY215: 81.879997 | DZ215: 31.99 | EA215: 44.215912 | EB215: 119.819 | EC215: 1.9 | ED215: 287.8183 | EE215: 139.42 | EF215: 264.22684 | EG215: 9.8999996 | EH215: 20.326214 | EI215: 88.551605 | EJ215: 59.462009 | EK215: 0.44999999 | EL215: 24.67 | EM215: 13.06 | EN215: 47.380001 | EO215: 258.04962 | EP215: 215.67999 | EQ215: 86.82 | ER215: 252.35001 | ES215: 4.4699998 | ET215: 11.39 | EU215: 24.549463 | EV215: 563.32001 | EW215: 1.2 | EX215: 10.05 | EY215: 92.230904 | EZ215: 70.943169 | FA215: 87.540001 | FB215: 585.60999 | FC215: 73.742249 | FD215: 5.8699999 | FE215: 22.430134 | FF215: 129.59503 | FG215: 54.490002 | FH215: 163.39999 | FI215: 202.01794 | FJ215: 389.80618 | FK215: 93.330002 | FL215: 4.3600001 | FM215: 87.799759 | FN215: 91.150253 | FO215: 12.16 | FP215: 73.629997 | FQ215: 5.79 | FR215: 1.49 | FS215: 173.23 | FT215: 14.04 | FU215: 189.79762 | FV215: 92.669998 | FW215: 36.84 | FX215: 3.6700001 | FY215: 9.5200005 | FZ215: 3.97 | GA215: 69.25 | GB215: 314.14999 | GC215: 43.700001 | GD215: 123 | GE215: 198.44 | GF215: 248.49001 | GG215: 29.950001 | GH215: 17.26 | GI215: 16.18 | GJ215: 2.8299999 | GK215: 661.72998 | GL215: 7.3000002 | GM215: 9.8446388 | GN215: 50.130001 | GO215: 177.99001 | GP215: 7.7800002 | GQ215: 11.69 | GR215: 195.48 | GS215: 13.22 | GT215: 4.9499998 | GU215: 18.24 | GV215: 58.599998 | GW215: 145.33 | GX215: 56.560001 | GY215: 251.47398 | GZ215: 214.53731 | HA215: 2.97 | HB215: 15.4 | HC215: 103.54519 | HD215: 104.16625 | HE215: 3.9200001 | HF215: 9.3699999 | HG215: 87.572525 | HH215: 103.55 | HI215: 4.73 | HJ215: 15.25 | HK215: 23.27 | HL215: 5.6999998 | HM215: 727.65314 | HN215: 7.6700001 | HO215: 65.380562 | HP215: 46.57 | HQ215: 9.3999996 | HR215: 2.0350001 | HS215: 18.860001 | HT215: 44.369999 | HU215: 9.1800003 | HV215: 94.18 | HW215: 33.492367 | HX215: 9.71 | HY215: 180.47838 | HZ215: 149.54311 | IA215: 298.32001 | IB215: 19.09 | IC215: 188.25 | ID215: 119.42 | IE215: 71.199997 | IF215: 51.799999 | IG215: 131.00999 | IH215: 0.79400003 | II215: 75.400002 | IJ215: 13.07 | IK215: 3.1199999 | IL215: 7.7399998 | IM215: 300.16 | IN215: 16.129999 | IO215: 8.6599998 | IP215: 47.220001 | IQ215: 25.639999 | IR215: 83.391243 | IS215: 28.985373 | IT215: 113.94721 | IU215: 1.63 | IV215: 18.215128 | IW215: 15.09 | IX215: 58.650002 | IY215: 166.57001 | IZ215: 166.24001 | JA215: 80.970001 | JB215: 13.06 | JC215: 82.18 | JD215: 27.92 | JE215: 151.15791 | JF215: 68.460022 | JG215: 92.410004 | JH215: 0.16 | JI215: 77.93
A216: 2026-07-30 | B216: 44.8829 | C216: 17.360001 | D216: 15.43 | E216: 90.110001 | F216: 56.189999 | G216: 333.14267 | H216: 35.906647 | I216: 152.08 | J216: 105.61 | K216: 26.549999 | L216: 4.7399998 | M216: 80.101608 | N216: 17.309999 | O216: 126.72179 | P216: 73.25 | Q216: 15.677468 | R216: 106.80683 | S216: 1.01 | T216: 113.75 | U216: 4.3200002 | V216: 485.39001 | W216: 365.4501 | X216: 3.5899999 | Y216: 48.171349 | Z216: 29.450001 | AA216: 235.5 | AB216: 171.02 | AC216: 5.6599998 | AD216: 28.629999 | AE216: 79.910004 | AF216: 8.1899996 | AG216: 4.1300001 | AH216: 17.709999 | AI216: 15.963099 | AJ216: 34.77 | AK216: 9.6599998 | AL216: 41.349998 | AM216: 61.416649 | AN216: 18.717529 | AO216: 86.908081 | AP216: 26.49 | AQ216: 16.99 | AR216: 11.658898 | AS216: 23.610001 | AT216: 12.37682 | AU216: 64.860001 | AV216: 47.480995 | AX216: 11.1 | AY216: 131.65067 | AZ216: 227.07001 | BA216: 12.943283 | BB216: 75.413467 | BC216: 88.230003 | BD216: 27.625315 | BE216: 35.73 | BF216: 125.1253 | BG216: 14.54 | BH216: 18.763947 | BI216: 23.67 | BJ216: 265.97144 | BK216: 249.06 | BL216: 163.58 | BM216: 11.46 | BN216: 118.24135 | BO216: 954.16998 | BP216: 5.2187724 | BQ216: 201.08 | BR216: 5.5599999 | BS216: 8.29 | BT216: 113.56 | BU216: 40.007698 | BV216: 50.052975 | BW216: 61.439999 | BX216: 105.22 | BY216: 716.65997 | BZ216: 88.589996 | CA216: 197.53 | CB216: 12.04 | CC216: 268.56 | CD216: 404.81 | CE216: 127.5 | CF216: 19.566999 | CG216: 91.870529 | CH216: 96.160004 | CI216: 10.38 | CJ216: 191.87431 | CK216: 29.209999 | CL216: 54.290001 | CM216: 2.4300001 | CN216: 29.74482 | CO216: 55.279999 | CP216: 11.42 | CQ216: 125.16948 | CR216: 66.782578 | CS216: 113.1759 | CT216: 27.25 | CU216: 49.029999 | CV216: 83.150002 | CW216: 36.529999 | CX216: 14.700786 | CY216: 59.889999 | CZ216: 50.07 | DA216: 3.8399999 | DB216: 8.7700005 | DC216: 154.25 | DD216: 103.42 | DE216: 76.779999 | DF216: 355.04001 | DG216: 377.16 | DH216: 21.52 | DI216: 88.217567 | DJ216: 333.4635 | DK216: 333.44568 | DL216: 27.889999 | DM216: 11.47 | DN216: 142.42523 | DO216: 27.040001 | DP216: 86.599998 | DQ216: 277.14603 | DR216: 77.300003 | DS216: 35.465 | DT216: 220.16069 | DU216: 205.09 | DV216: 4.5999999 | DW216: 1.575 | DX216: 6.8099999 | DY216: 91.129997 | DZ216: 35.77 | EA216: 47.485256 | EB216: 123.67901 | EC216: 1.83 | ED216: 291.82782 | EE216: 143.88 | EF216: 254.56451 | EG216: 10.14 | EH216: 20.166716 | EI216: 87.965096 | EJ216: 57.46571 | EK216: 0.44400001 | EL216: 24.549999 | EM216: 13.38 | EN216: 48.57 | EO216: 257.50082 | EP216: 210.08 | EQ216: 86.800003 | ER216: 297.72 | ES216: 4.6500001 | ET216: 12.25 | EU216: 24.718019 | EV216: 577.34998 | EW216: 1.25 | EX216: 11.82 | EY216: 92.469994 | EZ216: 74.561401 | FA216: 85.709999 | FB216: 539.03003 | FC216: 66.871979 | FD216: 6 | FE216: 22.578875 | FF216: 129.02837 | FG216: 57.919998 | FH216: 183.3 | FI216: 208.91 | FJ216: 450.25241 | FK216: 97.739998 | FL216: 4.5500002 | FM216: 87.273712 | FN216: 95.561073 | FO216: 13.16 | FP216: 73.169998 | FQ216: 6.0700002 | FR216: 1.54 | FS216: 173.98 | FT216: 14.49 | FU216: 194.82199 | FV216: 96.900002 | FW216: 41.09 | FX216: 3.8199999 | FY216: 9.4200001 | FZ216: 4.1199999 | GA216: 75.059998 | GB216: 325.67999 | GC216: 51.43 | GD216: 122.26 | GE216: 192 | GF216: 248.71001 | GG216: 29.34 | GH216: 18.91 | GI216: 17.98 | GJ216: 2.8399999 | GK216: 683.54999 | GL216: 8.0200005 | GM216: 9.7569141 | GN216: 48.669998 | GO216: 178.03999 | GP216: 8.4700003 | GQ216: 11.91 | GR216: 203.03999 | GS216: 14.86 | GT216: 5.0799999 | GU216: 22.120001 | GV216: 64.68 | GW216: 145.09 | GX216: 58.040001 | GY216: 252.08281 | GZ216: 213.6702 | HA216: 3.04 | HB216: 15.35 | HC216: 105.24541 | HD216: 104.02666 | HE216: 3.0380001 | HF216: 9.9799995 | HG216: 89.723679 | HH216: 114.61 | HI216: 4.6900001 | HJ216: 16.469999 | HK216: 22.77 | HL216: 6.1399999 | HM216: 739.85278 | HN216: 8.0299997 | HO216: 66.304634 | HP216: 45.610001 | HQ216: 10.05 | HR216: 1.98 | HS216: 19.18 | HT216: 43.700001 | HU216: 6.5799999 | HV216: 95.169998 | HW216: 33.772137 | HX216: 9.4799995 | HY216: 172.34531 | HZ216: 152.00378 | IA216: 308.85001 | IB216: 18.280001 | IC216: 190.94 | ID216: 123.56 | IE216: 70.370003 | IF216: 53.389999 | IG216: 137.57001 | IH216: 0.81 | II216: 75.739998 | IJ216: 14.65 | IK216: 3.2 | IL216: 8.1199999 | IM216: 310.50998 | IN216: 16.139999 | IO216: 8.1599998 | IP216: 46.110001 | IQ216: 25.469999 | IR216: 84.942329 | IS216: 27.357426 | IT216: 110.83466 | IU216: 1.76 | IV216: 18.774363 | IW216: 17.82 | IX216: 58.959999 | IY216: 175.73 | IZ216: 163.52 | JA216: 84.910004 | JB216: 12.98 | JC216: 82.589996 | JD216: 26.27 | JE216: 156.21243 | JF216: 68.996414 | JG216: 92.32 | JH216: 0.18000001 | JI216: 76.029999
A217: 2026-07-31 | B217: 45.172337 | C217: 18.700001 | D217: 15.27 | E217: 94.32 | F217: 55.540001 | G217: 308.64383 | H217: 35.945759 | I217: 151.52 | J217: 105.7 | K217: 25.870001 | L217: 4.6399999 | M217: 78.770058 | N217: 17.18 | O217: 126.84119 | P217: 71.510002 | Q217: 15.017995 | R217: 101.85183 | S217: 1.0700001 | T217: 115.18 | U217: 4.23 | V217: 476.14999 | W217: 366.72009 | X217: 3.4400001 | Y217: 49.778393 | Z217: 29.370001 | AA217: 271.57999 | AB217: 180.35001 | AC217: 5.6700001 | AD217: 27.07 | AE217: 80.349998 | AF217: 8.0600004 | AG217: 4.1100001 | AH217: 17.129999 | AI217: 15.982507 | AJ217: 35.169998 | AK217: 9.5200005 | AL217: 42.209999 | AM217: 61.635532 | AN217: 19.025515 | AO217: 85.364281 | AP217: 25.52 | AQ217: 16.950001 | AR217: 11.499187 | AS217: 22.790001 | AT217: 11.647595 | AU217: 65.309998 | AV217: 47.088921 | AX217: 10.52 | AY217: 131.78 | AZ217: 230.03 | BA217: 12.764343 | BB217: 75.206474 | BC217: 86.379997 | BD217: 27.665106 | BE217: 36.400002 | BF217: 124.54828 | BG217: 13.76 | BH217: 18.286644 | BI217: 23.959999 | BJ217: 266.53879 | BK217: 262.89001 | BL217: 146.25999 | BM217: 11.39 | BN217: 119.68175 | BO217: 951.89001 | BP217: 5.1799998 | BQ217: 206.99001 | BR217: 5.4899998 | BS217: 8.5200005 | BT217: 115.99 | BU217: 40.257 | BV217: 50.262402 | BW217: 62.360001 | BX217: 104.43 | BY217: 724 | BZ217: 87.440002 | CA217: 196.16 | CB217: 12.22 | CC217: 267.97 | CD217: 405.37 | CE217: 127.05 | CF217: 19.74 | CG217: 90.906502 | CH217: 96.190002 | CI217: 9.8599997 | CJ217: 187.23613 | CK217: 28.99 | CL217: 54.830002 | CM217: 2.54 | CN217: 29.942526 | CO217: 55.720001 | CP217: 11.77 | CQ217: 124.33681 | CR217: 67.311485 | CS217: 113.66441 | CT217: 26.83 | CU217: 46.419998 | CV217: 81.68 | CW217: 36.650002 | CX217: 14.522715 | CY217: 57.970001 | CZ217: 50.169998 | DA217: 3.9000001 | DB217: 8.4300003 | DC217: 161.95 | DD217: 105.12 | DE217: 74.099998 | DF217: 360.07001 | DG217: 371.54001 | DH217: 21.01 | DI217: 88.676613 | DJ217: 356.41861 | DK217: 355.90125 | DL217: 27.58 | DM217: 11.09 | DN217: 141.29022 | DO217: 27.77 | DP217: 86.559998 | DQ217: 282.12363 | DR217: 76.169998 | DS217: 35.34 | DT217: 222.05707 | DU217: 205.10001 | DV217: 4.6500001 | DW217: 1.8099999 | DX217: 7.0300002 | DY217: 90.199997 | DZ217: 36.439999 | EA217: 47.186234 | EB217: 121.37689 | EC217: 1.89 | ED217: 290.44144 | EE217: 146.66 | EF217: 255.0919 | EG217: 11.15 | EH217: 19.907528 | EI217: 87.070435 | EJ217: 57.346527 | EK217: 0.46000001 | EL217: 24.52 | EM217: 13.28 | EN217: 48.310001 | EO217: 262.9989 | EP217: 207.81 | EQ217: 84.110001 | ER217: 293.01999 | ES217: 4.6199999 | ET217: 12.34 | EU217: 24.608953 | EV217: 573.09998 | EW217: 1.25 | EX217: 11.32 | EY217: 92.480003 | EZ217: 73.845703 | FA217: 85.389999 | FB217: 556.71002 | FC217: 67.255844 | FD217: 5.9899998 | FE217: 21.93433 | FF217: 129.43596 | FG217: 54.82 | FH217: 187.56 | FI217: 210.42 | FJ217: 463.8468 | FK217: 93.279999 | FL217: 4.46 | FM217: 86.271248 | FN217: 93.515335 | FO217: 12.85 | FP217: 71.709999 | FQ217: 5.8299999 | FR217: 1.5 | FS217: 178.5 | FT217: 14.33 | FU217: 200.52562 | FV217: 89.870003 | FW217: 38.830002 | FX217: 3.77 | FY217: 9.3699999 | FZ217: 4.0700002 | GA217: 77.169998 | GB217: 331.82999 | GC217: 52.630001 | GD217: 123.06 | GE217: 190.82001 | GF217: 249.87 | GG217: 27.360001 | GH217: 18.41 | GI217: 18.08 | GJ217: 2.8900001 | GK217: 687.98999 | GL217: 8.1000004 | GM217: 9.7569141 | GN217: 35.599998 | GO217: 140.67 | GP217: 8.6199999 | GQ217: 12.09 | GR217: 198.35001 | GS217: 14.95 | GT217: 5.3200002 | GU217: 20.17 | GV217: 64.949997 | GW217: 145.00999 | GX217: 54.150002 | GY217: 250.58569 | GZ217: 214.50742 | HA217: 3 | HB217: 14.97 | HC217: 104.64885 | HD217: 104.93401 | HE217: 3.4300001 | HF217: 9.8699999 | HG217: 91.180908 | HH217: 117.82 | HI217: 4.6900001 | HJ217: 16.309999 | HK217: 23.26 | HL217: 6.1300001 | HM217: 745.17963 | HN217: 7.8200002 | HO217: 66.85112 | HP217: 44.630001 | HQ217: 9.46 | HR217: 1.97 | HS217: 19.309999 | HT217: 43.84 | HU217: 6.71 | HV217: 95.480003 | HW217: 34.231754 | HX217: 9.4499998 | HY217: 171.71893 | HZ217: 151.79457 | IA217: 311.20999 | IB217: 18.040001 | IC217: 197.35001 | ID217: 121.33 | IE217: 70.360001 | IF217: 52.740002 | IG217: 140.28 | IH217: 0.75599998 | II217: 74.18 | IJ217: 14.95 | IK217: 3.6300001 | IL217: 8.1199999 | IM217: 312.89999 | IN217: 15.78 | IO217: 8.2700005 | IP217: 46.810001 | IQ217: 26.299999 | IR217: 85.956505 | IS217: 25.769186 | IT217: 110.93442 | IU217: 1.84 | IV217: 19.343588 | IW217: 17.66 | IX217: 59.549999 | IY217: 175.35001 | IZ217: 162.55 | JA217: 85.720001 | JB217: 13 | JC217: 81.239998 | JD217: 26.43 | JE217: 152.51109 | JF217: 69.23481 | JG217: 96.07 | JH217: 0.17 | JI217: 77.290001
A218: 2026-08-03 | B218: 44.753151 | C218: 19.219999 | D218: 16.040001 | E218: 110.21 | F218: 55.68 | G218: 303.15857 | H218: 36.170666 | I218: 150.64 | J218: 107.12 | K218: 25.610001 | L218: 4.8400002 | M218: 77.567688 | N218: 17.870001 | O218: 126.07504 | P218: 75.629997 | Q218: 15.68746 | R218: 103.60651 | S218: 1.17 | T218: 117.88 | U218: 4.5999999 | V218: 484.64001 | W218: 380.8797 | X218: 3.6500001 | Y218: 50.746613 | Z218: 30.99 | AA218: 284.01999 | AB218: 184.89 | AC218: 5.9299998 | AD218: 27.27 | AE218: 81.669998 | AF218: 9 | AG218: 3.95 | AH218: 18.450001 | AI218: 15.84665 | AJ218: 36.68 | AK218: 10.15 | AL218: 45.73 | AM218: 62.162842 | AN218: 19.114929 | AO218: 84.364769 | AP218: 25.91 | AQ218: 17.290001 | AR218: 11.369422 | AS218: 23.549999 | AT218: 11.977244 | AU218: 65.470001 | AV218: 47.088921 | AX218: 11.37 | AY218: 133.57001 | AZ218: 235.60001 | BA218: 13.917508 | BB218: 75.640167 | BC218: 89.720001 | BD218: 28.59026 | BE218: 37.52 | BF218: 117.6936 | BG218: 14.65 | BH218: 18.714228 | BI218: 24.559999 | BJ218: 264.92636 | BK218: 288.14001 | BL218: 146.5 | BM218: 11.75 | BN218: 118.37049 | BO218: 954.08002 | BP218: 7.1799998 | BQ218: 218.35001 | BR218: 6.3800001 | BS218: 8.9200001 | BT218: 115.86 | BU218: 40.610001 | BV218: 49.693958 | BW218: 66.129997 | BX218: 105.37 | BY218: 747.66998 | BZ218: 91.589996 | CA218: 200.5 | CB218: 13.04 | CC218: 273.60001 | CD218: 429.01999 | CE218: 127.72 | CF218: 19.76 | CG218: 88.103874 | CH218: 98.139999 | CI218: 10.01 | CJ218: 189.91774 | CK218: 28.559999 | CL218: 55.130001 | CM218: 2.5799999 | CN218: 29.547112 | CO218: 55.369999 | CP218: 12.25 | CQ218: 123.19683 | CR218: 68.209641 | CS218: 106.80527 | CT218: 26.389999 | CU218: 45.139999 | CV218: 83.169998 | CW218: 36.419998 | CX218: 14.275393 | CY218: 60.299999 | CZ218: 50.169998 | DA218: 4.1999998 | DB218: 8.6700001 | DC218: 163.21001 | DD218: 107.04 | DE218: 76.050003 | DF218: 368.92999 | DG218: 371.70999 | DH218: 21.879999 | DI218: 87.499054 | DJ218: 372.22833 | DK218: 373.27008 | DL218: 27.65 | DM218: 11.7 | DN218: 142.27588 | DO218: 30.82 | DP218: 90.339996 | DQ218: 286.20163 | DR218: 76.190002 | DS218: 35.790001 | DT218: 224.69814 | DU218: 198.16 | DV218: 5.0300002 | DW218: 1.8200001 | DX218: 7.3699999 | DY218: 91 | DZ218: 38.849998 | EA218: 48.163048 | EB218: 123.12332 | EC218: 2.01 | ED218: 295.44836 | EE218: 146.39 | EF218: 253.16142 | EG218: 11.9 | EH218: 20.096935 | EI218: 86.344772 | EJ218: 57.823254 | EK218: 0.447 | EL218: 24.620001 | EM218: 13.24 | EN218: 53.049999 | EO218: 257.52078 | EP218: 212.06 | EQ218: 83.849998 | ER218: 294.60999 | ES218: 4.6700001 | ET218: 13.1 | EU218: 25.729345 | EV218: 570.96997 | EW218: 1.3200001 | EX218: 11.75 | EY218: 92.620003 | EZ218: 74.770142 | FA218: 86.68 | FB218: 590.23999 | FC218: 67.186943 | FD218: 5.9499998 | FE218: 21.626932 | FF218: 127.02023 | FG218: 55.139999 | FH218: 193.78 | FI218: 211.23 | FJ218: 486.7337 | FK218: 94.860001 | FL218: 4.54 | FM218: 85.904015 | FN218: 95.17189 | FO218: 12.85 | FP218: 73.330002 | FQ218: 5.9400001 | FR218: 1.5599999 | FS218: 182.92 | FT218: 14.44 | FU218: 206.40904 | FV218: 90.669998 | FW218: 41.220001 | FX218: 3.9400001 | FY218: 9.9200001 | FZ218: 4.3899999 | GA218: 80.139999 | GB218: 347.13 | GC218: 52.599998 | GD218: 125.65 | GE218: 187.41 | GF218: 251.72 | GG218: 27.92 | GH218: 19.07 | GI218: 19.98 | GJ218: 3.05 | GK218: 700.07001 | GL218: 8.7399998 | GM218: 10.117559 | GN218: 36.669998 | GO218: 154.71001 | GP218: 9.6400003 | GQ218: 12.53 | GR218: 202.03999 | GS218: 16.02 | GT218: 5.1500001 | GU218: 21.42 | GV218: 70.43 | GW218: 145.84 | GX218: 57.07 | GY218: 252.42215 | GZ218: 215.93266 | HA218: 3.1800001 | HB218: 16.129999 | HC218: 102.77959 | HD218: 105.56219 | HE218: 2.9300001 | HF218: 10.46 | HG218: 90.288719 | HH218: 119.08 | HI218: 5.04 | HJ218: 18.030001 | HK218: 22.629999 | HL218: 6.0999999 | HM218: 755.79321 | HN218: 8.1300001 | HO218: 65.55941 | HP218: 46 | HQ218: 9.3500004 | HR218: 1.98 | HS218: 19.6 | HT218: 43.98 | HU218: 6.6799998 | HV218: 94.300003 | HW218: 34.931179 | HX218: 9.5299997 | HY218: 176.07379 | HZ218: 155.04227 | IA218: 322.07999 | IB218: 18.299999 | IC218: 196.59 | ID218: 128.39 | IE218: 71.610001 | IF218: 52.75 | IG218: 146.32001 | IH218: 0.80000001 | II218: 77.690002 | IJ218: 15.86 | IK218: 3.3299999 | IL218: 7.3000002 | IM218: 307.54001 | IN218: 15.61 | IO218: 8.6400003 | IP218: 47.360001 | IQ218: 26.09 | IR218: 87.38829 | IS218: 24.915508 | IT218: 110.44559 | IU218: 1.91 | IV218: 20.961376 | IW218: 18.83 | IX218: 58.790001 | IY218: 178.03999 | IZ218: 162.24001 | JA218: 87.010002 | JB218: 12.37 | JC218: 82.089996 | JD218: 26.809999 | JE218: 148.05356 | JF218: 70.367203 | JG218: 98.25 | JH218: 0.17 | JI218: 77.099998
A219: 2026-08-04 | B219: 46.7393 | C219: 20.549999 | D219: 16.559999 | E219: 131.63 | F219: 58.830002 | G219: 309.1134 | H219: 36.248894 | I219: 149.92 | J219: 105.46 | K219: 27.15 | L219: 5.3099999 | M219: 79.36628 | N219: 18.08 | O219: 124.52287 | P219: 78.120003 | Q219: 16.47683 | R219: 106.87662 | S219: 1.1900001 | T219: 123.35 | U219: 4.75 | V219: 518.58002 | W219: 383.40964 | X219: 19.5 | Y219: 55.767372 | Z219: 33.450001 | AA219: 277.42001 | AB219: 190.50999 | AC219: 6.21 | AD219: 28.23 | AE219: 85.665001 | AF219: 9.5100002 | AG219: 4.0900002 | AH219: 21.98 | AI219: 15.943692 | AJ219: 38.700001 | AK219: 10.35 | AL219: 45.959999 | AM219: 62.580711 | AN219: 19.39311 | AO219: 85.453346 | AP219: 28.35 | AQ219: 17.139999 | AR219: 11.089928 | AS219: 23.459999 | AT219: 12.137074 | AU219: 65.889999 | AV219: 46.639977 | AX219: 11.38 | AY219: 136.87 | AZ219: 233.55 | BA219: 14.166035 | BB219: 76.546982 | BC219: 93.089996 | BD219: 29.435831 | BE219: 38.5 | BF219: 117.50457 | BG219: 14.17 | BH219: 19.241249 | BI219: 24.93 | BJ219: 261.40289 | BK219: 323.73001 | BL219: 150.73 | BM219: 12 | BN219: 117.15857 | BO219: 947.84998 | BP219: 7.77 | BQ219: 237.92 | BR219: 6.7800002 | BS219: 9.3900003 | BT219: 121.74 | BU219: 40.509998 | BV219: 50.890678 | BW219: 68.029999 | BX219: 104.42 | BY219: 757.31 | BZ219: 92.769997 | CA219: 202.37 | CB219: 13.14 | CC219: 288.14999 | CD219: 467.26999 | CE219: 127.26 | CF219: 19.459999 | CG219: 87.706337 | CH219: 98.18 | CI219: 10.34 | CJ219: 192.56955 | CK219: 30.02 | CL219: 57.540001 | CM219: 2.5599999 | CN219: 29.982065 | CO219: 56.720001 | CP219: 12.78 | CQ219: 123.18691 | CR219: 69.487015 | CS219: 109.27775 | CT219: 25.42 | CU219: 45.830002 | CV219: 86.43 | CW219: 36.09 | CX219: 14.087428 | CY219: 70.339996 | CZ219: 51.540001 | DA219: 4.1300001 | DB219: 9.0500002 | DC219: 168.28999 | DD219: 109 | DE219: 77.919998 | DF219: 377.28 | DG219: 374.16 | DH219: 22.139999 | DI219: 88.127747 | DJ219: 375.10648 | DK219: 377.40741 | DL219: 27.49 | DM219: 12.25 | DN219: 141.42961 | DO219: 32.16 | DP219: 93.510002 | DQ219: 288.06076 | DR219: 76.690002 | DS219: 36.259998 | DT219: 233.47516 | DU219: 203.00999 | DV219: 5.1199999 | DW219: 1.8099999 | DX219: 7.75 | DY219: 100.86 | DZ219: 41.720001 | EA219: 49.44886 | EB219: 124.5423 | EC219: 2.1500001 | ED219: 300.92404 | EE219: 153.62 | EF219: 253.67886 | EG219: 13.08 | EH219: 20.246466 | EI219: 86.046547 | EJ219: 57.396187 | EK219: 0.46000001 | EL219: 24.5 | EM219: 13.02 | EN219: 54.110001 | EO219: 256.73251 | EP219: 218.08 | EQ219: 88.379997 | ER219: 317.73999 | ES219: 4.8400002 | ET219: 13.96 | EU219: 25.987133 | EV219: 571.09998 | EW219: 1.36 | EX219: 11.75 | EY219: 94.209999 | EZ219: 80.187546 | FA219: 86.199997 | FB219: 587.94 | FC219: 66.999931 | FD219: 5.9699998 | FE219: 22.519377 | FF219: 127.24888 | FG219: 56.990002 | FH219: 218.59 | FI219: 217.03999 | FJ219: 491.88403 | FK219: 97.650002 | FL219: 4.75 | FM219: 86.549156 | FN219: 97.526985 | FO219: 13.5 | FP219: 73.57 | FQ219: 6.3299999 | FR219: 1.58 | FS219: 190.46001 | FT219: 14.33 | FU219: 211.70311 | FV219: 98.440002 | FW219: 43.330002 | FX219: 4.1199999 | FY219: 9.8100004 | FZ219: 4.46 | GA219: 83.919998 | GB219: 366.34 | GC219: 57.84 | GD219: 162.66 | GE219: 186.91 | GF219: 254.14 | GG219: 26.959999 | GH219: 20.68 | GI219: 21.83 | GJ219: 2.8699999 | GK219: 723.84998 | GL219: 9.2299995 | GM219: 10.117559 | GN219: 37 | GO219: 159.97 | GP219: 10.63 | GQ219: 12.72 | GR219: 206.03 | GS219: 17.450001 | GT219: 5.2199998 | GU219: 21.559999 | GV219: 74.480003 | GW219: 147.33 | GX219: 59.119999 | GY219: 250.57571 | GZ219: 217.20844 | HA219: 3.3099999 | HB219: 16.559999 | HC219: 104.37045 | HD219: 106.04079 | HE219: 3.02 | HF219: 11.1 | HG219: 89.059494 | HH219: 129.16 | HI219: 5.79 | HJ219: 18.700001 | HK219: 22.35 | HL219: 6.5100002 | HM219: 769.41937 | HN219: 8.8000002 | HO219: 64.039162 | HP219: 43.25 | HQ219: 9.0500002 | HR219: 1.97 | HS219: 19.950001 | HT219: 44.119999 | HU219: 6.71 | HV219: 92.860001 | HW219: 34.581467 | HX219: 9.6199999 | HY219: 176.19312 | HZ219: 155.38098 | IA219: 327.35001 | IB219: 19.34 | IC219: 194.05 | ID219: 132.62 | IE219: 71.989998 | IF219: 53.459999 | IG219: 154.14 | IH219: 0.833 | II219: 78.879997 | IJ219: 17.275 | IK219: 3.4100001 | IL219: 7.8000002 | IM219: 308.73001 | IN219: 15.69 | IO219: 8.8800001 | IP219: 46.880001 | IQ219: 25.790001 | IR219: 87.885437 | IS219: 25.610363 | IT219: 111.28358 | IU219: 1.98 | IV219: 22.359468 | IW219: 18.879999 | IX219: 58.52 | IY219: 186.89999 | IZ219: 162.10001 | JA219: 91.660004 | JB219: 12.05 | JC219: 84.639999 | JD219: 26.629999 | JE219: 146.93918 | JF219: 71.290993 | JG219: 102.12 | JH219: 0.16 | JI219: 76.040001
